Workbook
Name a: Tabela_de_categorias_e_funcionários[[#Headers],[Aprovações]]
Name a: Tabela_de_categorias_e_funcionários[[#Headers],[Aprovações]]
Name Arcangelo: Tabela_de_categorias_e_funcionários[[#Headers],[Aprovações]]
Name Arcangelo: Tabela_de_categorias_e_funcionários[[#Headers],[Aprovações]]
Name Arcangelo: Tabela_de_categorias_e_funcionários[[#Headers],[Aprovações]]
Name Arcangelo: Tabela_de_categorias_e_funcionários[[#Headers],[Aprovações]]
Name Arcangelo: Tabela_de_categorias_e_funcionários[[#Headers],[Aprovações]]
Name Arcangelo: Tabela_de_categorias_e_funcionários[[#Headers],[Aprovações]]
Name Arcangelo: Tabela_de_categorias_e_funcionários[[#Headers],[Aprovações]]
Name Arcangelo: Tabela_de_categorias_e_funcionários[[#Headers],[Aprovações]]
Name Arcangelo: Tabela_de_categorias_e_funcionários[[#Headers],[Aprovações]]
Name Biopark: Tabela_de_categorias_e_funcionários[[#Headers],[Aprovações]]
Name Categoria_Lista: Configuração!$B$5:$B$11
Name ColumnTitle1: 'Prot. CVEL - Altona'!$B$4
Name ColumnTitle1: 'Prot. CVEL - Bella Citta'!$B$4
Name ColumnTitle1: 'Prot. CVEL - Bresolin'!$B$4
Name ColumnTitle1: 'Prot. TLD - 13 de Abril'!$B$4
Name ColumnTitle1: 'Prot. TLD - Biopark'!$B$4
Name ColumnTitle1: 'Prot. TLD - Carmel'!$B$4
Name ColumnTitle1: 'Prot. TLD - Horizont'!$B$4
Name ColumnTitle1: 'Prot. TLD - Lot. Ludovico'!$B$4
Name ColumnTitle1: 'Prot. TLD - Lot. Vera Cruz'!$B$4
Name ColumnTitle1: 'Prot. TLD - Reserva do Lago'!$B$4
Name ColumnTitle1: 'Prot. TLD - Sede Hélio'!$B$4
Name ColumnTitle1: 'Prot. TLD - Solar de Verona'!$B$4
Name ColumnTitle1: 'Prot. TLD - Sperafico'!$B$4
Name ColumnTitle1: 'Prot. TLD - Villa Bella I'!$B$4
Name ColumnTitle1: 'Prot. TLD - Ducale'!$B$4
Name ColumnTitle2: Tabela_de_categorias_e_funcionários[[#Headers],[Aprovações]]
Name ColumnTitle2: Tabela_de_categorias_e_funcionários[[#Headers],[Aprovações]]
Name ColumnTitle2: Tabela_de_categorias_e_funcionários[[#Headers],[Aprovações]]
Name ColumnTitle2: Tabela_de_categorias_e_funcionários[[#Headers],[Aprovações]]
Name ColumnTitle2: Tabela_de_categorias_e_funcionários[[#Headers],[Aprovações]]
Name ColumnTitle2: Tabela_de_categorias_e_funcionários[[#Headers],[Aprovações]]
Name ColumnTitle2: Tabela_de_categorias_e_funcionários[[#Headers],[Aprovações]]
Name ColumnTitle2: Tabela_de_categorias_e_funcionários[[#Headers],[Aprovações]]
Name ColumnTitle2: Tabela_de_categorias_e_funcionários[[#Headers],[Aprovações]]
Name ColumnTitle2: Tabela_de_categorias_e_funcionários[[#Headers],[Aprovações]]
Name ColumnTitle2: Tabela_de_categorias_e_funcionários[[#Headers],[Aprovações]]
Name ColumnTitle2: Tabela_de_categorias_e_funcionários[[#Headers],[Aprovações]]
Name ColumnTitle2: Tabela_de_categorias_e_funcionários[[#Headers],[Aprovações]]
Name ColumnTitle2: Tabela_de_categorias_e_funcionários[[#Headers],[Aprovações]]
Name ColumnTitle2: Tabela_de_categorias_e_funcionários[[#Headers],[Aprovações]]
Name Funcionário_Lista: Configuração!$C$5:$C$11
Name ll: Tabela_de_categorias_e_funcionários[[#Headers],[Aprovações]]
Name ll: Tabela_de_categorias_e_funcionários[[#Headers],[Aprovações]]
Name SedeHélio: Tabela_de_categorias_e_funcionários[[#Headers],[Aprovações]]
Name SedeHélio: Tabela_de_categorias_e_funcionários[[#Headers],[Aprovações]]
Name SedeHélio: Tabela_de_categorias_e_funcionários[[#Headers],[Aprovações]]
Name SedeHélio: Tabela_de_categorias_e_funcionários[[#Headers],[Aprovações]]
Name SedeHélio: Tabela_de_categorias_e_funcionários[[#Headers],[Aprovações]]
Name SedeHélio: Tabela_de_categorias_e_funcionários[[#Headers],[Aprovações]]
Name SedeHélio: Tabela_de_categorias_e_funcionários[[#Headers],[Aprovações]]
Name SedeHélio: Tabela_de_categorias_e_funcionários[[#Headers],[Aprovações]]
Name Sinalizador_Porcentagem: 'Prot. CVEL - Altona'!$D$2
Name Sinalizador_Porcentagem: 'Prot. CVEL - Bella Citta'!$D$2
Name Sinalizador_Porcentagem: 'Prot. CVEL - Bresolin'!$D$2
Name Sinalizador_Porcentagem: 'Prot. TLD - 13 de Abril'!$D$2
Name Sinalizador_Porcentagem: 'Prot. TLD - Biopark'!$D$2
Name Sinalizador_Porcentagem: 'Prot. TLD - Carmel'!$D$2

Sheet Configuração
B1: Configuração
B4: Aprovações | C4: Nome do Funcionário | D4: Link
B5: Prefeitura Toledo | C5: Lavinia | D5: https://equiplano.toledo.pr.gov.br:7443/contribuinte/#/stpProcessos/pesquisa
B6: Cartório Reg. Imóveis | C6: Lavinia | D6: https://www.cartoriospr.com.br/eandamento/index.php?token=
B7: IAT | C7: Renan | D7: https://www.iat.pr.gov.br/protocolo/info
B8: ANAC | C8: Michael | D8: https://sei.anac.gov.br/sei/controlador_externo.php?acao=usuario_externo_logar&id_orgao_acesso_externo=0
B9: Sanepar | C9: Cristian | D9: https://auth-cs.identidadedigital.pr.gov.br/centralautenticacao/login.html?response_type=code&client_id=9188905e74c28e489b44e954ec0b9bca&redirect_uri=https%3A%2F%2Fwww.eprotocolo.pr.gov.br%2Fspiweb&scope=null&state=1779132779562&urlCert=https://certauth-cs.identidadedigital.pr.gov.br&dnsCidadao=https://cidadao-cs.identidadedigital.pr.gov.br/centralcidadao&loginPadrao=btnCentral&labelCentral=CPF&modulosDeAutenticacao=btnCertificado,btnCpf,btnSanepar,btnCentral&urlLogo=https%3A%2F%2Fwww.eprotocolo.pr.gov.br%2Fspiweb%2Fimages%2Flogo_eprotocolo.png&acesso=2096&tokenFormat=jwt&exibirLinkAutoCadastro=true&exibirLinkRecuperarSenha=true&exibirLinkAutoCadastroCertificado=false&exibirAviso=true&captcha=false
B10: Copel | C10: Renan | D10: https://www.copel.com/site/copel-distribuicao/acompanhamento-de-solicitacoes/?utm_source=home-page&utm_medium=consulta-protocolo&utm_campaign=servicos
B11: IPHAN | C11: Renan | D11: https://saip.iphan.gov.br/
B12: Corpo de Bombeiros | C12: Cristian | D12: https://auth-cs.identidadedigital.pr.gov.br/centralautenticacao/login.html?response_type=code&client_id=9188905e74c28e489b44e954ec0b9bca&redirect_uri=https%3A%2F%2Fwww.eprotocolo.pr.gov.br%2Fspiweb&scope=null&state=1779132779562&urlCert=https://certauth-cs.identidadedigital.pr.gov.br&dnsCidadao=https://cidadao-cs.identidadedigital.pr.gov.br/centralcidadao&loginPadrao=btnCentral&labelCentral=CPF&modulosDeAutenticacao=btnCertificado,btnCpf,btnSanepar,btnCentral&urlLogo=https%3A%2F%2Fwww.eprotocolo.pr.gov.br%2Fspiweb%2Fimages%2Flogo_eprotocolo.png&acesso=2096&tokenFormat=jwt&exibirLinkAutoCadastro=true&exibirLinkRecuperarSenha=true&exibirLinkAutoCadastroCertificado=false&exibirAviso=true&captcha=false
B13: Prefeitura de Cascavel | C13: Michael | D13: https://prefa.cascavel.pr.gov.br/autoatendimento/servicos/consulta-de-processo-digital

Sheet Prot. TLD - Horizont
B1: Controlador De Protocolos Residencial Horizont - Toledo
D2: Sinalizador de Porcentagem Acima/Abaixo:
A4: STATUS | B4: Projeto + Protocolo | C4: Atividade | D4: Aprovações | E4: Atribuída a | F4: Estimado Início | G4: Estimado Término | H4: Duração Estimada (em dias) | I4: Real Início | J4: Real Término | K4: Sinalizador para duração real acima/abaixo (em dias)S | L4: Duração Real (em dias) | M4: Anotações | N4: Situação
A5: APRO | B5: Horizont - 50027/2023 | C5: Alvará de Construção | D5: Prefeitura Toledo | E5: Michael | F5: 45224 | G5: 45338 | H5: =IF(COUNTA('Prot. TLD - Horizont'!$F5,'Prot. TLD - Horizont'!$G5)<>2,"",DAYS360('Prot. TLD - Horizont'!$F5,'Prot. TLD - Horizont'!$G5,FALSE)) -> 111 | I5: 45224 | J5: 45366 | K5: =IFERROR(IF(ControladorDeProjetos5[[#This Row],[Duração Real (em dias)]]=0,"",IF(ABS((ControladorDeProjetos5[[#This Row],[Duração Real (em dias)]]-ControladorDeProjetos5[[#This Row],[Duração Estimada (em dias)]])/ControladorDeProjetos5[[#This Row],[Duração Estimada (em dias)]])>Sinalizador_Porcentagem,1,0)),"") -> 1 | L5: =IF(COUNTA('Prot. TLD - Horizont'!$I5,'Prot. TLD - Horizont'!$J5)<>2,"",DAYS360('Prot. TLD - Horizont'!$I5,'Prot. TLD - Horizont'!$J5,FALSE)) -> 140 | M5: Correções Encaminhada CLOS> | N5: Retirado / Arquitetos
A6: APRO | B6: Horizont - 49428/2023 | C6: Desmembramento | D6: Prefeitura Toledo | E6: Michael | F6: 45215 | G6: 45280 | H6: =IF(COUNTA('Prot. TLD - Horizont'!$F6,'Prot. TLD - Horizont'!$G6)<>2,"",DAYS360('Prot. TLD - Horizont'!$F6,'Prot. TLD - Horizont'!$G6,FALSE)) -> 64 | I6: 45215 | J6: 45280 | K6: =IFERROR(IF(ControladorDeProjetos5[[#This Row],[Duração Real (em dias)]]=0,"",IF(ABS((ControladorDeProjetos5[[#This Row],[Duração Real (em dias)]]-ControladorDeProjetos5[[#This Row],[Duração Estimada (em dias)]])/ControladorDeProjetos5[[#This Row],[Duração Estimada (em dias)]])>Sinalizador_Porcentagem,1,0)),"") -> 0 | L6: =IF(COUNTA('Prot. TLD - Horizont'!$I6,'Prot. TLD - Horizont'!$J6)<>2,"",DAYS360('Prot. TLD - Horizont'!$I6,'Prot. TLD - Horizont'!$J6,FALSE)) -> 64 | M6: 1ºAprovação | N6: Protocolo Finalizado
A7: APRO | B7: Horizont - 1923/2024 | C7: Recarimbo Desmembramento | D7: Prefeitura Toledo | E7: Michael | F7: 45307 | G7: 45314 | H7: =IF(COUNTA('Prot. TLD - Horizont'!$F7,'Prot. TLD - Horizont'!$G7)<>2,"",DAYS360('Prot. TLD - Horizont'!$F7,'Prot. TLD - Horizont'!$G7,FALSE)) -> 7 | I7: 45307 | J7: 45314 | K7: =IFERROR(IF(ControladorDeProjetos5[[#This Row],[Duração Real (em dias)]]=0,"",IF(ABS((ControladorDeProjetos5[[#This Row],[Duração Real (em dias)]]-ControladorDeProjetos5[[#This Row],[Duração Estimada (em dias)]])/ControladorDeProjetos5[[#This Row],[Duração Estimada (em dias)]])>Sinalizador_Porcentagem,1,0)),"") -> 0 | L7: =IF(COUNTA('Prot. TLD - Horizont'!$I7,'Prot. TLD - Horizont'!$J7)<>2,"",DAYS360('Prot. TLD - Horizont'!$I7,'Prot. TLD - Horizont'!$J7,FALSE)) -> 7 | M7: Tainara irá Analisar | N7: Análise Prefeitura
A8: APRO | B8: Horizont - 328.011 06/12/2023 Alteração de Protocolo 329.317 | C8: Desmembramento | D8: Cartório Reg. Imóveis | E8: Michael | F8: 45266 | G8: 44983 | H8: =IF(COUNTA('Prot. TLD - Horizont'!$F8,'Prot. TLD - Horizont'!$G8)<>2,"",DAYS360('Prot. TLD - Horizont'!$F8,'Prot. TLD - Horizont'!$G8,FALSE)) -> -280 | I8: 45266 | J8: 45350 | K8: =IFERROR(IF(ControladorDeProjetos5[[#This Row],[Duração Real (em dias)]]=0,"",IF(ABS((ControladorDeProjetos5[[#This Row],[Duração Real (em dias)]]-ControladorDeProjetos5[[#This Row],[Duração Estimada (em dias)]])/ControladorDeProjetos5[[#This Row],[Duração Estimada (em dias)]])>Sinalizador_Porcentagem,1,0)),"") -> 1 | L8: =IF(COUNTA('Prot. TLD - Horizont'!$I8,'Prot. TLD - Horizont'!$J8)<>2,"",DAYS360('Prot. TLD - Horizont'!$I8,'Prot. TLD - Horizont'!$J8,FALSE)) -> 82 | M8: Aguardando Análise Cartório | N8: Aguardando
A9: APRO | B9: Horizont - IAT 21.594.976-1 | C9: Autorização Ambiental Desmembramento | D9: IAT | E9: Michael | F9: 45308 | G9: 45317 | H9: =IF(COUNTA('Prot. TLD - Horizont'!$F9,'Prot. TLD - Horizont'!$G9)<>2,"",DAYS360('Prot. TLD - Horizont'!$F9,'Prot. TLD - Horizont'!$G9,FALSE)) -> 9 | I9: 45309 | J9: 45320 | K9: =IFERROR(IF(ControladorDeProjetos5[[#This Row],[Duração Real (em dias)]]=0,"",IF(ABS((ControladorDeProjetos5[[#This Row],[Duração Real (em dias)]]-ControladorDeProjetos5[[#This Row],[Duração Estimada (em dias)]])/ControladorDeProjetos5[[#This Row],[Duração Estimada (em dias)]])>Sinalizador_Porcentagem,1,0)),"") -> 1 | L9: =IF(COUNTA('Prot. TLD - Horizont'!$I9,'Prot. TLD - Horizont'!$J9)<>2,"",DAYS360('Prot. TLD - Horizont'!$I9,'Prot. TLD - Horizont'!$J9,FALSE)) -> 11 | M9: Protocolo Aberto | N9: Em Análise Protocolo Criado em 18/01/2024
A10: APRO | B10: Horizont - 21.656.886-9 2024 | C10: LAS - Licenciamento Ambiental Simplificado | D10: IAT | E10: Michael | F10: 45322 | G10: 45366 | H10: =IF(COUNTA('Prot. TLD - Horizont'!$F10,'Prot. TLD - Horizont'!$G10)<>2,"",DAYS360('Prot. TLD - Horizont'!$F10,'Prot. TLD - Horizont'!$G10,FALSE)) -> 45 | I10: 45322 | J10: 45372 | K10: =IFERROR(IF(ControladorDeProjetos5[[#This Row],[Duração Real (em dias)]]=0,"",IF(ABS((ControladorDeProjetos5[[#This Row],[Duração Real (em dias)]]-ControladorDeProjetos5[[#This Row],[Duração Estimada (em dias)]])/ControladorDeProjetos5[[#This Row],[Duração Estimada (em dias)]])>Sinalizador_Porcentagem,1,0)),"") -> 1 | L10: =IF(COUNTA('Prot. TLD - Horizont'!$I10,'Prot. TLD - Horizont'!$J10)<>2,"",DAYS360('Prot. TLD - Horizont'!$I10,'Prot. TLD - Horizont'!$J10,FALSE)) -> 51 | M10: Arquivos Entregues para Análise | N10: Protocolo Aberto
A11: CANC | B11: Horizont - 01450.000692/2024-36 | C11: Anuência IPHAN | D11: IPHAN | E11: Michael | F11: 45317 | G11: 45348 | H11: =IF(COUNTA('Prot. TLD - Horizont'!$F11,'Prot. TLD - Horizont'!$G11)<>2,"",DAYS360('Prot. TLD - Horizont'!$F11,'Prot. TLD - Horizont'!$G11,FALSE)) -> 30 | I11: 45317 | K11: =IFERROR(IF(ControladorDeProjetos5[[#This Row],[Duração Real (em dias)]]=0,"",IF(ABS((ControladorDeProjetos5[[#This Row],[Duração Real (em dias)]]-ControladorDeProjetos5[[#This Row],[Duração Estimada (em dias)]])/ControladorDeProjetos5[[#This Row],[Duração Estimada (em dias)]])>Sinalizador_Porcentagem,1,0)),"") | L11: =IF(COUNTA('Prot. TLD - Horizont'!$I11,'Prot. TLD - Horizont'!$J11)<>2,"",DAYS360('Prot. TLD - Horizont'!$I11,'Prot. TLD - Horizont'!$J11,FALSE)) | M11: Anuência IPHAN Qunato a Implantação do Empreendimento | N11: Protocolo Aberto
A12: CANC | B12: Horizont - 2.2.01.24.0001668600-47 | C12: Aprovação PCIP | D12: Corpo de Bombeiros | E12: Michael | F12: 45321 | G12: 45350 | H12: =IF(COUNTA('Prot. TLD - Horizont'!$F12,'Prot. TLD - Horizont'!$G12)<>2,"",DAYS360('Prot. TLD - Horizont'!$F12,'Prot. TLD - Horizont'!$G12,FALSE)) -> 28 | I12: 45321 | K12: =IFERROR(IF(ControladorDeProjetos5[[#This Row],[Duração Real (em dias)]]=0,"",IF(ABS((ControladorDeProjetos5[[#This Row],[Duração Real (em dias)]]-ControladorDeProjetos5[[#This Row],[Duração Estimada (em dias)]])/ControladorDeProjetos5[[#This Row],[Duração Estimada (em dias)]])>Sinalizador_Porcentagem,1,0)),"") | L12: =IF(COUNTA('Prot. TLD - Horizont'!$I12,'Prot. TLD - Horizont'!$J12)<>2,"",DAYS360('Prot. TLD - Horizont'!$I12,'Prot. TLD - Horizont'!$J12,FALSE)) | M12: Protocolo Aberto Aprovação de Projetos | N12: 1º Análise Realizada Projetista Realizando Alterações
A13: APRO | B13: Horizont - 2597 / 2024 | C13: Notificação Laudo Cautelar | D13: Cartório | E13: Michael | F13: 45324 | G13: 45353 | H13: =IF(COUNTA('Prot. TLD - Horizont'!$F13,'Prot. TLD - Horizont'!$G13)<>2,"",DAYS360('Prot. TLD - Horizont'!$F13,'Prot. TLD - Horizont'!$G13,FALSE)) -> 30 | I13: 45324 | J13: 45351 | K13: =IFERROR(IF(ControladorDeProjetos5[[#This Row],[Duração Real (em dias)]]=0,"",IF(ABS((ControladorDeProjetos5[[#This Row],[Duração Real (em dias)]]-ControladorDeProjetos5[[#This Row],[Duração Estimada (em dias)]])/ControladorDeProjetos5[[#This Row],[Duração Estimada (em dias)]])>Sinalizador_Porcentagem,1,0)),"") -> 1 | L13: =IF(COUNTA('Prot. TLD - Horizont'!$I13,'Prot. TLD - Horizont'!$J13)<>2,"",DAYS360('Prot. TLD - Horizont'!$I13,'Prot. TLD - Horizont'!$J13,FALSE)) -> 27 | M13: Protocolado em Cartório | N13: Protocolo Aberto
A14: APRO | B14: Horizont - 2598 / 2024 | C14: Notificação Laudo Cautelar | D14: Cartório | E14: Michael | F14: 45324 | G14: 45353 | H14: =IF(COUNTA('Prot. TLD - Horizont'!$F14,'Prot. TLD - Horizont'!$G14)<>2,"",DAYS360('Prot. TLD - Horizont'!$F14,'Prot. TLD - Horizont'!$G14,FALSE)) -> 30 | I14: 45324 | J14: 45351 | K14: =IFERROR(IF(ControladorDeProjetos5[[#This Row],[Duração Real (em dias)]]=0,"",IF(ABS((ControladorDeProjetos5[[#This Row],[Duração Real (em dias)]]-ControladorDeProjetos5[[#This Row],[Duração Estimada (em dias)]])/ControladorDeProjetos5[[#This Row],[Duração Estimada (em dias)]])>Sinalizador_Porcentagem,1,0)),"") -> 1 | L14: =IF(COUNTA('Prot. TLD - Horizont'!$I14,'Prot. TLD - Horizont'!$J14)<>2,"",DAYS360('Prot. TLD - Horizont'!$I14,'Prot. TLD - Horizont'!$J14,FALSE)) -> 27 | M14: Protocolado em Cartório | N14: Protocolo Aberto
A15: APRO | B15: Horizont - 2599 / 2024 | C15: Notificação Laudo Cautelar | D15: Cartório | E15: Michael | F15: 45324 | G15: 45353 | H15: =IF(COUNTA('Prot. TLD - Horizont'!$F15,'Prot. TLD - Horizont'!$G15)<>2,"",DAYS360('Prot. TLD - Horizont'!$F15,'Prot. TLD - Horizont'!$G15,FALSE)) -> 30 | I15: 45324 | J15: 45351 | K15: =IFERROR(IF(ControladorDeProjetos5[[#This Row],[Duração Real (em dias)]]=0,"",IF(ABS((ControladorDeProjetos5[[#This Row],[Duração Real (em dias)]]-ControladorDeProjetos5[[#This Row],[Duração Estimada (em dias)]])/ControladorDeProjetos5[[#This Row],[Duração Estimada (em dias)]])>Sinalizador_Porcentagem,1,0)),"") -> 1 | L15: =IF(COUNTA('Prot. TLD - Horizont'!$I15,'Prot. TLD - Horizont'!$J15)<>2,"",DAYS360('Prot. TLD - Horizont'!$I15,'Prot. TLD - Horizont'!$J15,FALSE)) -> 27 | M15: Protocolado em Cartório | N15: Protocolo Aberto
A16: APRO | B16: Horizont - 2600 / 2024 | C16: Notificação Laudo Cautelar | D16: Cartório | E16: Michael | F16: 45324 | G16: 45353 | H16: =IF(COUNTA('Prot. TLD - Horizont'!$F16,'Prot. TLD - Horizont'!$G16)<>2,"",DAYS360('Prot. TLD - Horizont'!$F16,'Prot. TLD - Horizont'!$G16,FALSE)) -> 30 | I16: 45324 | J16: 45351 | K16: =IFERROR(IF(ControladorDeProjetos5[[#This Row],[Duração Real (em dias)]]=0,"",IF(ABS((ControladorDeProjetos5[[#This Row],[Duração Real (em dias)]]-ControladorDeProjetos5[[#This Row],[Duração Estimada (em dias)]])/ControladorDeProjetos5[[#This Row],[Duração Estimada (em dias)]])>Sinalizador_Porcentagem,1,0)),"") -> 1 | L16: =IF(COUNTA('Prot. TLD - Horizont'!$I16,'Prot. TLD - Horizont'!$J16)<>2,"",DAYS360('Prot. TLD - Horizont'!$I16,'Prot. TLD - Horizont'!$J16,FALSE)) -> 27 | M16: Protocolado em Cartório | N16: Protocolo Aberto
A17: CANC | B17: Horizont - 20245957717392 | C17: Ligação Provisória Copel | D17: Copel | E17: Michael | F17: 45355 | G17: 45363 | H17: =IF(COUNTA('Prot. TLD - Horizont'!$F17,'Prot. TLD - Horizont'!$G17)<>2,"",DAYS360('Prot. TLD - Horizont'!$F17,'Prot. TLD - Horizont'!$G17,FALSE)) -> 8 | I17: 45355 | J17: 45369 | K17: =IFERROR(IF(ControladorDeProjetos5[[#This Row],[Duração Real (em dias)]]=0,"",IF(ABS((ControladorDeProjetos5[[#This Row],[Duração Real (em dias)]]-ControladorDeProjetos5[[#This Row],[Duração Estimada (em dias)]])/ControladorDeProjetos5[[#This Row],[Duração Estimada (em dias)]])>Sinalizador_Porcentagem,1,0)),"") -> 1 | L17: =IF(COUNTA('Prot. TLD - Horizont'!$I17,'Prot. TLD - Horizont'!$J17)<>2,"",DAYS360('Prot. TLD - Horizont'!$I17,'Prot. TLD - Horizont'!$J17,FALSE)) -> 14 | M17: Protocolado em Copel | N17: Protocolo Aberto
A18: APRO | B18: Horizont - 330.571 | C18: Incoporação Imobiliária | D18: Cartório Reg. Imóveis | E18: Michael | F18: 45366 | G18: 45379 | H18: =IF(COUNTA('Prot. TLD - Horizont'!$F18,'Prot. TLD - Horizont'!$G18)<>2,"",DAYS360('Prot. TLD - Horizont'!$F18,'Prot. TLD - Horizont'!$G18,FALSE)) -> 13 | I18: 45366 | J18: 45411 | K18: =IFERROR(IF(ControladorDeProjetos5[[#This Row],[Duração Real (em dias)]]=0,"",IF(ABS((ControladorDeProjetos5[[#This Row],[Duração Real (em dias)]]-ControladorDeProjetos5[[#This Row],[Duração Estimada (em dias)]])/ControladorDeProjetos5[[#This Row],[Duração Estimada (em dias)]])>Sinalizador_Porcentagem,1,0)),"") -> 1 | L18: =IF(COUNTA('Prot. TLD - Horizont'!$I18,'Prot. TLD - Horizont'!$J18)<>2,"",DAYS360('Prot. TLD - Horizont'!$I18,'Prot. TLD - Horizont'!$J18,FALSE)) -> 44 | M18: Abertura de Processo | N18: 29/04/2024 - Finalizado
A19: APRO | B19: Horizont - 20246044579234 | C19: Ligação Provisória Copel | D19: Copel | E19: Michael | F19: 45369 | G19: 45376 | H19: =IF(COUNTA('Prot. TLD - Horizont'!$F19,'Prot. TLD - Horizont'!$G19)<>2,"",DAYS360('Prot. TLD - Horizont'!$F19,'Prot. TLD - Horizont'!$G19,FALSE)) -> 7 | I19: 45369 | J19: 45398 | K19: =IFERROR(IF(ControladorDeProjetos5[[#This Row],[Duração Real (em dias)]]=0,"",IF(ABS((ControladorDeProjetos5[[#This Row],[Duração Real (em dias)]]-ControladorDeProjetos5[[#This Row],[Duração Estimada (em dias)]])/ControladorDeProjetos5[[#This Row],[Duração Estimada (em dias)]])>Sinalizador_Porcentagem,1,0)),"") -> 1 | L19: =IF(COUNTA('Prot. TLD - Horizont'!$I19,'Prot. TLD - Horizont'!$J19)<>2,"",DAYS360('Prot. TLD - Horizont'!$I19,'Prot. TLD - Horizont'!$J19,FALSE)) -> 28 | M19: Solicitação Liagção de 80A | N19: 16/04/2024 - Finalizado
A20: ANÁL | B20: 20259368532011 | C20: Ampliação de Carga | D20: Copel | E20: Cristian | F20: 45799 | G20: 45834 | H20: =IF(COUNTA('Prot. TLD - Horizont'!$F20,'Prot. TLD - Horizont'!$G20)<>2,"",DAYS360('Prot. TLD - Horizont'!$F20,'Prot. TLD - Horizont'!$G20,FALSE)) -> 34 | I20: 45799 | K20: =IFERROR(IF(ControladorDeProjetos5[[#This Row],[Duração Real (em dias)]]=0,"",IF(ABS((ControladorDeProjetos5[[#This Row],[Duração Real (em dias)]]-ControladorDeProjetos5[[#This Row],[Duração Estimada (em dias)]])/ControladorDeProjetos5[[#This Row],[Duração Estimada (em dias)]])>Sinalizador_Porcentagem,1,0)),"") | L20: =IF(COUNTA('Prot. TLD - Horizont'!$I20,'Prot. TLD - Horizont'!$J20)<>2,"",DAYS360('Prot. TLD - Horizont'!$I20,'Prot. TLD - Horizont'!$J20,FALSE)) | M20: aprovação de orçamento pelo cliente
A21: ANÁL | B21: Horizont II - 244444482 | C21: Protocolo SANEPAR | D21: Sanepar | E21: Cristian | F21: 45875 | G21: 45917 | H21: =IF(COUNTA('Prot. TLD - Horizont'!$F21,'Prot. TLD - Horizont'!$G21)<>2,"",DAYS360('Prot. TLD - Horizont'!$F21,'Prot. TLD - Horizont'!$G21,FALSE)) -> 41 | I21: 45875 | K21: =IFERROR(IF(ControladorDeProjetos5[[#This Row],[Duração Real (em dias)]]=0,"",IF(ABS((ControladorDeProjetos5[[#This Row],[Duração Real (em dias)]]-ControladorDeProjetos5[[#This Row],[Duração Estimada (em dias)]])/ControladorDeProjetos5[[#This Row],[Duração Estimada (em dias)]])>Sinalizador_Porcentagem,1,0)),"") | L21: =IF(COUNTA('Prot. TLD - Horizont'!$I21,'Prot. TLD - Horizont'!$J21)<>2,"",DAYS360('Prot. TLD - Horizont'!$I21,'Prot. TLD - Horizont'!$J21,FALSE)) | M21: Aprovação de projeto para ligação da servidão | N21: Protocolo aberto
A22: CANC | B22: 41779 / 2025 | C22: Liberação para reforma de calçada e rua | D22: Prefeitura Toledo | E22: Eduarda | F22: 45897 | G22: =F22+15 -> 45912 | H22: =IF(COUNTA('Prot. TLD - Horizont'!$F22,'Prot. TLD - Horizont'!$G22)<>2,"",DAYS360('Prot. TLD - Horizont'!$F22,'Prot. TLD - Horizont'!$G22,FALSE)) -> 14 | I22: 45897 | K22: =IFERROR(IF(ControladorDeProjetos5[[#This Row],[Duração Real (em dias)]]=0,"",IF(ABS((ControladorDeProjetos5[[#This Row],[Duração Real (em dias)]]-ControladorDeProjetos5[[#This Row],[Duração Estimada (em dias)]])/ControladorDeProjetos5[[#This Row],[Duração Estimada (em dias)]])>Sinalizador_Porcentagem,1,0)),"") | L22: =IF(COUNTA('Prot. TLD - Horizont'!$I22,'Prot. TLD - Horizont'!$J22)<>2,"",DAYS360('Prot. TLD - Horizont'!$I22,'Prot. TLD - Horizont'!$J22,FALSE)) | N22: Protocolo Aberto
A23: ANÁL | B23: Sanepar - 20250827115509211 | C23: Ligação definitiva | D23: Sanepar | E23: Cristian | F23: 45896 | G23: =F23+15 -> 45911 | H23: =IF(COUNTA('Prot. TLD - Horizont'!$F23,'Prot. TLD - Horizont'!$G23)<>2,"",DAYS360('Prot. TLD - Horizont'!$F23,'Prot. TLD - Horizont'!$G23,FALSE)) -> 14 | I23: 45896 | K23: =IFERROR(IF(ControladorDeProjetos5[[#This Row],[Duração Real (em dias)]]=0,"",IF(ABS((ControladorDeProjetos5[[#This Row],[Duração Real (em dias)]]-ControladorDeProjetos5[[#This Row],[Duração Estimada (em dias)]])/ControladorDeProjetos5[[#This Row],[Duração Estimada (em dias)]])>Sinalizador_Porcentagem,1,0)),"") | L23: =IF(COUNTA('Prot. TLD - Horizont'!$I23,'Prot. TLD - Horizont'!$J23)<>2,"",DAYS360('Prot. TLD - Horizont'!$I23,'Prot. TLD - Horizont'!$J23,FALSE)) | N23: Protocolo aberto
A24: APRO | B24: Horizont - 50917 / 2025 | C24: Aprovação de drenagem | D24: Prefeitura Toledo | E24: Eduarda | F24: 45947 | G24: 45978 | H24: =G24-F24 -> 31 | I24: 45947 | J24: 46035 | K24: =IFERROR(IF(ControladorDeProjetos5[[#This Row],[Duração Real (em dias)]]=0,"",IF(ABS((ControladorDeProjetos5[[#This Row],[Duração Real (em dias)]]-ControladorDeProjetos5[[#This Row],[Duração Estimada (em dias)]])/ControladorDeProjetos5[[#This Row],[Duração Estimada (em dias)]])>Sinalizador_Porcentagem,1,0)),"") | L24: =J24-I24 -> 88 | M24: Aprovação de projeto para a ligação de drenagem do empreendimento | N24: Protocolo aberto

Sheet Prot. TLD - Ducale
B1: Controlador De Protocolos Residencial Ducale - Toledo
D2: Sinalizador de Porcentagem Acima/Abaixo:
A4: STATUS | B4: Projeto + Protocolo | C4: Atividade | D4: Aprovações | E4: Atribuída a | F4: Estimado Início | G4: Estimado Término | H4: Duração Estimada (em dias) | I4: Real Início | J4: Real Término | K4: Sinalizador para duração real acima/abaixo (em dias)S | L4: Duração Real (em dias) | M4: Anotações | N4: Situação
A5: APRO | B5: Ducale - 50900/2023 | C5: Renovação Alvará | D5: Prefeitura Toledo | E5: Michael | F5: 45223 | G5: 45321 | H5: =IF(COUNTA('Prot. TLD - Ducale'!$F5,'Prot. TLD - Ducale'!$G5)<>2,"",DAYS360('Prot. TLD - Ducale'!$F5,'Prot. TLD - Ducale'!$G5,FALSE)) -> 96 | I5: 45223 | J5: 45320 | K5: =IFERROR(IF(ControladorDeProjetos[[#This Row],[Duração Real (em dias)]]=0,"",IF(ABS((ControladorDeProjetos[[#This Row],[Duração Real (em dias)]]-ControladorDeProjetos[[#This Row],[Duração Estimada (em dias)]])/ControladorDeProjetos[[#This Row],[Duração Estimada (em dias)]])>Sinalizador_Porcentagem,1,0)),"") -> 1 | L5: =IF(COUNTA('Prot. TLD - Ducale'!$I5,'Prot. TLD - Ducale'!$J5)<>2,"",DAYS360('Prot. TLD - Ducale'!$I5,'Prot. TLD - Ducale'!$J5,FALSE)) -> 95 | M5: Pagamento da Taxa Realizado e Encaminhado ao Setor Responsável | N5: Análise Prefeitura
A6: CANC | B6: Duucale - 20240119.1537.02016 | C6: Solicitação Ponto de Esgoto | D6: Sanepar | E6: Michael | F6: 45310 | G6: 45342 | H6: =IF(COUNTA('Prot. TLD - Ducale'!$F6,'Prot. TLD - Ducale'!$G6)<>2,"",DAYS360('Prot. TLD - Ducale'!$F6,'Prot. TLD - Ducale'!$G6,FALSE)) -> 31 | I6: 45310 | K6: =IFERROR(IF(ControladorDeProjetos[[#This Row],[Duração Real (em dias)]]=0,"",IF(ABS((ControladorDeProjetos[[#This Row],[Duração Real (em dias)]]-ControladorDeProjetos[[#This Row],[Duração Estimada (em dias)]])/ControladorDeProjetos[[#This Row],[Duração Estimada (em dias)]])>Sinalizador_Porcentagem,1,0)),"") | L6: =IF(COUNTA('Prot. TLD - Ducale'!$I6,'Prot. TLD - Ducale'!$J6)<>2,"",DAYS360('Prot. TLD - Ducale'!$I6,'Prot. TLD - Ducale'!$J6,FALSE)) | M6: Aguardando Prazo de 30 Dias / Solicitação de execução de mais um ponto de esgoto, conforme projeto aprovado | N6: ProtocoloAberto
A7: CANC | B7: Ducale - 20245757138534 | C7: Atualização Valor Padrão de Entrada | D7: Copel | E7: Michael | F7: 45313 | G7: 45344 | H7: =IF(COUNTA('Prot. TLD - Ducale'!$F7,'Prot. TLD - Ducale'!$G7)<>2,"",DAYS360('Prot. TLD - Ducale'!$F7,'Prot. TLD - Ducale'!$G7,FALSE)) -> 30 | I7: 45313 | K7: =IFERROR(IF(ControladorDeProjetos[[#This Row],[Duração Real (em dias)]]=0,"",IF(ABS((ControladorDeProjetos[[#This Row],[Duração Real (em dias)]]-ControladorDeProjetos[[#This Row],[Duração Estimada (em dias)]])/ControladorDeProjetos[[#This Row],[Duração Estimada (em dias)]])>Sinalizador_Porcentagem,1,0)),"") | L7: =IF(COUNTA('Prot. TLD - Ducale'!$I7,'Prot. TLD - Ducale'!$J7)<>2,"",DAYS360('Prot. TLD - Ducale'!$I7,'Prot. TLD - Ducale'!$J7,FALSE)) | M7: Ataulização de Valor Prolongamento de Rede | N7: Protocolo Aberto
A8: APRO | B8: 2.2.01.25.0001529159-23 | C8: Aprovação corpo de bombeiros - PR | D8: Corpo de Bombeiros | E8: Suellen / Isabelly | F8: 45730 | G8: =ControladorDeProjetos[[#This Row],[Estimado Início]]+60 -> 45790 | H8: =IF(COUNTA('Prot. TLD - Ducale'!$F8,'Prot. TLD - Ducale'!$G8)<>2,"",DAYS360('Prot. TLD - Ducale'!$F8,'Prot. TLD - Ducale'!$G8,FALSE)) -> 59 | I8: 45730 | K8: =IFERROR(IF(ControladorDeProjetos[[#This Row],[Duração Real (em dias)]]=0,"",IF(ABS((ControladorDeProjetos[[#This Row],[Duração Real (em dias)]]-ControladorDeProjetos[[#This Row],[Duração Estimada (em dias)]])/ControladorDeProjetos[[#This Row],[Duração Estimada (em dias)]])>Sinalizador_Porcentagem,1,0)),"") | L8: =IF(COUNTA('Prot. TLD - Ducale'!$I8,'Prot. TLD - Ducale'!$J8)<>2,"",DAYS360('Prot. TLD - Ducale'!$I8,'Prot. TLD - Ducale'!$J8,FALSE)) | M8: Aqua engenharia esta fazendo a aprovação para nós | N8: Protocolo Aberto
A9: ANÁL | B9: 35432 | C9: Ligação definitiva ducale | D9: Copel | E9: Cristian | F9: 45887 | G9: =F9+30 -> 45917 | H9: =IF(COUNTA('Prot. TLD - Ducale'!$F9,'Prot. TLD - Ducale'!$G9)<>2,"",DAYS360('Prot. TLD - Ducale'!$F9,'Prot. TLD - Ducale'!$G9,FALSE)) -> 29 | I9: 45887 | K9: =IFERROR(IF(ControladorDeProjetos[[#This Row],[Duração Real (em dias)]]=0,"",IF(ABS((ControladorDeProjetos[[#This Row],[Duração Real (em dias)]]-ControladorDeProjetos[[#This Row],[Duração Estimada (em dias)]])/ControladorDeProjetos[[#This Row],[Duração Estimada (em dias)]])>Sinalizador_Porcentagem,1,0)),"") | L9: =IF(COUNTA('Prot. TLD - Ducale'!$I9,'Prot. TLD - Ducale'!$J9)<>2,"",DAYS360('Prot. TLD - Ducale'!$I9,'Prot. TLD - Ducale'!$J9,FALSE)) | N9: Protocolo Aberto

Sheet Prot. TLD - Villa Bella I
A1: Controlador De Protocolos Villa Bella I - Toledo | E1: CNPJ PRATI: | F1: 35.538.973/0001-63 | G1: CPF RODRIGO | H1: 078.910.009-64
C2: Sinalizador de Porcentagem Acima/Abaixo: | E2: CNPJ VILLA BELLA: | F2: 57.740.735/0001-79
A4: Status | B4: Projeto + Protocolo | C4: Atividade | D4: Aprovações | E4: Atribuída a | F4: Estimado Início | G4: Estimado Término | H4: Duração Estimada (em dias) | I4: Real Início | J4: Real Término | K4: Sinalizador para duração real acima/abaixo (em dias)S | L4: Duração Real (em dias) | M4: Anotações | N4: Situação
A5: APRO | B5: Ceconi - 40136 /2024 | C5: Solicitação a Comissão de Urbanismo - COMURB - Versão 1 - CNPJ: 04047086924 | D5: Prefeitura Toledo | E5: Michael | F5: 45519 | G5: 45550 | H5: =IF(COUNTA('Prot. TLD - Villa Bella I'!$F5,'Prot. TLD - Villa Bella I'!$G5)<>2,"",DAYS360('Prot. TLD - Villa Bella I'!$F5,'Prot. TLD - Villa Bella I'!$G5,FALSE)) -> 30 | I5: 45519 | J5: 45589 | K5: =IFERROR(IF(ControladorDeProjetos38[[#This Row],[Duração Real (em dias)]]=0,"",IF(ABS((ControladorDeProjetos38[[#This Row],[Duração Real (em dias)]]-ControladorDeProjetos38[[#This Row],[Duração Estimada (em dias)]])/ControladorDeProjetos38[[#This Row],[Duração Estimada (em dias)]])>Sinalizador_Porcentagem,1,0)),"") -> 1 | L5: =ControladorDeProjetos38[[#This Row],[Real Término]]-ControladorDeProjetos38[[#This Row],[Real Início]] -> 70 | M5: Aprovado | N5: Concluido
A6: APRO | B6: Ceconi - 48687/2024 | C6: Desmembramento Imóvel Urbano - CNPJ: 36.686.706/0001-04 | D6: Prefeitura Toledo | E6: Michael | F6: 45567 | G6: 45574 | H6: =ControladorDeProjetos38[[#This Row],[Estimado Término]]-ControladorDeProjetos38[[#This Row],[Estimado Início]] -> 7 | I6: 45567 | J6: 45607 | L6: =ControladorDeProjetos38[[#This Row],[Real Término]]-ControladorDeProjetos38[[#This Row],[Real Início]] -> 40 | M6: Aprovado | N6: Concluido
A7: APRO | B7: Ceconi - 52374 / 2024 | C7: Análise Prévia de Projeto - EIV | D7: Prefeitura Toledo | E7: Michael | F7: 45699 | G7: =ControladorDeProjetos38[[#This Row],[Estimado Início]]+30 -> 45729 | H7: =IF(COUNTA('Prot. TLD - Villa Bella I'!$F7,'Prot. TLD - Villa Bella I'!$G7)<>2,"",DAYS360('Prot. TLD - Villa Bella I'!$F7,'Prot. TLD - Villa Bella I'!$G7,FALSE)) -> 32 | I7: 45716 | J7: 45734 | L7: =ControladorDeProjetos38[[#This Row],[Real Término]]-ControladorDeProjetos38[[#This Row],[Real Início]] -> 18 | M7: Aprovado | N7: Concluido
A8: APRO | B8: Ceconi - 52374 / 2024 | C8: Análise Prévia de Projeto - Versão 1 | D8: Prefeitura Toledo | E8: Michael | F8: 45587 | G8: 45618 | H8: =IF(COUNTA('Prot. TLD - Villa Bella I'!$F8,'Prot. TLD - Villa Bella I'!$G8)<>2,"",DAYS360('Prot. TLD - Villa Bella I'!$F8,'Prot. TLD - Villa Bella I'!$G8,FALSE)) -> 30 | I8: 45587 | J8: 45743 | L8: =ControladorDeProjetos38[[#This Row],[Real Término]]-ControladorDeProjetos38[[#This Row],[Real Início]] -> 156 | M8: Aprovado | N8: Concluido
A9: APRO | B9: Villa Bella - 59.226 / 2024 | C9: Anuência Prévia para IAP - Versão 05 | D9: Prefeitura Toledo | E9: Michael | F9: 45622 | G9: 45652 | H9: =IF(COUNTA('Prot. TLD - Villa Bella I'!$F9,'Prot. TLD - Villa Bella I'!$G9)<>2,"",DAYS360('Prot. TLD - Villa Bella I'!$F9,'Prot. TLD - Villa Bella I'!$G9,FALSE)) -> 30 | I9: 45622 | J9: 45664 | K9: =IFERROR(IF(ControladorDeProjetos38[[#This Row],[Duração Real (em dias)]]=0,"",IF(ABS((ControladorDeProjetos38[[#This Row],[Duração Real (em dias)]]-ControladorDeProjetos38[[#This Row],[Duração Estimada (em dias)]])/ControladorDeProjetos38[[#This Row],[Duração Estimada (em dias)]])>Sinalizador_Porcentagem,1,0)),"") -> 1 | L9: =ControladorDeProjetos38[[#This Row],[Real Término]]-ControladorDeProjetos38[[#This Row],[Real Início]] -> 42 | N9: Concluido
A10: APRO | B10: Villa Bella - 59.238 / 2024 | C10: Solicitação de Unificação de Lotes - Versão 03 CPF: 060.525.989-56 | D10: Prefeitura Toledo | E10: Michael | F10: 45622 | G10: 45652 | H10: =IF(COUNTA('Prot. TLD - Villa Bella I'!$F10,'Prot. TLD - Villa Bella I'!$G10)<>2,"",DAYS360('Prot. TLD - Villa Bella I'!$F10,'Prot. TLD - Villa Bella I'!$G10,FALSE)) -> 30 | I10: 45622 | J10: 45639 | K10: =IFERROR(IF(ControladorDeProjetos38[[#This Row],[Duração Real (em dias)]]=0,"",IF(ABS((ControladorDeProjetos38[[#This Row],[Duração Real (em dias)]]-ControladorDeProjetos38[[#This Row],[Duração Estimada (em dias)]])/ControladorDeProjetos38[[#This Row],[Duração Estimada (em dias)]])>Sinalizador_Porcentagem,1,0)),"") -> 1 | L10: =ControladorDeProjetos38[[#This Row],[Real Término]]-ControladorDeProjetos38[[#This Row],[Real Início]] -> 17 | N10: Concluido
A11: APRO | B11: Villa Bella - 338.851 / 2024 | C11: Escritura Pública de Doação | D11: Cartório Reg. Imóveis | E11: Michael | F11: 45628 | G11: 45659 | H11: =IF(COUNTA('Prot. TLD - Villa Bella I'!$F11,'Prot. TLD - Villa Bella I'!$G11)<>2,"",DAYS360('Prot. TLD - Villa Bella I'!$F11,'Prot. TLD - Villa Bella I'!$G11,FALSE)) -> 30 | I11: 45628 | J11: 45664 | K11: =IFERROR(IF(ControladorDeProjetos38[[#This Row],[Duração Real (em dias)]]=0,"",IF(ABS((ControladorDeProjetos38[[#This Row],[Duração Real (em dias)]]-ControladorDeProjetos38[[#This Row],[Duração Estimada (em dias)]])/ControladorDeProjetos38[[#This Row],[Duração Estimada (em dias)]])>Sinalizador_Porcentagem,1,0)),"") -> 1 | L11: =ControladorDeProjetos38[[#This Row],[Real Término]]-ControladorDeProjetos38[[#This Row],[Real Início]] -> 36 | N11: Concluido
A12: APRO | B12: Villa Bella - 23.177.759-8 | C12: Licenciamento Ambiental | D12: IAT | E12: Michael | F12: 45664 | G12: 45695 | H12: =IF(COUNTA('Prot. TLD - Villa Bella I'!$F12,'Prot. TLD - Villa Bella I'!$G12)<>2,"",DAYS360('Prot. TLD - Villa Bella I'!$F12,'Prot. TLD - Villa Bella I'!$G12,FALSE)) -> 30 | I12: 45664 | K12: =IFERROR(IF(ControladorDeProjetos38[[#This Row],[Duração Real (em dias)]]=0,"",IF(ABS((ControladorDeProjetos38[[#This Row],[Duração Real (em dias)]]-ControladorDeProjetos38[[#This Row],[Duração Estimada (em dias)]])/ControladorDeProjetos38[[#This Row],[Duração Estimada (em dias)]])>Sinalizador_Porcentagem,1,0)),"") -> 1 | L12: =ControladorDeProjetos38[[#This Row],[Real Término]]-ControladorDeProjetos38[[#This Row],[Real Início]] -> -45664 | N12: Encaminhado
A13: APRO | B13: Villa Bella - 073-001351 / 2025 | C13: Aprovação de Projeto Villa Bella I | D13: Prefeitura Toledo | E13: Michael | F13: 45667 | G13: =ControladorDeProjetos38[[#This Row],[Estimado Início]]+30 -> 45697 | H13: =IF(COUNTA('Prot. TLD - Villa Bella I'!$F13,'Prot. TLD - Villa Bella I'!$G13)<>2,"",DAYS360('Prot. TLD - Villa Bella I'!$F13,'Prot. TLD - Villa Bella I'!$G13,FALSE)) -> 29 | I13: 45667 | J13: 45743 | K13: =IFERROR(IF(ControladorDeProjetos38[[#This Row],[Duração Real (em dias)]]=0,"",IF(ABS((ControladorDeProjetos38[[#This Row],[Duração Real (em dias)]]-ControladorDeProjetos38[[#This Row],[Duração Estimada (em dias)]])/ControladorDeProjetos38[[#This Row],[Duração Estimada (em dias)]])>Sinalizador_Porcentagem,1,0)),"") -> 1 | L13: =ControladorDeProjetos38[[#This Row],[Real Término]]-ControladorDeProjetos38[[#This Row],[Real Início]] -> 76 | N13: Concluido
A14: CANC | B14: 20258808646103 | C14: Aprovação de projeto de medição elétrica | D14: Copel | E14: Rodrigo | F14: 45730 | G14: 45762 | H14: =IF(COUNTA('Prot. TLD - Villa Bella I'!$F14,'Prot. TLD - Villa Bella I'!$G14)<>2,"",DAYS360('Prot. TLD - Villa Bella I'!$F14,'Prot. TLD - Villa Bella I'!$G14,FALSE)) -> 31 | I14: 45730 | K14: =IFERROR(IF(ControladorDeProjetos38[[#This Row],[Duração Real (em dias)]]=0,"",IF(ABS((ControladorDeProjetos38[[#This Row],[Duração Real (em dias)]]-ControladorDeProjetos38[[#This Row],[Duração Estimada (em dias)]])/ControladorDeProjetos38[[#This Row],[Duração Estimada (em dias)]])>Sinalizador_Porcentagem,1,0)),"") -> 1 | L14: =ControladorDeProjetos38[[#This Row],[Real Término]]-ControladorDeProjetos38[[#This Row],[Real Início]] -> -45730 | M14: Atendido dia 07/04 | N14: Encaminhado
A15: ANÁL | B15: 23.685.993-2 | C15: Corpo de bombeiros | D15: Corpo de Bombeiros | E15: Rodrigo | F15: 45735 | G15: =ControladorDeProjetos38[[#This Row],[Estimado Início]]+30 -> 45765 | H15: =IF(COUNTA('Prot. TLD - Villa Bella I'!$F15,'Prot. TLD - Villa Bella I'!$G15)<>2,"",DAYS360('Prot. TLD - Villa Bella I'!$F15,'Prot. TLD - Villa Bella I'!$G15,FALSE)) -> 29 | I15: 45735 | K15: =IFERROR(IF(ControladorDeProjetos38[[#This Row],[Duração Real (em dias)]]=0,"",IF(ABS((ControladorDeProjetos38[[#This Row],[Duração Real (em dias)]]-ControladorDeProjetos38[[#This Row],[Duração Estimada (em dias)]])/ControladorDeProjetos38[[#This Row],[Duração Estimada (em dias)]])>Sinalizador_Porcentagem,1,0)),"") -> 1 | L15: =ControladorDeProjetos38[[#This Row],[Real Término]]-ControladorDeProjetos38[[#This Row],[Real Início]] -> -45735 | N15: Encaminhado
A16: CANC | B16: 344147 | C16: Registro da Incorporação de condomínio | D16: Cartório Reg. Imóveis | E16: Rodrigo | F16: 45744 | G16: =ControladorDeProjetos38[[#This Row],[Estimado Início]]+20 -> 45764 | H16: =IF(COUNTA('Prot. TLD - Villa Bella I'!$F16,'Prot. TLD - Villa Bella I'!$G16)<>2,"",DAYS360('Prot. TLD - Villa Bella I'!$F16,'Prot. TLD - Villa Bella I'!$G16,FALSE)) -> 19 | I16: 45744 | K16: =IFERROR(IF(ControladorDeProjetos38[[#This Row],[Duração Real (em dias)]]=0,"",IF(ABS((ControladorDeProjetos38[[#This Row],[Duração Real (em dias)]]-ControladorDeProjetos38[[#This Row],[Duração Estimada (em dias)]])/ControladorDeProjetos38[[#This Row],[Duração Estimada (em dias)]])>Sinalizador_Porcentagem,1,0)),"") -> 1 | L16: =ControladorDeProjetos38[[#This Row],[Real Término]]-ControladorDeProjetos38[[#This Row],[Real Início]] -> -45744 | M16: 18/06 - diligencias / assinaturas | N16: Encaminhado
A17: CANC | B17: 344146 | C17: Escritura Pública de Permuta | D17: Cartório Reg. Imóveis | E17: Rodrigo | F17: 45744 | G17: =ControladorDeProjetos38[[#This Row],[Estimado Início]]+20 -> 45764 | H17: =IF(COUNTA('Prot. TLD - Villa Bella I'!$F17,'Prot. TLD - Villa Bella I'!$G17)<>2,"",DAYS360('Prot. TLD - Villa Bella I'!$F17,'Prot. TLD - Villa Bella I'!$G17,FALSE)) -> 19 | I17: 45744 | K17: =IFERROR(IF(ControladorDeProjetos38[[#This Row],[Duração Real (em dias)]]=0,"",IF(ABS((ControladorDeProjetos38[[#This Row],[Duração Real (em dias)]]-ControladorDeProjetos38[[#This Row],[Duração Estimada (em dias)]])/ControladorDeProjetos38[[#This Row],[Duração Estimada (em dias)]])>Sinalizador_Porcentagem,1,0)),"") -> 1 | L17: =ControladorDeProjetos38[[#This Row],[Real Término]]-ControladorDeProjetos38[[#This Row],[Real Início]] -> -45744 | M17: 18/06 - diligencias / exigencias
A18: CANC | B18: 20259119627173 | C18: Aprovação de projeto de medição elétrica | D18: Copel | E18: Rodrigo | F18: 45771 | G18: 45803 | H18: =IF(COUNTA('Prot. TLD - Villa Bella I'!$F18,'Prot. TLD - Villa Bella I'!$G18)<>2,"",DAYS360('Prot. TLD - Villa Bella I'!$F18,'Prot. TLD - Villa Bella I'!$G18,FALSE)) -> 32 | I18: 45730 | K18: =IFERROR(IF(ControladorDeProjetos38[[#This Row],[Duração Real (em dias)]]=0,"",IF(ABS((ControladorDeProjetos38[[#This Row],[Duração Real (em dias)]]-ControladorDeProjetos38[[#This Row],[Duração Estimada (em dias)]])/ControladorDeProjetos38[[#This Row],[Duração Estimada (em dias)]])>Sinalizador_Porcentagem,1,0)),"") -> 1 | L18: =ControladorDeProjetos38[[#This Row],[Real Término]]-ControladorDeProjetos38[[#This Row],[Real Início]] -> -45730
A19: APRO | B19: 20259333369822 | C19: Aprovação de projeto de medição elétrica | D19: Copel | E19: Rodrigo | F19: 45766 | G19: =ControladorDeProjetos38[[#This Row],[Estimado Início]]+30 -> 45796 | H19: =IF(COUNTA('Prot. TLD - Villa Bella I'!$F19,'Prot. TLD - Villa Bella I'!$G19)<>2,"",DAYS360('Prot. TLD - Villa Bella I'!$F19,'Prot. TLD - Villa Bella I'!$G19,FALSE)) -> 30 | I19: 45730 | J19: 45861 | K19: =IFERROR(IF(ControladorDeProjetos38[[#This Row],[Duração Real (em dias)]]=0,"",IF(ABS((ControladorDeProjetos38[[#This Row],[Duração Real (em dias)]]-ControladorDeProjetos38[[#This Row],[Duração Estimada (em dias)]])/ControladorDeProjetos38[[#This Row],[Duração Estimada (em dias)]])>Sinalizador_Porcentagem,1,0)),"") -> 1 | L19: =ControladorDeProjetos38[[#This Row],[Real Término]]-ControladorDeProjetos38[[#This Row],[Real Início]] -> 131
A20: APRO | B20: 20259459823693 (20259901871675) | C20: Solicitação de Fornecimento de Energia | D20: Copel | E20: Rodrigo | F20: 45811 | G20: 45813 | H20: =IF(COUNTA('Prot. TLD - Villa Bella I'!$F20,'Prot. TLD - Villa Bella I'!$G20)<>2,"",DAYS360('Prot. TLD - Villa Bella I'!$F20,'Prot. TLD - Villa Bella I'!$G20,FALSE)) -> 2 | I20: 45811 | J20: 45861 | K20: =IFERROR(IF(ControladorDeProjetos38[[#This Row],[Duração Real (em dias)]]=0,"",IF(ABS((ControladorDeProjetos38[[#This Row],[Duração Real (em dias)]]-ControladorDeProjetos38[[#This Row],[Duração Estimada (em dias)]])/ControladorDeProjetos38[[#This Row],[Duração Estimada (em dias)]])>Sinalizador_Porcentagem,1,0)),"") -> 1 | L20: =ControladorDeProjetos38[[#This Row],[Real Término]]-ControladorDeProjetos38[[#This Row],[Real Início]] -> 50 | M20: Previsão de entrega do orçamento 03/07/2025
A21: APRO | B21: 345242 | C21: Escritura pública de permuta | D21: Cartório Reg. Imóveis | E21: Rodrigo | F21: 45826 | G21: 45841 | H21: =IF(COUNTA('Prot. TLD - Villa Bella I'!$F21,'Prot. TLD - Villa Bella I'!$G21)<>2,"",DAYS360('Prot. TLD - Villa Bella I'!$F21,'Prot. TLD - Villa Bella I'!$G21,FALSE)) -> 15 | I21: 45826 | J21: 45846 | K21: =IFERROR(IF(ControladorDeProjetos38[[#This Row],[Duração Real (em dias)]]=0,"",IF(ABS((ControladorDeProjetos38[[#This Row],[Duração Real (em dias)]]-ControladorDeProjetos38[[#This Row],[Duração Estimada (em dias)]])/ControladorDeProjetos38[[#This Row],[Duração Estimada (em dias)]])>Sinalizador_Porcentagem,1,0)),"") -> 1 | L21: =ControladorDeProjetos38[[#This Row],[Real Término]]-ControladorDeProjetos38[[#This Row],[Real Início]] -> 20
A22: APRO | B22: 345244 | C22: Registro da Incorporação de condomínio | D22: Cartório Reg. Imóveis | E22: Rodrigo | F22: 45826 | G22: 45841 | H22: =IF(COUNTA('Prot. TLD - Villa Bella I'!$F22,'Prot. TLD - Villa Bella I'!$G22)<>2,"",DAYS360('Prot. TLD - Villa Bella I'!$F22,'Prot. TLD - Villa Bella I'!$G22,FALSE)) -> 15 | I22: 45826 | J22: 45846 | K22: =IFERROR(IF(ControladorDeProjetos38[[#This Row],[Duração Real (em dias)]]=0,"",IF(ABS((ControladorDeProjetos38[[#This Row],[Duração Real (em dias)]]-ControladorDeProjetos38[[#This Row],[Duração Estimada (em dias)]])/ControladorDeProjetos38[[#This Row],[Duração Estimada (em dias)]])>Sinalizador_Porcentagem,1,0)),"") -> 1 | L22: =ControladorDeProjetos38[[#This Row],[Real Término]]-ControladorDeProjetos38[[#This Row],[Real Início]] -> 20
A23: CANC | B23: 24126299 | C23: Corte de árvores isoladas | D23: IAT | E23: Rodrigo | F23: 45854 | G23: =F23+45 -> 45899 | H23: =IF(COUNTA('Prot. TLD - Villa Bella I'!$F23,'Prot. TLD - Villa Bella I'!$G23)<>2,"",DAYS360('Prot. TLD - Villa Bella I'!$F23,'Prot. TLD - Villa Bella I'!$G23,FALSE)) -> 44 | I23: 45854 | K23: =IFERROR(IF(ControladorDeProjetos38[[#This Row],[Duração Real (em dias)]]=0,"",IF(ABS((ControladorDeProjetos38[[#This Row],[Duração Real (em dias)]]-ControladorDeProjetos38[[#This Row],[Duração Estimada (em dias)]])/ControladorDeProjetos38[[#This Row],[Duração Estimada (em dias)]])>Sinalizador_Porcentagem,1,0)),"") | L23: =ControladorDeProjetos38[[#This Row],[Real Término]]-ControladorDeProjetos38[[#This Row],[Real Início]] -> #VALUE!
A24: CANC | B24: 33869 / 2025 | C24: Certidão de uso do solo | D24: Prefeitura Toledo | E24: Eduarda | F24: 45860 | G24: 45876 | H24: =IF(COUNTA('Prot. TLD - Villa Bella I'!$F24,'Prot. TLD - Villa Bella I'!$G24)<>2,"",DAYS360('Prot. TLD - Villa Bella I'!$F24,'Prot. TLD - Villa Bella I'!$G24,FALSE)) -> 15 | I24: 45860 | K24: =IFERROR(IF(ControladorDeProjetos38[[#This Row],[Duração Real (em dias)]]=0,"",IF(ABS((ControladorDeProjetos38[[#This Row],[Duração Real (em dias)]]-ControladorDeProjetos38[[#This Row],[Duração Estimada (em dias)]])/ControladorDeProjetos38[[#This Row],[Duração Estimada (em dias)]])>Sinalizador_Porcentagem,1,0)),"") | L24: =ControladorDeProjetos38[[#This Row],[Real Término]]-ControladorDeProjetos38[[#This Row],[Real Início]] -> #VALUE!
A25: APRO | B25: 24.269.948-3 | C25: Protocolo sanepar | D25: Sanepar | E25: Cristian | F25: 45846 | G25: 45888 | H25: =IF(COUNTA('Prot. TLD - Villa Bella I'!$F25,'Prot. TLD - Villa Bella I'!$G25)<>2,"",DAYS360('Prot. TLD - Villa Bella I'!$F25,'Prot. TLD - Villa Bella I'!$G25,FALSE)) -> 41 | I25: 45846 | K25: =IFERROR(IF(ControladorDeProjetos38[[#This Row],[Duração Real (em dias)]]=0,"",IF(ABS((ControladorDeProjetos38[[#This Row],[Duração Real (em dias)]]-ControladorDeProjetos38[[#This Row],[Duração Estimada (em dias)]])/ControladorDeProjetos38[[#This Row],[Duração Estimada (em dias)]])>Sinalizador_Porcentagem,1,0)),"") | L25: =ControladorDeProjetos38[[#This Row],[Real Término]]-ControladorDeProjetos38[[#This Row],[Real Início]] -> #VALUE!
A26: APRO | B26: 43194 / 2025 | C26: Ativação de cadastro V.B. 1 | D26: Prefeitura Toledo | E26: Eduarda | F26: 45905 | G26: =F26+15 -> 45920 | H26: =IF(COUNTA('Prot. TLD - Villa Bella I'!$F26,'Prot. TLD - Villa Bella I'!$G26)<>2,"",DAYS360('Prot. TLD - Villa Bella I'!$F26,'Prot. TLD - Villa Bella I'!$G26,FALSE)) -> 15 | I26: 45905 | K26: =IFERROR(IF(ControladorDeProjetos38[[#This Row],[Duração Real (em dias)]]=0,"",IF(ABS((ControladorDeProjetos38[[#This Row],[Duração Real (em dias)]]-ControladorDeProjetos38[[#This Row],[Duração Estimada (em dias)]])/ControladorDeProjetos38[[#This Row],[Duração Estimada (em dias)]])>Sinalizador_Porcentagem,1,0)),"")
A27: APRO | B27: 353321 | C27: Requerimento Servidão de Passagem | D27: Cartório Reg. Imóveis | E27: Eduarda | F27: 46057 | G27: 46073 | H27: =IF(COUNTA('Prot. TLD - Villa Bella I'!$F27,'Prot. TLD - Villa Bella I'!$G27)<>2,"",DAYS360('Prot. TLD - Villa Bella I'!$F27,'Prot. TLD - Villa Bella I'!$G27,FALSE)) -> 16 | I27: 46057 | J27: 46099 | K27: =IFERROR(IF(ControladorDeProjetos367314[[#This Row],[Duração Real (em dias)]]=0,"",IF(ABS((ControladorDeProjetos367314[[#This Row],[Duração Real (em dias)]]-ControladorDeProjetos367314[[#This Row],[Duração Estimada (em dias)]])/ControladorDeProjetos367314[[#This Row],[Duração Estimada (em dias)]])>Sinalizador_Porcentagem,1,0)),"") | L27: =IF(COUNTA('Prot. CVEL - Bella Citta'!$I27,'Prot. CVEL - Bella Citta'!$J27)<>2,"",DAYS360('Prot. CVEL - Bella Citta'!$I27,'Prot. CVEL - Bella Citta'!$J27,FALSE))
A28: ANÁL | B28: 10140 / 2026 | C28: Drenagem | D28: Prefeitura Toledo | E28: Lavinia | F28: 46079 | G28: 46107 | H28: =IF(COUNTA('Prot. TLD - Villa Bella I'!$F28,'Prot. TLD - Villa Bella I'!$G28)<>2,"",DAYS360('Prot. TLD - Villa Bella I'!$F28,'Prot. TLD - Villa Bella I'!$G28,FALSE)) -> 30 | I28: 46079 | K28: =IFERROR(IF(ControladorDeProjetos367314[[#This Row],[Duração Real (em dias)]]=0,"",IF(ABS((ControladorDeProjetos367314[[#This Row],[Duração Real (em dias)]]-ControladorDeProjetos367314[[#This Row],[Duração Estimada (em dias)]])/ControladorDeProjetos367314[[#This Row],[Duração Estimada (em dias)]])>Sinalizador_Porcentagem,1,0)),"") | L28: =IF(COUNTA('Prot. CVEL - Bella Citta'!$I28,'Prot. CVEL - Bella Citta'!$J28)<>2,"",DAYS360('Prot. CVEL - Bella Citta'!$I28,'Prot. CVEL - Bella Citta'!$J28,FALSE))

Sheet Prot. TLD - Villa Bella II
A1: Controlador De Protocolos Villa Bella II - Toledo | E1: CNPJ PRATI: | F1: 35.538.973/0001-63 | I1: #VALUE!
C2: Sinalizador de Porcentagem Acima/Abaixo: | E2: CNPJ VILLA BELLA: | F2: 57.740.735/0001-79
E3: CPF RODRIGO | F3: 078.910.009-64
A4: Status | B4: Projeto + Protocolo | C4: Atividade | D4: Aprovações | E4: Atribuída a | F4: Estimado Início | G4: Estimado Término | H4: Duração Estimada (em dias) | I4: Real Início | J4: Real Término | K4: Sinalizador para duração real acima/abaixo (em dias)S | L4: Duração Real (em dias) | M4: Anotações | N4: Situação
A5: APRO | B5: Villa Bella II -073-001667 / 2025 | C5: Aprovação de Projeto Villa Bella II | D5: Prefeitura Toledo | E5: Rodrigo | F5: 45706 | G5: 45767 | H5: =IF(COUNTA('Prot. TLD - Villa Bella I'!$F13,'Prot. TLD - Villa Bella I'!$G13)<>2,"",DAYS360('Prot. TLD - Villa Bella I'!$F13,'Prot. TLD - Villa Bella I'!$G13,FALSE)) -> 29 | K5: =IFERROR(IF(ControladorDeProjetos38[[#This Row],[Duração Real (em dias)]]=0,"",IF(ABS((ControladorDeProjetos38[[#This Row],[Duração Real (em dias)]]-ControladorDeProjetos38[[#This Row],[Duração Estimada (em dias)]])/ControladorDeProjetos38[[#This Row],[Duração Estimada (em dias)]])>Sinalizador_Porcentagem,1,0)),"") -> 1 | L5: =ControladorDeProjetos38[[#This Row],[Real Término]]-ControladorDeProjetos38[[#This Row],[Real Início]] -> 70 | M5: Acompanhar pelo email | N5: Encaminhado
A6: APRO | B6: 18047/2025 | C6: EIV Villa Bella II - CNPJ: 57.740.735/0001-79 | D6: Prefeitura Toledo | E6: Rodrigo | H6: =IF(COUNTA('Prot. TLD - Villa Bella I'!$F14,'Prot. TLD - Villa Bella I'!$G14)<>2,"",DAYS360('Prot. TLD - Villa Bella I'!$F14,'Prot. TLD - Villa Bella I'!$G14,FALSE)) -> 31 | K6: =IFERROR(IF(ControladorDeProjetos38[[#This Row],[Duração Real (em dias)]]=0,"",IF(ABS((ControladorDeProjetos38[[#This Row],[Duração Real (em dias)]]-ControladorDeProjetos38[[#This Row],[Duração Estimada (em dias)]])/ControladorDeProjetos38[[#This Row],[Duração Estimada (em dias)]])>Sinalizador_Porcentagem,1,0)),"") -> 1 | L6: =ControladorDeProjetos38[[#This Row],[Real Término]]-ControladorDeProjetos38[[#This Row],[Real Início]] -> 40 | M6: Aprovação de projetos
A7: APRO | B7: 346063 | C7: Escritura Pública de Permuta | D7: Cartório Reg. Imóveis | E7: Eduarda | F7: 45849 | G7: 45863 | H7: =G7-F7 -> 14 | I7: 45849 | K7: =IFERROR(IF(ControladorDeProjetos38[[#This Row],[Duração Real (em dias)]]=0,"",IF(ABS((ControladorDeProjetos38[[#This Row],[Duração Real (em dias)]]-ControladorDeProjetos38[[#This Row],[Duração Estimada (em dias)]])/ControladorDeProjetos38[[#This Row],[Duração Estimada (em dias)]])>Sinalizador_Porcentagem,1,0)),"") -> 1 | M7: Enca | N7: Encaminhado
A8: APRO | B8: 346065 | C8: Incorporação de Condomínio | D8: Cartório Reg. Imóveis | E8: Eduarda | F8: 45849 | G8: 45863 | H8: =G8-F8 -> 14 | I8: 45849 | K8: =IFERROR(IF(ControladorDeProjetos38[[#This Row],[Duração Real (em dias)]]=0,"",IF(ABS((ControladorDeProjetos38[[#This Row],[Duração Real (em dias)]]-ControladorDeProjetos38[[#This Row],[Duração Estimada (em dias)]])/ControladorDeProjetos38[[#This Row],[Duração Estimada (em dias)]])>Sinalizador_Porcentagem,1,0)),"") -> 1 | N8: Encaminhado
A9: APRO | B9: 309448 | C9: certidão vintenaria | D9: Cartório Reg. Imóveis | E9: Rodrigo | F9: 45875 | G9: 45882 | H9: =IF(COUNTA('Prot. TLD - Villa Bella II'!$F9,'Prot. TLD - Villa Bella II'!$G9)<>2,"",DAYS360('Prot. TLD - Villa Bella II'!$F9,'Prot. TLD - Villa Bella II'!$G9,FALSE)) -> 7 | I9: 45875 | K9: =IFERROR(IF(ControladorDeProjetos369[[#This Row],[Duração Real (em dias)]]=0,"",IF(ABS((ControladorDeProjetos369[[#This Row],[Duração Real (em dias)]]-ControladorDeProjetos369[[#This Row],[Duração Estimada (em dias)]])/ControladorDeProjetos369[[#This Row],[Duração Estimada (em dias)]])>Sinalizador_Porcentagem,1,0)),"") -> 0 | L9: =ControladorDeProjetos369[[#This Row],[Real Término]]-ControladorDeProjetos369[[#This Row],[Real Início]] -> 7
A10: APRO | B10: 24.301.139-6 | C10: Carta de viabilidade | D10: Sanepar | E10: Cristian | F10: 45849 | G10: 45891 | H10: =IF(COUNTA('Prot. TLD - Villa Bella II'!$F10,'Prot. TLD - Villa Bella II'!$G10)<>2,"",DAYS360('Prot. TLD - Villa Bella II'!$F10,'Prot. TLD - Villa Bella II'!$G10,FALSE)) -> 41 | I10: 45849 | J10: 45903 | K10: =IFERROR(IF(ControladorDeProjetos38[[#This Row],[Duração Real (em dias)]]=0,"",IF(ABS((ControladorDeProjetos38[[#This Row],[Duração Real (em dias)]]-ControladorDeProjetos38[[#This Row],[Duração Estimada (em dias)]])/ControladorDeProjetos38[[#This Row],[Duração Estimada (em dias)]])>Sinalizador_Porcentagem,1,0)),"") -> 1 | M10: Pedido carta de viabilidade | N10: Aprovado
A11: APRO | B11: 43196 / 2025 | C11: Ativação de cadastro V.B. 2 | D11: Prefeitura Toledo | E11: Rodrigo | F11: 45905 | G11: =F11+15 -> 45920 | H11: 15 | I11: 45905 | K11: =IFERROR(IF(ControladorDeProjetos38[[#This Row],[Duração Real (em dias)]]=0,"",IF(ABS((ControladorDeProjetos38[[#This Row],[Duração Real (em dias)]]-ControladorDeProjetos38[[#This Row],[Duração Estimada (em dias)]])/ControladorDeProjetos38[[#This Row],[Duração Estimada (em dias)]])>Sinalizador_Porcentagem,1,0)),"") -> 1 | N11: Protocolado

Sheet Prot. TLD - Carmel
A1: Controlador De Protocolos Empreendimento Carmel - Toledo
C2: Sinalizador de Porcentagem Acima/Abaixo: | I2: CNPJ CARMEL | J2: 59.387.026/0001-87
A4: Status | B4: Projeto + Protocolo | C4: Atividade | D4: Aprovações | E4: Atribuída a | F4: Estimado Início | G4: Estimado Término | H4: Duração Estimada (em dias) | I4: Real Início | J4: Real Término | K4: Sinalizador para duração real acima/abaixo (em dias)S | L4: Duração Real (em dias) | M4: Anotações | N4: Situação
A5: CANC | B5: Carmel - 339.058 / 2024 | C5: Escritura Pública de Compra e Venda | D5: Cartório Reg. Imóveis | E5: Michael | F5: 45632 | G5: 45639 | H5: =IF(COUNTA('Prot. TLD - Carmel'!$F5,'Prot. TLD - Carmel'!$G5)<>2,"",DAYS360('Prot. TLD - Carmel'!$F5,'Prot. TLD - Carmel'!$G5,FALSE)) -> 7 | I5: 45632 | J5: 45667 | K5: =IFERROR(IF(ControladorDeProjetos369[[#This Row],[Duração Real (em dias)]]=0,"",IF(ABS((ControladorDeProjetos369[[#This Row],[Duração Real (em dias)]]-ControladorDeProjetos369[[#This Row],[Duração Estimada (em dias)]])/ControladorDeProjetos369[[#This Row],[Duração Estimada (em dias)]])>Sinalizador_Porcentagem,1,0)),"") -> 1 | L5: =ControladorDeProjetos369[[#This Row],[Real Término]]-ControladorDeProjetos369[[#This Row],[Real Início]] -> 35 | N5: Cancelado
A6: CANC | B6: Carmel - 339.059 / 2024 | C6: Requerimento de Averbação da Unificação | D6: Cartório Reg. Imóveis | E6: Michael | F6: 45632 | G6: 45646 | H6: =IF(COUNTA('Prot. TLD - Carmel'!$F6,'Prot. TLD - Carmel'!$G6)<>2,"",DAYS360('Prot. TLD - Carmel'!$F6,'Prot. TLD - Carmel'!$G6,FALSE)) -> 14 | I6: 45632 | J6: 45667 | L6: =ControladorDeProjetos369[[#This Row],[Real Término]]-ControladorDeProjetos369[[#This Row],[Real Início]] -> 35 | N6: Cancelado
A7: APRO | B7: Carmel - 340.165 / 2025 | C7: 339.058 / pt2 | D7: Cartório Reg. Imóveis | E7: Michael | F7: 45671 | G7: 45678 | H7: =IF(COUNTA('Prot. TLD - Carmel'!$F7,'Prot. TLD - Carmel'!$G7)<>2,"",DAYS360('Prot. TLD - Carmel'!$F7,'Prot. TLD - Carmel'!$G7,FALSE)) -> 7 | I7: 45671 | J7: 45678 | L7: =ControladorDeProjetos369[[#This Row],[Real Término]]-ControladorDeProjetos369[[#This Row],[Real Início]] -> 7 | N7: Finalizado
A8: APRO | B8: Carmel - 340.166 / 2025 | C8: pt2 | D8: Cartório Reg. Imóveis | E8: Michael | F8: 45671 | G8: 45685 | H8: =IF(COUNTA('Prot. TLD - Carmel'!$F8,'Prot. TLD - Carmel'!$G8)<>2,"",DAYS360('Prot. TLD - Carmel'!$F8,'Prot. TLD - Carmel'!$G8,FALSE)) -> 14 | I8: 45671 | J8: 45678 | L8: =ControladorDeProjetos369[[#This Row],[Real Término]]-ControladorDeProjetos369[[#This Row],[Real Início]] -> 7 | N8: Finalizado
A9: APRO | B9: Carmel - 340.167 / 2025 | C9: 339.059 / pt2 | D9: Cartório Reg. Imóveis | E9: Michael | F9: 45671 | G9: 45678 | H9: =IF(COUNTA('Prot. TLD - Carmel'!$F9,'Prot. TLD - Carmel'!$G9)<>2,"",DAYS360('Prot. TLD - Carmel'!$F9,'Prot. TLD - Carmel'!$G9,FALSE)) -> 7 | I9: 45671 | J9: 45678 | L9: =ControladorDeProjetos369[[#This Row],[Real Término]]-ControladorDeProjetos369[[#This Row],[Real Início]] -> 7 | N9: Finalizado
A10: APRO | B10: Carmel 20258398330847 | C10: Medição | D10: Copel | E10: Michael | F10: 45680 | G10: 45711 | H10: =IF(COUNTA('Prot. TLD - Carmel'!$F10,'Prot. TLD - Carmel'!$G10)<>2,"",DAYS360('Prot. TLD - Carmel'!$F10,'Prot. TLD - Carmel'!$G10,FALSE)) -> 30 | I10: 45680 | J10: 45685 | L10: =ControladorDeProjetos369[[#This Row],[Real Término]]-ControladorDeProjetos369[[#This Row],[Real Início]] -> 5 | N10: Finalizado
A11: APRO | B11: 20258677359583 | C11: Solicitação carta de viabilidade | D11: Copel | E11: Rodrigo | F11: 45715 | G11: 45747 | H11: =IF(COUNTA('Prot. TLD - Carmel'!$F11,'Prot. TLD - Carmel'!$G11)<>2,"",DAYS360('Prot. TLD - Carmel'!$F11,'Prot. TLD - Carmel'!$G11,FALSE)) -> 34 | I11: 45715 | J11: 45719 | K11: =IFERROR(IF(ControladorDeProjetos369[[#This Row],[Duração Real (em dias)]]=0,"",IF(ABS((ControladorDeProjetos369[[#This Row],[Duração Real (em dias)]]-ControladorDeProjetos369[[#This Row],[Duração Estimada (em dias)]])/ControladorDeProjetos369[[#This Row],[Duração Estimada (em dias)]])>Sinalizador_Porcentagem,1,0)),"") -> 1 | L11: =ControladorDeProjetos369[[#This Row],[Real Término]]-ControladorDeProjetos369[[#This Row],[Real Início]] -> 4 | N11: Finalizado
A12: CANC | B12: 089-001941-2025 | C12: Análise prévia urbana (EIV) | D12: Prefeitura Toledo | E12: Rodrigo | F12: 45744 | G12: =ControladorDeProjetos369[[#This Row],[Estimado Início]]+30 -> 45774 | H12: =IF(COUNTA('Prot. TLD - Carmel'!$F12,'Prot. TLD - Carmel'!$G12)<>2,"",DAYS360('Prot. TLD - Carmel'!$F12,'Prot. TLD - Carmel'!$G12,FALSE)) -> 29 | I12: 45747 | J12: 45761 | K12: =IFERROR(IF(ControladorDeProjetos369[[#This Row],[Duração Real (em dias)]]=0,"",IF(ABS((ControladorDeProjetos369[[#This Row],[Duração Real (em dias)]]-ControladorDeProjetos369[[#This Row],[Duração Estimada (em dias)]])/ControladorDeProjetos369[[#This Row],[Duração Estimada (em dias)]])>Sinalizador_Porcentagem,1,0)),"") -> 1 | L12: =ControladorDeProjetos369[[#This Row],[Real Término]]-ControladorDeProjetos369[[#This Row],[Real Início]] -> 14 | N12: Finalizado
A13: APRO | B13: 18.624 / 2025 | C13: Análise EIV- 59.387.026/0001-87 | D13: Prefeitura Toledo | E13: Eduarda | F13: 45763 | G13: 45793 | H13: =IF(COUNTA('Prot. TLD - Carmel'!$F13,'Prot. TLD - Carmel'!$G13)<>2,"",DAYS360('Prot. TLD - Carmel'!$F13,'Prot. TLD - Carmel'!$G13,FALSE)) -> 30 | I13: 45763 | J13: 46083 | K13: =IFERROR(IF(ControladorDeProjetos369[[#This Row],[Duração Real (em dias)]]=0,"",IF(ABS((ControladorDeProjetos369[[#This Row],[Duração Real (em dias)]]-ControladorDeProjetos369[[#This Row],[Duração Estimada (em dias)]])/ControladorDeProjetos369[[#This Row],[Duração Estimada (em dias)]])>Sinalizador_Porcentagem,1,0)),"") -> 1 | L13: =ControladorDeProjetos369[[#This Row],[Real Término]]-ControladorDeProjetos369[[#This Row],[Real Início]] -> 320
A14: APRO | B14: 073-002070-2025 | C14: Análise projeto arquitetonico | D14: Prefeitura Toledo | E14: Rodrigo | F14: 45756 | G14: =ControladorDeProjetos369[[#This Row],[Estimado Início]]+30 -> 45786 | H14: =IF(COUNTA('Prot. TLD - Carmel'!$F14,'Prot. TLD - Carmel'!$G14)<>2,"",DAYS360('Prot. TLD - Carmel'!$F14,'Prot. TLD - Carmel'!$G14,FALSE)) -> 30 | I14: 45756 | K14: =IFERROR(IF(ControladorDeProjetos369[[#This Row],[Duração Real (em dias)]]=0,"",IF(ABS((ControladorDeProjetos369[[#This Row],[Duração Real (em dias)]]-ControladorDeProjetos369[[#This Row],[Duração Estimada (em dias)]])/ControladorDeProjetos369[[#This Row],[Duração Estimada (em dias)]])>Sinalizador_Porcentagem,1,0)),"") -> 1 | L14: =ControladorDeProjetos369[[#This Row],[Real Término]]-ControladorDeProjetos369[[#This Row],[Real Início]] -> -45756
A15: CANC | B15: 345360 | C15: Registro da Incorporação de condomInio | D15: Cartório Reg. Imóveis | E15: Rodrigo | F15: 45828 | G15: =ControladorDeProjetos369[[#This Row],[Estimado Início]]+30 -> 45858 | H15: =IF(COUNTA('Prot. TLD - Carmel'!$F15,'Prot. TLD - Carmel'!$G15)<>2,"",DAYS360('Prot. TLD - Carmel'!$F15,'Prot. TLD - Carmel'!$G15,FALSE)) -> 30 | I15: 45828 | J15: 45853 | K15: =IFERROR(IF(ControladorDeProjetos369[[#This Row],[Duração Real (em dias)]]=0,"",IF(ABS((ControladorDeProjetos369[[#This Row],[Duração Real (em dias)]]-ControladorDeProjetos369[[#This Row],[Duração Estimada (em dias)]])/ControladorDeProjetos369[[#This Row],[Duração Estimada (em dias)]])>Sinalizador_Porcentagem,1,0)),"") -> 1 | L15: =ControladorDeProjetos369[[#This Row],[Real Término]]-ControladorDeProjetos369[[#This Row],[Real Início]] -> 25 | N15: Finalizado
A16: APRO | B16: 31.947 / 2025 | C16: LICENÇA PARA DEMOLIÇÃO | D16: Prefeitura Toledo | E16: Rodrigo | F16: 45841 | G16: 45872 | H16: =IF(COUNTA('Prot. TLD - Carmel'!$F16,'Prot. TLD - Carmel'!$G16)<>2,"",DAYS360('Prot. TLD - Carmel'!$F16,'Prot. TLD - Carmel'!$G16,FALSE)) -> 30 | I16: 45750 | K16: =IFERROR(IF(ControladorDeProjetos369[[#This Row],[Duração Real (em dias)]]=0,"",IF(ABS((ControladorDeProjetos369[[#This Row],[Duração Real (em dias)]]-ControladorDeProjetos369[[#This Row],[Duração Estimada (em dias)]])/ControladorDeProjetos369[[#This Row],[Duração Estimada (em dias)]])>Sinalizador_Porcentagem,1,0)),"") -> 1 | L16: =ControladorDeProjetos369[[#This Row],[Real Término]]-ControladorDeProjetos369[[#This Row],[Real Início]] -> -45750
A17: APRO | B17: 38.321 / 2025 | C17: Anuência Prévia | D17: Prefeitura Toledo | E17: Eduarda | F17: 45877 | G17: 45908 | H17: =IF(COUNTA('Prot. TLD - Carmel'!$F17,'Prot. TLD - Carmel'!$G17)<>2,"",DAYS360('Prot. TLD - Carmel'!$F17,'Prot. TLD - Carmel'!$G17,FALSE)) -> 30 | I17: 45877 | K17: =IFERROR(IF(ControladorDeProjetos369[[#This Row],[Duração Real (em dias)]]=0,"",IF(ABS((ControladorDeProjetos369[[#This Row],[Duração Real (em dias)]]-ControladorDeProjetos369[[#This Row],[Duração Estimada (em dias)]])/ControladorDeProjetos369[[#This Row],[Duração Estimada (em dias)]])>Sinalizador_Porcentagem,1,0)),"") -> 1 | L17: =ControladorDeProjetos369[[#This Row],[Real Término]]-ControladorDeProjetos369[[#This Row],[Real Início]] -> -45877
A18: CANC | B18: 347232 | C18: Registro da Incorporação de condomInio | D18: Cartório Reg. Imóveis | E18: Eduarda | F18: 45828 | G18: 45898 | H18: =IF(COUNTA('Prot. TLD - Carmel'!$F18,'Prot. TLD - Carmel'!$G18)<>2,"",DAYS360('Prot. TLD - Carmel'!$F18,'Prot. TLD - Carmel'!$G18,FALSE)) -> 69 | I18: 45828 | K18: =IFERROR(IF(ControladorDeProjetos369[[#This Row],[Duração Real (em dias)]]=0,"",IF(ABS((ControladorDeProjetos369[[#This Row],[Duração Real (em dias)]]-ControladorDeProjetos369[[#This Row],[Duração Estimada (em dias)]])/ControladorDeProjetos369[[#This Row],[Duração Estimada (em dias)]])>Sinalizador_Porcentagem,1,0)),"") | N18: retirado
A19: CANC | B19: 348691 | C19: Registro da Incorporação de condomInio | D19: Cartório Reg. Imóveis | E19: Eduarda | F19: 45929 | G19: 45943 | H19: =IF(COUNTA('Prot. TLD - Carmel'!$F19,'Prot. TLD - Carmel'!$G19)<>2,"",DAYS360('Prot. TLD - Carmel'!$F19,'Prot. TLD - Carmel'!$G19,FALSE)) -> 14 | I19: 45959
A20: ANÁL | B20: 25.453.390-4. | D20: Sanepar | E20: Cristian | F20: 46073 | G20: 46101 | H20: =IF(COUNTA('Prot. TLD - Carmel'!$F20,'Prot. TLD - Carmel'!$G20)<>2,"",DAYS360('Prot. TLD - Carmel'!$F20,'Prot. TLD - Carmel'!$G20,FALSE)) -> 30 | I20: 46073 | K20: =IFERROR(IF(ControladorDeProjetos369[[#This Row],[Duração Real (em dias)]]=0,"",IF(ABS((ControladorDeProjetos369[[#This Row],[Duração Real (em dias)]]-ControladorDeProjetos369[[#This Row],[Duração Estimada (em dias)]])/ControladorDeProjetos369[[#This Row],[Duração Estimada (em dias)]])>Sinalizador_Porcentagem,1,0)),"")
A21: ANÁL | B21: 20264129470402 | C21: Pedido de ligação provisória do carmel | D21: Copel | E21: Cristian | F21: 46136 | G21: 46166 | H21: =IF(COUNTA('Prot. TLD - Carmel'!$F21,'Prot. TLD - Carmel'!$G21)<>2,"",DAYS360('Prot. TLD - Carmel'!$F21,'Prot. TLD - Carmel'!$G21,FALSE)) -> 30 | I21: 46136 | K21: =IFERROR(IF(ControladorDeProjetos369[[#This Row],[Duração Real (em dias)]]=0,"",IF(ABS((ControladorDeProjetos369[[#This Row],[Duração Real (em dias)]]-ControladorDeProjetos369[[#This Row],[Duração Estimada (em dias)]])/ControladorDeProjetos369[[#This Row],[Duração Estimada (em dias)]])>Sinalizador_Porcentagem,1,0)),"")

Sheet Prot. CVEL - Altona
A1: Controlador De Protocolos Empreendimento Altona - Cascavel | G1: CNPJ PRATI: | H1: 35.538.973/0001-63
C2: Sinalizador de Porcentagem Acima/Abaixo:
A4: Status | B4: Protocolo | C4: Atividade | D4: Aprovações | E4: Atribuída a | F4: Estimado Início | G4: Estimado Término | H4: Duração Estimada (em dias) | I4: Real Início | J4: Real Término | K4: Sinalizador para duração real acima/abaixo (em dias)S | L4: Duração Real (em dias) | M4: Anotações | N4: Situação
A5: APRO | B5: 20262763132062 | C5: Protocolo de viabilidade copel | D5: Copel | E5: Renan | F5: 46027 | G5: 46034 | H5: =ControladorDeProjetos3673111213151617[[#This Row],[Estimado Término]]-ControladorDeProjetos3673111213151617[[#This Row],[Estimado Início]] -> 7
H8: =IF(COUNTA('Prot. CVEL - Altona'!$F8,'Prot. CVEL - Altona'!$G8)<>2,"",DAYS360('Prot. CVEL - Altona'!$F8,'Prot. CVEL - Altona'!$G8,FALSE)) | K8: =IFERROR(IF(ControladorDeProjetos3673111213151617[[#This Row],[Duração Real (em dias)]]=0,"",IF(ABS((ControladorDeProjetos3673111213151617[[#This Row],[Duração Real (em dias)]]-ControladorDeProjetos3673111213151617[[#This Row],[Duração Estimada (em dias)]])/ControladorDeProjetos3673111213151617[[#This Row],[Duração Estimada (em dias)]])>Sinalizador_Porcentagem,1,0)),"") | L8: =IF(COUNTA('Prot. CVEL - Altona'!$I8,'Prot. CVEL - Altona'!$J8)<>2,"",DAYS360('Prot. CVEL - Altona'!$I8,'Prot. CVEL - Altona'!$J8,FALSE))
H9: =IF(COUNTA('Prot. CVEL - Altona'!$F9,'Prot. CVEL - Altona'!$G9)<>2,"",DAYS360('Prot. CVEL - Altona'!$F9,'Prot. CVEL - Altona'!$G9,FALSE)) | K9: =IFERROR(IF(ControladorDeProjetos3673111213151617[[#This Row],[Duração Real (em dias)]]=0,"",IF(ABS((ControladorDeProjetos3673111213151617[[#This Row],[Duração Real (em dias)]]-ControladorDeProjetos3673111213151617[[#This Row],[Duração Estimada (em dias)]])/ControladorDeProjetos3673111213151617[[#This Row],[Duração Estimada (em dias)]])>Sinalizador_Porcentagem,1,0)),"") | L9: =IF(COUNTA('Prot. CVEL - Altona'!$I9,'Prot. CVEL - Altona'!$J9)<>2,"",DAYS360('Prot. CVEL - Altona'!$I9,'Prot. CVEL - Altona'!$J9,FALSE))
H10: =IF(COUNTA('Prot. CVEL - Altona'!$F10,'Prot. CVEL - Altona'!$G10)<>2,"",DAYS360('Prot. CVEL - Altona'!$F10,'Prot. CVEL - Altona'!$G10,FALSE)) | K10: =IFERROR(IF(ControladorDeProjetos3673111213151617[[#This Row],[Duração Real (em dias)]]=0,"",IF(ABS((ControladorDeProjetos3673111213151617[[#This Row],[Duração Real (em dias)]]-ControladorDeProjetos3673111213151617[[#This Row],[Duração Estimada (em dias)]])/ControladorDeProjetos3673111213151617[[#This Row],[Duração Estimada (em dias)]])>Sinalizador_Porcentagem,1,0)),"") | L10: =IF(COUNTA('Prot. CVEL - Altona'!$I10,'Prot. CVEL - Altona'!$J10)<>2,"",DAYS360('Prot. CVEL - Altona'!$I10,'Prot. CVEL - Altona'!$J10,FALSE))
H11: =IF(COUNTA('Prot. CVEL - Altona'!$F11,'Prot. CVEL - Altona'!$G11)<>2,"",DAYS360('Prot. CVEL - Altona'!$F11,'Prot. CVEL - Altona'!$G11,FALSE)) | K11: =IFERROR(IF(ControladorDeProjetos3673111213151617[[#This Row],[Duração Real (em dias)]]=0,"",IF(ABS((ControladorDeProjetos3673111213151617[[#This Row],[Duração Real (em dias)]]-ControladorDeProjetos3673111213151617[[#This Row],[Duração Estimada (em dias)]])/ControladorDeProjetos3673111213151617[[#This Row],[Duração Estimada (em dias)]])>Sinalizador_Porcentagem,1,0)),"") | L11: =IF(COUNTA('Prot. CVEL - Altona'!$I11,'Prot. CVEL - Altona'!$J11)<>2,"",DAYS360('Prot. CVEL - Altona'!$I11,'Prot. CVEL - Altona'!$J11,FALSE))
H12: =IF(COUNTA('Prot. CVEL - Altona'!$F12,'Prot. CVEL - Altona'!$G12)<>2,"",DAYS360('Prot. CVEL - Altona'!$F12,'Prot. CVEL - Altona'!$G12,FALSE)) | K12: =IFERROR(IF(ControladorDeProjetos3673111213151617[[#This Row],[Duração Real (em dias)]]=0,"",IF(ABS((ControladorDeProjetos3673111213151617[[#This Row],[Duração Real (em dias)]]-ControladorDeProjetos3673111213151617[[#This Row],[Duração Estimada (em dias)]])/ControladorDeProjetos3673111213151617[[#This Row],[Duração Estimada (em dias)]])>Sinalizador_Porcentagem,1,0)),"") | L12: =IF(COUNTA('Prot. CVEL - Altona'!$I12,'Prot. CVEL - Altona'!$J12)<>2,"",DAYS360('Prot. CVEL - Altona'!$I12,'Prot. CVEL - Altona'!$J12,FALSE))
H13: =IF(COUNTA('Prot. CVEL - Altona'!$F13,'Prot. CVEL - Altona'!$G13)<>2,"",DAYS360('Prot. CVEL - Altona'!$F13,'Prot. CVEL - Altona'!$G13,FALSE)) | K13: =IFERROR(IF(ControladorDeProjetos3673111213151617[[#This Row],[Duração Real (em dias)]]=0,"",IF(ABS((ControladorDeProjetos3673111213151617[[#This Row],[Duração Real (em dias)]]-ControladorDeProjetos3673111213151617[[#This Row],[Duração Estimada (em dias)]])/ControladorDeProjetos3673111213151617[[#This Row],[Duração Estimada (em dias)]])>Sinalizador_Porcentagem,1,0)),"") | L13: =IF(COUNTA('Prot. CVEL - Altona'!$I13,'Prot. CVEL - Altona'!$J13)<>2,"",DAYS360('Prot. CVEL - Altona'!$I13,'Prot. CVEL - Altona'!$J13,FALSE))
H14: =IF(COUNTA('Prot. CVEL - Altona'!$F14,'Prot. CVEL - Altona'!$G14)<>2,"",DAYS360('Prot. CVEL - Altona'!$F14,'Prot. CVEL - Altona'!$G14,FALSE)) | K14: =IFERROR(IF(ControladorDeProjetos3673111213151617[[#This Row],[Duração Real (em dias)]]=0,"",IF(ABS((ControladorDeProjetos3673111213151617[[#This Row],[Duração Real (em dias)]]-ControladorDeProjetos3673111213151617[[#This Row],[Duração Estimada (em dias)]])/ControladorDeProjetos3673111213151617[[#This Row],[Duração Estimada (em dias)]])>Sinalizador_Porcentagem,1,0)),"") | L14: =IF(COUNTA('Prot. CVEL - Altona'!$I14,'Prot. CVEL - Altona'!$J14)<>2,"",DAYS360('Prot. CVEL - Altona'!$I14,'Prot. CVEL - Altona'!$J14,FALSE))
H15: =IF(COUNTA('Prot. CVEL - Altona'!$F15,'Prot. CVEL - Altona'!$G15)<>2,"",DAYS360('Prot. CVEL - Altona'!$F15,'Prot. CVEL - Altona'!$G15,FALSE)) | K15: =IFERROR(IF(ControladorDeProjetos3673111213151617[[#This Row],[Duração Real (em dias)]]=0,"",IF(ABS((ControladorDeProjetos3673111213151617[[#This Row],[Duração Real (em dias)]]-ControladorDeProjetos3673111213151617[[#This Row],[Duração Estimada (em dias)]])/ControladorDeProjetos3673111213151617[[#This Row],[Duração Estimada (em dias)]])>Sinalizador_Porcentagem,1,0)),"") | L15: =IF(COUNTA('Prot. CVEL - Altona'!$I15,'Prot. CVEL - Altona'!$J15)<>2,"",DAYS360('Prot. CVEL - Altona'!$I15,'Prot. CVEL - Altona'!$J15,FALSE))

Sheet Prot. TLD - Biopark
A1: Controlador De Protocolos Empreendimento Biopark Toledo
C2: Sinalizador de Porcentagem Acima/Abaixo: | H2: 35.538.973/0001-63
A4: Status | B4: Protocolo | C4: Atividade | D4: Aprovações | E4: Atribuída a | F4: Estimado Início | G4: Estimado Término | H4: Duração Estimada (em dias) | I4: Real Início | J4: Real Término | K4: Sinalizador para duração real acima/abaixo (em dias)S | L4: Duração Real (em dias) | M4: Anotações | N4: Situação
A5: ANÁL | B5: 24.528 / 2026 | C5: Solicitação a Comissão de Urbanismo - COMURB | D5: Prefeitura Toledo | E5: Lavinia | F5: 46156 | G5: 46187 | H5: =ControladorDeProjetos3673111213151618[[#This Row],[Estimado Término]]-ControladorDeProjetos3673111213151618[[#This Row],[Estimado Início]] -> 31 | I5: 46156
H8: =IF(COUNTA('Prot. TLD - Biopark'!$F8,'Prot. TLD - Biopark'!$G8)<>2,"",DAYS360('Prot. TLD - Biopark'!$F8,'Prot. TLD - Biopark'!$G8,FALSE)) | K8: =IFERROR(IF(ControladorDeProjetos3673111213151618[[#This Row],[Duração Real (em dias)]]=0,"",IF(ABS((ControladorDeProjetos3673111213151618[[#This Row],[Duração Real (em dias)]]-ControladorDeProjetos3673111213151618[[#This Row],[Duração Estimada (em dias)]])/ControladorDeProjetos3673111213151618[[#This Row],[Duração Estimada (em dias)]])>Sinalizador_Porcentagem,1,0)),"") | L8: =IF(COUNTA('Prot. TLD - Biopark'!$I8,'Prot. TLD - Biopark'!$J8)<>2,"",DAYS360('Prot. TLD - Biopark'!$I8,'Prot. TLD - Biopark'!$J8,FALSE))
H9: =IF(COUNTA('Prot. TLD - Biopark'!$F9,'Prot. TLD - Biopark'!$G9)<>2,"",DAYS360('Prot. TLD - Biopark'!$F9,'Prot. TLD - Biopark'!$G9,FALSE)) | K9: =IFERROR(IF(ControladorDeProjetos3673111213151618[[#This Row],[Duração Real (em dias)]]=0,"",IF(ABS((ControladorDeProjetos3673111213151618[[#This Row],[Duração Real (em dias)]]-ControladorDeProjetos3673111213151618[[#This Row],[Duração Estimada (em dias)]])/ControladorDeProjetos3673111213151618[[#This Row],[Duração Estimada (em dias)]])>Sinalizador_Porcentagem,1,0)),"") | L9: =IF(COUNTA('Prot. TLD - Biopark'!$I9,'Prot. TLD - Biopark'!$J9)<>2,"",DAYS360('Prot. TLD - Biopark'!$I9,'Prot. TLD - Biopark'!$J9,FALSE))
H10: =IF(COUNTA('Prot. TLD - Biopark'!$F10,'Prot. TLD - Biopark'!$G10)<>2,"",DAYS360('Prot. TLD - Biopark'!$F10,'Prot. TLD - Biopark'!$G10,FALSE)) | K10: =IFERROR(IF(ControladorDeProjetos3673111213151618[[#This Row],[Duração Real (em dias)]]=0,"",IF(ABS((ControladorDeProjetos3673111213151618[[#This Row],[Duração Real (em dias)]]-ControladorDeProjetos3673111213151618[[#This Row],[Duração Estimada (em dias)]])/ControladorDeProjetos3673111213151618[[#This Row],[Duração Estimada (em dias)]])>Sinalizador_Porcentagem,1,0)),"") | L10: =IF(COUNTA('Prot. TLD - Biopark'!$I10,'Prot. TLD - Biopark'!$J10)<>2,"",DAYS360('Prot. TLD - Biopark'!$I10,'Prot. TLD - Biopark'!$J10,FALSE))
H11: =IF(COUNTA('Prot. TLD - Biopark'!$F11,'Prot. TLD - Biopark'!$G11)<>2,"",DAYS360('Prot. TLD - Biopark'!$F11,'Prot. TLD - Biopark'!$G11,FALSE)) | K11: =IFERROR(IF(ControladorDeProjetos3673111213151618[[#This Row],[Duração Real (em dias)]]=0,"",IF(ABS((ControladorDeProjetos3673111213151618[[#This Row],[Duração Real (em dias)]]-ControladorDeProjetos3673111213151618[[#This Row],[Duração Estimada (em dias)]])/ControladorDeProjetos3673111213151618[[#This Row],[Duração Estimada (em dias)]])>Sinalizador_Porcentagem,1,0)),"") | L11: =IF(COUNTA('Prot. TLD - Biopark'!$I11,'Prot. TLD - Biopark'!$J11)<>2,"",DAYS360('Prot. TLD - Biopark'!$I11,'Prot. TLD - Biopark'!$J11,FALSE))
H12: =IF(COUNTA('Prot. TLD - Biopark'!$F12,'Prot. TLD - Biopark'!$G12)<>2,"",DAYS360('Prot. TLD - Biopark'!$F12,'Prot. TLD - Biopark'!$G12,FALSE)) | K12: =IFERROR(IF(ControladorDeProjetos3673111213151618[[#This Row],[Duração Real (em dias)]]=0,"",IF(ABS((ControladorDeProjetos3673111213151618[[#This Row],[Duração Real (em dias)]]-ControladorDeProjetos3673111213151618[[#This Row],[Duração Estimada (em dias)]])/ControladorDeProjetos3673111213151618[[#This Row],[Duração Estimada (em dias)]])>Sinalizador_Porcentagem,1,0)),"") | L12: =IF(COUNTA('Prot. TLD - Biopark'!$I12,'Prot. TLD - Biopark'!$J12)<>2,"",DAYS360('Prot. TLD - Biopark'!$I12,'Prot. TLD - Biopark'!$J12,FALSE))
H13: =IF(COUNTA('Prot. TLD - Biopark'!$F13,'Prot. TLD - Biopark'!$G13)<>2,"",DAYS360('Prot. TLD - Biopark'!$F13,'Prot. TLD - Biopark'!$G13,FALSE)) | K13: =IFERROR(IF(ControladorDeProjetos3673111213151618[[#This Row],[Duração Real (em dias)]]=0,"",IF(ABS((ControladorDeProjetos3673111213151618[[#This Row],[Duração Real (em dias)]]-ControladorDeProjetos3673111213151618[[#This Row],[Duração Estimada (em dias)]])/ControladorDeProjetos3673111213151618[[#This Row],[Duração Estimada (em dias)]])>Sinalizador_Porcentagem,1,0)),"") | L13: =IF(COUNTA('Prot. TLD - Biopark'!$I13,'Prot. TLD - Biopark'!$J13)<>2,"",DAYS360('Prot. TLD - Biopark'!$I13,'Prot. TLD - Biopark'!$J13,FALSE))
H14: =IF(COUNTA('Prot. TLD - Biopark'!$F14,'Prot. TLD - Biopark'!$G14)<>2,"",DAYS360('Prot. TLD - Biopark'!$F14,'Prot. TLD - Biopark'!$G14,FALSE)) | K14: =IFERROR(IF(ControladorDeProjetos3673111213151618[[#This Row],[Duração Real (em dias)]]=0,"",IF(ABS((ControladorDeProjetos3673111213151618[[#This Row],[Duração Real (em dias)]]-ControladorDeProjetos3673111213151618[[#This Row],[Duração Estimada (em dias)]])/ControladorDeProjetos3673111213151618[[#This Row],[Duração Estimada (em dias)]])>Sinalizador_Porcentagem,1,0)),"") | L14: =IF(COUNTA('Prot. TLD - Biopark'!$I14,'Prot. TLD - Biopark'!$J14)<>2,"",DAYS360('Prot. TLD - Biopark'!$I14,'Prot. TLD - Biopark'!$J14,FALSE))
H15: =IF(COUNTA('Prot. TLD - Biopark'!$F15,'Prot. TLD - Biopark'!$G15)<>2,"",DAYS360('Prot. TLD - Biopark'!$F15,'Prot. TLD - Biopark'!$G15,FALSE)) | K15: =IFERROR(IF(ControladorDeProjetos3673111213151618[[#This Row],[Duração Real (em dias)]]=0,"",IF(ABS((ControladorDeProjetos3673111213151618[[#This Row],[Duração Real (em dias)]]-ControladorDeProjetos3673111213151618[[#This Row],[Duração Estimada (em dias)]])/ControladorDeProjetos3673111213151618[[#This Row],[Duração Estimada (em dias)]])>Sinalizador_Porcentagem,1,0)),"") | L15: =IF(COUNTA('Prot. TLD - Biopark'!$I15,'Prot. TLD - Biopark'!$J15)<>2,"",DAYS360('Prot. TLD - Biopark'!$I15,'Prot. TLD - Biopark'!$J15,FALSE))

Sheet Prot. CVEL - Bresolin
A1: Controlador De Protocolos Empreendimento Bresolin - Cascavel | G1: CNPJ PRATI: | H1: 35.538.973/0001-63
C2: Sinalizador de Porcentagem Acima/Abaixo:
A4: Status | B4: Protocolo | C4: Atividade | D4: Aprovações | E4: Atribuída a | F4: Estimado Início | G4: Estimado Término | H4: Duração Estimada (em dias) | I4: Real Início | J4: Real Término | K4: Sinalizador para duração real acima/abaixo (em dias)S | L4: Duração Real (em dias) | M4: Anotações | N4: Situação
A5: APRO | B5: 20252660794528 | C5: Solicitação de viabilidade técnica do bresolin em cascavel | D5: Copel | E5: Renan | F5: 46015 | G5: 46045 | H5: =ControladorDeProjetos36731112131516[[#This Row],[Estimado Término]]-ControladorDeProjetos36731112131516[[#This Row],[Estimado Início]] -> 30 | I5: 46380 | J5: 46030 | L5: =ControladorDeProjetos36731112131516[[#This Row],[Real Início]]-ControladorDeProjetos36731112131516[[#This Row],[Real Término]] -> 350
H8: =IF(COUNTA('Prot. CVEL - Bresolin'!$F8,'Prot. CVEL - Bresolin'!$G8)<>2,"",DAYS360('Prot. CVEL - Bresolin'!$F8,'Prot. CVEL - Bresolin'!$G8,FALSE)) | K8: =IFERROR(IF(ControladorDeProjetos36731112131516[[#This Row],[Duração Real (em dias)]]=0,"",IF(ABS((ControladorDeProjetos36731112131516[[#This Row],[Duração Real (em dias)]]-ControladorDeProjetos36731112131516[[#This Row],[Duração Estimada (em dias)]])/ControladorDeProjetos36731112131516[[#This Row],[Duração Estimada (em dias)]])>Sinalizador_Porcentagem,1,0)),"") | L8: =IF(COUNTA('Prot. CVEL - Bresolin'!$I8,'Prot. CVEL - Bresolin'!$J8)<>2,"",DAYS360('Prot. CVEL - Bresolin'!$I8,'Prot. CVEL - Bresolin'!$J8,FALSE))
H9: =IF(COUNTA('Prot. CVEL - Bresolin'!$F9,'Prot. CVEL - Bresolin'!$G9)<>2,"",DAYS360('Prot. CVEL - Bresolin'!$F9,'Prot. CVEL - Bresolin'!$G9,FALSE)) | K9: =IFERROR(IF(ControladorDeProjetos36731112131516[[#This Row],[Duração Real (em dias)]]=0,"",IF(ABS((ControladorDeProjetos36731112131516[[#This Row],[Duração Real (em dias)]]-ControladorDeProjetos36731112131516[[#This Row],[Duração Estimada (em dias)]])/ControladorDeProjetos36731112131516[[#This Row],[Duração Estimada (em dias)]])>Sinalizador_Porcentagem,1,0)),"") | L9: =IF(COUNTA('Prot. CVEL - Bresolin'!$I9,'Prot. CVEL - Bresolin'!$J9)<>2,"",DAYS360('Prot. CVEL - Bresolin'!$I9,'Prot. CVEL - Bresolin'!$J9,FALSE))
H10: =IF(COUNTA('Prot. CVEL - Bresolin'!$F10,'Prot. CVEL - Bresolin'!$G10)<>2,"",DAYS360('Prot. CVEL - Bresolin'!$F10,'Prot. CVEL - Bresolin'!$G10,FALSE)) | K10: =IFERROR(IF(ControladorDeProjetos36731112131516[[#This Row],[Duração Real (em dias)]]=0,"",IF(ABS((ControladorDeProjetos36731112131516[[#This Row],[Duração Real (em dias)]]-ControladorDeProjetos36731112131516[[#This Row],[Duração Estimada (em dias)]])/ControladorDeProjetos36731112131516[[#This Row],[Duração Estimada (em dias)]])>Sinalizador_Porcentagem,1,0)),"") | L10: =IF(COUNTA('Prot. CVEL - Bresolin'!$I10,'Prot. CVEL - Bresolin'!$J10)<>2,"",DAYS360('Prot. CVEL - Bresolin'!$I10,'Prot. CVEL - Bresolin'!$J10,FALSE))
H11: =IF(COUNTA('Prot. CVEL - Bresolin'!$F11,'Prot. CVEL - Bresolin'!$G11)<>2,"",DAYS360('Prot. CVEL - Bresolin'!$F11,'Prot. CVEL - Bresolin'!$G11,FALSE)) | K11: =IFERROR(IF(ControladorDeProjetos36731112131516[[#This Row],[Duração Real (em dias)]]=0,"",IF(ABS((ControladorDeProjetos36731112131516[[#This Row],[Duração Real (em dias)]]-ControladorDeProjetos36731112131516[[#This Row],[Duração Estimada (em dias)]])/ControladorDeProjetos36731112131516[[#This Row],[Duração Estimada (em dias)]])>Sinalizador_Porcentagem,1,0)),"") | L11: =IF(COUNTA('Prot. CVEL - Bresolin'!$I11,'Prot. CVEL - Bresolin'!$J11)<>2,"",DAYS360('Prot. CVEL - Bresolin'!$I11,'Prot. CVEL - Bresolin'!$J11,FALSE))
H12: =IF(COUNTA('Prot. CVEL - Bresolin'!$F12,'Prot. CVEL - Bresolin'!$G12)<>2,"",DAYS360('Prot. CVEL - Bresolin'!$F12,'Prot. CVEL - Bresolin'!$G12,FALSE)) | K12: =IFERROR(IF(ControladorDeProjetos36731112131516[[#This Row],[Duração Real (em dias)]]=0,"",IF(ABS((ControladorDeProjetos36731112131516[[#This Row],[Duração Real (em dias)]]-ControladorDeProjetos36731112131516[[#This Row],[Duração Estimada (em dias)]])/ControladorDeProjetos36731112131516[[#This Row],[Duração Estimada (em dias)]])>Sinalizador_Porcentagem,1,0)),"") | L12: =IF(COUNTA('Prot. CVEL - Bresolin'!$I12,'Prot. CVEL - Bresolin'!$J12)<>2,"",DAYS360('Prot. CVEL - Bresolin'!$I12,'Prot. CVEL - Bresolin'!$J12,FALSE))
H13: =IF(COUNTA('Prot. CVEL - Bresolin'!$F13,'Prot. CVEL - Bresolin'!$G13)<>2,"",DAYS360('Prot. CVEL - Bresolin'!$F13,'Prot. CVEL - Bresolin'!$G13,FALSE)) | K13: =IFERROR(IF(ControladorDeProjetos36731112131516[[#This Row],[Duração Real (em dias)]]=0,"",IF(ABS((ControladorDeProjetos36731112131516[[#This Row],[Duração Real (em dias)]]-ControladorDeProjetos36731112131516[[#This Row],[Duração Estimada (em dias)]])/ControladorDeProjetos36731112131516[[#This Row],[Duração Estimada (em dias)]])>Sinalizador_Porcentagem,1,0)),"") | L13: =IF(COUNTA('Prot. CVEL - Bresolin'!$I13,'Prot. CVEL - Bresolin'!$J13)<>2,"",DAYS360('Prot. CVEL - Bresolin'!$I13,'Prot. CVEL - Bresolin'!$J13,FALSE))
H14: =IF(COUNTA('Prot. CVEL - Bresolin'!$F14,'Prot. CVEL - Bresolin'!$G14)<>2,"",DAYS360('Prot. CVEL - Bresolin'!$F14,'Prot. CVEL - Bresolin'!$G14,FALSE)) | K14: =IFERROR(IF(ControladorDeProjetos36731112131516[[#This Row],[Duração Real (em dias)]]=0,"",IF(ABS((ControladorDeProjetos36731112131516[[#This Row],[Duração Real (em dias)]]-ControladorDeProjetos36731112131516[[#This Row],[Duração Estimada (em dias)]])/ControladorDeProjetos36731112131516[[#This Row],[Duração Estimada (em dias)]])>Sinalizador_Porcentagem,1,0)),"") | L14: =IF(COUNTA('Prot. CVEL - Bresolin'!$I14,'Prot. CVEL - Bresolin'!$J14)<>2,"",DAYS360('Prot. CVEL - Bresolin'!$I14,'Prot. CVEL - Bresolin'!$J14,FALSE))
H15: =IF(COUNTA('Prot. CVEL - Bresolin'!$F15,'Prot. CVEL - Bresolin'!$G15)<>2,"",DAYS360('Prot. CVEL - Bresolin'!$F15,'Prot. CVEL - Bresolin'!$G15,FALSE)) | K15: =IFERROR(IF(ControladorDeProjetos36731112131516[[#This Row],[Duração Real (em dias)]]=0,"",IF(ABS((ControladorDeProjetos36731112131516[[#This Row],[Duração Real (em dias)]]-ControladorDeProjetos36731112131516[[#This Row],[Duração Estimada (em dias)]])/ControladorDeProjetos36731112131516[[#This Row],[Duração Estimada (em dias)]])>Sinalizador_Porcentagem,1,0)),"") | L15: =IF(COUNTA('Prot. CVEL - Bresolin'!$I15,'Prot. CVEL - Bresolin'!$J15)<>2,"",DAYS360('Prot. CVEL - Bresolin'!$I15,'Prot. CVEL - Bresolin'!$J15,FALSE))

Sheet Prot. CVEL - Bella Citta
A1: Controlador De Protocolos Bella Citta - Cascavel | H1: C8SE4AGQ
C2: Sinalizador de Porcentagem Acima/Abaixo: | G2: CNPJ | H2: 61.876.344/0001-53
A4: Status | B4: Protocolo | C4: Atividade | D4: Aprovações | E4: Atribuída a | F4: Estimado Início | G4: Estimado Término | H4: Duração Estimada (em dias) | I4: Real Início | J4: Real Término | K4: Sinalizador para duração real acima/abaixo (em dias)S | L4: Duração Real (em dias) | M4: Anotações | N4: Situação
A5: APRO | B5: 143544 / 2025 | C5: PGRCC Plano gerador residuos da construção | D5: Prefeitura Toledo | E5: Eduarda | F5: 45940 | G5: 45971 | H5: =IF(COUNTA('Prot. CVEL - Bella Citta'!$F5,'Prot. CVEL - Bella Citta'!$G5)<>2,"",DAYS360('Prot. CVEL - Bella Citta'!$F5,'Prot. CVEL - Bella Citta'!$G5,FALSE)) -> 30 | I5: 45940 | K5: =IFERROR(IF(ControladorDeProjetos367314[[#This Row],[Duração Real (em dias)]]=0,"",IF(ABS((ControladorDeProjetos367314[[#This Row],[Duração Real (em dias)]]-ControladorDeProjetos367314[[#This Row],[Duração Estimada (em dias)]])/ControladorDeProjetos367314[[#This Row],[Duração Estimada (em dias)]])>Sinalizador_Porcentagem,1,0)),"") | L5: =IF(COUNTA('Prot. CVEL - Bella Citta'!$I5,'Prot. CVEL - Bella Citta'!$J5)<>2,"",DAYS360('Prot. CVEL - Bella Citta'!$I5,'Prot. CVEL - Bella Citta'!$J5,FALSE)) | N5: Análise
A6: ANÁL | B6: 3518-25-CVL-DEU | C6: Desmembramento | E6: Michael | H6: =IF(COUNTA('Prot. CVEL - Bella Citta'!$F6,'Prot. CVEL - Bella Citta'!$G6)<>2,"",DAYS360('Prot. CVEL - Bella Citta'!$F6,'Prot. CVEL - Bella Citta'!$G6,FALSE)) | K6: =IFERROR(IF(ControladorDeProjetos367314[[#This Row],[Duração Real (em dias)]]=0,"",IF(ABS((ControladorDeProjetos367314[[#This Row],[Duração Real (em dias)]]-ControladorDeProjetos367314[[#This Row],[Duração Estimada (em dias)]])/ControladorDeProjetos367314[[#This Row],[Duração Estimada (em dias)]])>Sinalizador_Porcentagem,1,0)),"") | L6: =IF(COUNTA('Prot. CVEL - Bella Citta'!$I6,'Prot. CVEL - Bella Citta'!$J6)<>2,"",DAYS360('Prot. CVEL - Bella Citta'!$I6,'Prot. CVEL - Bella Citta'!$J6,FALSE)) | N6: Michael acompanha pelo email
H7: =IF(COUNTA('Prot. CVEL - Bella Citta'!$F7,'Prot. CVEL - Bella Citta'!$G7)<>2,"",DAYS360('Prot. CVEL - Bella Citta'!$F7,'Prot. CVEL - Bella Citta'!$G7,FALSE)) | K7: =IFERROR(IF(ControladorDeProjetos367314[[#This Row],[Duração Real (em dias)]]=0,"",IF(ABS((ControladorDeProjetos367314[[#This Row],[Duração Real (em dias)]]-ControladorDeProjetos367314[[#This Row],[Duração Estimada (em dias)]])/ControladorDeProjetos367314[[#This Row],[Duração Estimada (em dias)]])>Sinalizador_Porcentagem,1,0)),"") | L7: =IF(COUNTA('Prot. CVEL - Bella Citta'!$I7,'Prot. CVEL - Bella Citta'!$J7)<>2,"",DAYS360('Prot. CVEL - Bella Citta'!$I7,'Prot. CVEL - Bella Citta'!$J7,FALSE))
H8: =IF(COUNTA('Prot. CVEL - Bella Citta'!$F8,'Prot. CVEL - Bella Citta'!$G8)<>2,"",DAYS360('Prot. CVEL - Bella Citta'!$F8,'Prot. CVEL - Bella Citta'!$G8,FALSE)) | K8: =IFERROR(IF(ControladorDeProjetos367314[[#This Row],[Duração Real (em dias)]]=0,"",IF(ABS((ControladorDeProjetos367314[[#This Row],[Duração Real (em dias)]]-ControladorDeProjetos367314[[#This Row],[Duração Estimada (em dias)]])/ControladorDeProjetos367314[[#This Row],[Duração Estimada (em dias)]])>Sinalizador_Porcentagem,1,0)),"") | L8: =IF(COUNTA('Prot. CVEL - Bella Citta'!$I8,'Prot. CVEL - Bella Citta'!$J8)<>2,"",DAYS360('Prot. CVEL - Bella Citta'!$I8,'Prot. CVEL - Bella Citta'!$J8,FALSE))
H9: =IF(COUNTA('Prot. CVEL - Bella Citta'!$F9,'Prot. CVEL - Bella Citta'!$G9)<>2,"",DAYS360('Prot. CVEL - Bella Citta'!$F9,'Prot. CVEL - Bella Citta'!$G9,FALSE)) | K9: =IFERROR(IF(ControladorDeProjetos367314[[#This Row],[Duração Real (em dias)]]=0,"",IF(ABS((ControladorDeProjetos367314[[#This Row],[Duração Real (em dias)]]-ControladorDeProjetos367314[[#This Row],[Duração Estimada (em dias)]])/ControladorDeProjetos367314[[#This Row],[Duração Estimada (em dias)]])>Sinalizador_Porcentagem,1,0)),"") | L9: =IF(COUNTA('Prot. CVEL - Bella Citta'!$I9,'Prot. CVEL - Bella Citta'!$J9)<>2,"",DAYS360('Prot. CVEL - Bella Citta'!$I9,'Prot. CVEL - Bella Citta'!$J9,FALSE))
H10: =IF(COUNTA('Prot. CVEL - Bella Citta'!$F10,'Prot. CVEL - Bella Citta'!$G10)<>2,"",DAYS360('Prot. CVEL - Bella Citta'!$F10,'Prot. CVEL - Bella Citta'!$G10,FALSE)) | K10: =IFERROR(IF(ControladorDeProjetos367314[[#This Row],[Duração Real (em dias)]]=0,"",IF(ABS((ControladorDeProjetos367314[[#This Row],[Duração Real (em dias)]]-ControladorDeProjetos367314[[#This Row],[Duração Estimada (em dias)]])/ControladorDeProjetos367314[[#This Row],[Duração Estimada (em dias)]])>Sinalizador_Porcentagem,1,0)),"") | L10: =IF(COUNTA('Prot. CVEL - Bella Citta'!$I10,'Prot. CVEL - Bella Citta'!$J10)<>2,"",DAYS360('Prot. CVEL - Bella Citta'!$I10,'Prot. CVEL - Bella Citta'!$J10,FALSE))
H11: =IF(COUNTA('Prot. CVEL - Bella Citta'!$F11,'Prot. CVEL - Bella Citta'!$G11)<>2,"",DAYS360('Prot. CVEL - Bella Citta'!$F11,'Prot. CVEL - Bella Citta'!$G11,FALSE)) | K11: =IFERROR(IF(ControladorDeProjetos367314[[#This Row],[Duração Real (em dias)]]=0,"",IF(ABS((ControladorDeProjetos367314[[#This Row],[Duração Real (em dias)]]-ControladorDeProjetos367314[[#This Row],[Duração Estimada (em dias)]])/ControladorDeProjetos367314[[#This Row],[Duração Estimada (em dias)]])>Sinalizador_Porcentagem,1,0)),"") | L11: =IF(COUNTA('Prot. CVEL - Bella Citta'!$I11,'Prot. CVEL - Bella Citta'!$J11)<>2,"",DAYS360('Prot. CVEL - Bella Citta'!$I11,'Prot. CVEL - Bella Citta'!$J11,FALSE))
H12: =IF(COUNTA('Prot. CVEL - Bella Citta'!$F12,'Prot. CVEL - Bella Citta'!$G12)<>2,"",DAYS360('Prot. CVEL - Bella Citta'!$F12,'Prot. CVEL - Bella Citta'!$G12,FALSE)) | K12: =IFERROR(IF(ControladorDeProjetos367314[[#This Row],[Duração Real (em dias)]]=0,"",IF(ABS((ControladorDeProjetos367314[[#This Row],[Duração Real (em dias)]]-ControladorDeProjetos367314[[#This Row],[Duração Estimada (em dias)]])/ControladorDeProjetos367314[[#This Row],[Duração Estimada (em dias)]])>Sinalizador_Porcentagem,1,0)),"") | L12: =IF(COUNTA('Prot. CVEL - Bella Citta'!$I12,'Prot. CVEL - Bella Citta'!$J12)<>2,"",DAYS360('Prot. CVEL - Bella Citta'!$I12,'Prot. CVEL - Bella Citta'!$J12,FALSE))
H13: =IF(COUNTA('Prot. CVEL - Bella Citta'!$F13,'Prot. CVEL - Bella Citta'!$G13)<>2,"",DAYS360('Prot. CVEL - Bella Citta'!$F13,'Prot. CVEL - Bella Citta'!$G13,FALSE)) | K13: =IFERROR(IF(ControladorDeProjetos367314[[#This Row],[Duração Real (em dias)]]=0,"",IF(ABS((ControladorDeProjetos367314[[#This Row],[Duração Real (em dias)]]-ControladorDeProjetos367314[[#This Row],[Duração Estimada (em dias)]])/ControladorDeProjetos367314[[#This Row],[Duração Estimada (em dias)]])>Sinalizador_Porcentagem,1,0)),"") | L13: =IF(COUNTA('Prot. CVEL - Bella Citta'!$I13,'Prot. CVEL - Bella Citta'!$J13)<>2,"",DAYS360('Prot. CVEL - Bella Citta'!$I13,'Prot. CVEL - Bella Citta'!$J13,FALSE))
H14: =IF(COUNTA('Prot. CVEL - Bella Citta'!$F14,'Prot. CVEL - Bella Citta'!$G14)<>2,"",DAYS360('Prot. CVEL - Bella Citta'!$F14,'Prot. CVEL - Bella Citta'!$G14,FALSE)) | K14: =IFERROR(IF(ControladorDeProjetos367314[[#This Row],[Duração Real (em dias)]]=0,"",IF(ABS((ControladorDeProjetos367314[[#This Row],[Duração Real (em dias)]]-ControladorDeProjetos367314[[#This Row],[Duração Estimada (em dias)]])/ControladorDeProjetos367314[[#This Row],[Duração Estimada (em dias)]])>Sinalizador_Porcentagem,1,0)),"") | L14: =IF(COUNTA('Prot. CVEL - Bella Citta'!$I14,'Prot. CVEL - Bella Citta'!$J14)<>2,"",DAYS360('Prot. CVEL - Bella Citta'!$I14,'Prot. CVEL - Bella Citta'!$J14,FALSE))

Sheet Prot. TLD - Solar de Verona
A1: Controlador De Protocolos Solar de Verona - Toledo | G1: CNPJ PRATI: | H1: 35.538.973/0001-63
C2: Sinalizador de Porcentagem Acima/Abaixo: | G2: CPF | H2: 603.734.589-91
A4: Status | B4: Protocolo | C4: Atividade | D4: Aprovações | E4: Atribuída a | F4: Estimado Início | G4: Estimado Término | H4: Duração Estimada (em dias) | I4: Real Início | J4: Real Término | K4: Sinalizador para duração real acima/abaixo (em dias)S | L4: Duração Real (em dias) | M4: Anotações | N4: Situação
A5: APRO | B5: 34.228 / 2025 | C5: Anuência Prévia | D5: Prefeitura Toledo | E5: Eduarda | F5: 45854 | G5: 45885 | H5: =IF(COUNTA('Prot. TLD - Solar de Verona'!$F5,'Prot. TLD - Solar de Verona'!$G5)<>2,"",DAYS360('Prot. TLD - Solar de Verona'!$F5,'Prot. TLD - Solar de Verona'!$G5,FALSE)) -> 30 | K5: =IFERROR(IF(ControladorDeProjetos3673[[#This Row],[Duração Real (em dias)]]=0,"",IF(ABS((ControladorDeProjetos3673[[#This Row],[Duração Real (em dias)]]-ControladorDeProjetos3673[[#This Row],[Duração Estimada (em dias)]])/ControladorDeProjetos3673[[#This Row],[Duração Estimada (em dias)]])>Sinalizador_Porcentagem,1,0)),"") | L5: =IF(COUNTA('Prot. TLD - Solar de Verona'!$I5,'Prot. TLD - Solar de Verona'!$J5)<>2,"",DAYS360('Prot. TLD - Solar de Verona'!$I5,'Prot. TLD - Solar de Verona'!$J5,FALSE)) | M5: 08/01 - aprovação | N5: Análise
A6: ANÁL | B6: 46.668 / 2025 | C6: Desmembramento | D6: Prefeitura Toledo | E6: Lavinia | F6: 45924 | G6: 45954 | H6: =IF(COUNTA('Prot. TLD - Solar de Verona'!$F6,'Prot. TLD - Solar de Verona'!$G6)<>2,"",DAYS360('Prot. TLD - Solar de Verona'!$F6,'Prot. TLD - Solar de Verona'!$G6,FALSE)) -> 30 | K6: =IFERROR(IF(ControladorDeProjetos3673[[#This Row],[Duração Real (em dias)]]=0,"",IF(ABS((ControladorDeProjetos3673[[#This Row],[Duração Real (em dias)]]-ControladorDeProjetos3673[[#This Row],[Duração Estimada (em dias)]])/ControladorDeProjetos3673[[#This Row],[Duração Estimada (em dias)]])>Sinalizador_Porcentagem,1,0)),"") | L6: =IF(COUNTA('Prot. TLD - Solar de Verona'!$I6,'Prot. TLD - Solar de Verona'!$J6)<>2,"",DAYS360('Prot. TLD - Solar de Verona'!$I6,'Prot. TLD - Solar de Verona'!$J6,FALSE)) | N6: Análise
A7: APRO | B7: 24.765.615-4 | C7: Autorização Ambiental Desmembramento | D7: IAT | E7: Michael | F7: 45933 | G7: 45964 | H7: =IF(COUNTA('Prot. TLD - Solar de Verona'!$F7,'Prot. TLD - Solar de Verona'!$G7)<>2,"",DAYS360('Prot. TLD - Solar de Verona'!$F7,'Prot. TLD - Solar de Verona'!$G7,FALSE)) -> 30 | N7: Análise
A8: APRO | B8: 16.483 / 2026 - 62.827.424/0001-81 | C8: impacto de vizinhança | D8: Prefeitura Toledo | E8: Eduarda | F8: 46113 | G8: 46155 | H8: =IF(COUNTA('Prot. TLD - Solar de Verona'!$F8,'Prot. TLD - Solar de Verona'!$G8)<>2,"",DAYS360('Prot. TLD - Solar de Verona'!$F8,'Prot. TLD - Solar de Verona'!$G8,FALSE)) -> 42 | N8: Análise
H9: =IF(COUNTA('Prot. TLD - Solar de Verona'!$F9,'Prot. TLD - Solar de Verona'!$G9)<>2,"",DAYS360('Prot. TLD - Solar de Verona'!$F9,'Prot. TLD - Solar de Verona'!$G9,FALSE)) | K9: =IFERROR(IF(ControladorDeProjetos3673[[#This Row],[Duração Real (em dias)]]=0,"",IF(ABS((ControladorDeProjetos3673[[#This Row],[Duração Real (em dias)]]-ControladorDeProjetos3673[[#This Row],[Duração Estimada (em dias)]])/ControladorDeProjetos3673[[#This Row],[Duração Estimada (em dias)]])>Sinalizador_Porcentagem,1,0)),"") | L9: =IF(COUNTA('Prot. TLD - Solar de Verona'!$I9,'Prot. TLD - Solar de Verona'!$J9)<>2,"",DAYS360('Prot. TLD - Solar de Verona'!$I9,'Prot. TLD - Solar de Verona'!$J9,FALSE))
H10: =IF(COUNTA('Prot. TLD - Solar de Verona'!$F10,'Prot. TLD - Solar de Verona'!$G10)<>2,"",DAYS360('Prot. TLD - Solar de Verona'!$F10,'Prot. TLD - Solar de Verona'!$G10,FALSE)) | K10: =IFERROR(IF(ControladorDeProjetos3673[[#This Row],[Duração Real (em dias)]]=0,"",IF(ABS((ControladorDeProjetos3673[[#This Row],[Duração Real (em dias)]]-ControladorDeProjetos3673[[#This Row],[Duração Estimada (em dias)]])/ControladorDeProjetos3673[[#This Row],[Duração Estimada (em dias)]])>Sinalizador_Porcentagem,1,0)),"") | L10: =IF(COUNTA('Prot. TLD - Solar de Verona'!$I10,'Prot. TLD - Solar de Verona'!$J10)<>2,"",DAYS360('Prot. TLD - Solar de Verona'!$I10,'Prot. TLD - Solar de Verona'!$J10,FALSE))
H11: =IF(COUNTA('Prot. TLD - Solar de Verona'!$F11,'Prot. TLD - Solar de Verona'!$G11)<>2,"",DAYS360('Prot. TLD - Solar de Verona'!$F11,'Prot. TLD - Solar de Verona'!$G11,FALSE)) | K11: =IFERROR(IF(ControladorDeProjetos3673[[#This Row],[Duração Real (em dias)]]=0,"",IF(ABS((ControladorDeProjetos3673[[#This Row],[Duração Real (em dias)]]-ControladorDeProjetos3673[[#This Row],[Duração Estimada (em dias)]])/ControladorDeProjetos3673[[#This Row],[Duração Estimada (em dias)]])>Sinalizador_Porcentagem,1,0)),"") | L11: =IF(COUNTA('Prot. TLD - Solar de Verona'!$I11,'Prot. TLD - Solar de Verona'!$J11)<>2,"",DAYS360('Prot. TLD - Solar de Verona'!$I11,'Prot. TLD - Solar de Verona'!$J11,FALSE))
H12: =IF(COUNTA('Prot. TLD - Solar de Verona'!$F12,'Prot. TLD - Solar de Verona'!$G12)<>2,"",DAYS360('Prot. TLD - Solar de Verona'!$F12,'Prot. TLD - Solar de Verona'!$G12,FALSE)) | K12: =IFERROR(IF(ControladorDeProjetos3673[[#This Row],[Duração Real (em dias)]]=0,"",IF(ABS((ControladorDeProjetos3673[[#This Row],[Duração Real (em dias)]]-ControladorDeProjetos3673[[#This Row],[Duração Estimada (em dias)]])/ControladorDeProjetos3673[[#This Row],[Duração Estimada (em dias)]])>Sinalizador_Porcentagem,1,0)),"") | L12: =IF(COUNTA('Prot. TLD - Solar de Verona'!$I12,'Prot. TLD - Solar de Verona'!$J12)<>2,"",DAYS360('Prot. TLD - Solar de Verona'!$I12,'Prot. TLD - Solar de Verona'!$J12,FALSE))
H13: =IF(COUNTA('Prot. TLD - Solar de Verona'!$F13,'Prot. TLD - Solar de Verona'!$G13)<>2,"",DAYS360('Prot. TLD - Solar de Verona'!$F13,'Prot. TLD - Solar de Verona'!$G13,FALSE)) | K13: =IFERROR(IF(ControladorDeProjetos3673[[#This Row],[Duração Real (em dias)]]=0,"",IF(ABS((ControladorDeProjetos3673[[#This Row],[Duração Real (em dias)]]-ControladorDeProjetos3673[[#This Row],[Duração Estimada (em dias)]])/ControladorDeProjetos3673[[#This Row],[Duração Estimada (em dias)]])>Sinalizador_Porcentagem,1,0)),"") | L13: =IF(COUNTA('Prot. TLD - Solar de Verona'!$I13,'Prot. TLD - Solar de Verona'!$J13)<>2,"",DAYS360('Prot. TLD - Solar de Verona'!$I13,'Prot. TLD - Solar de Verona'!$J13,FALSE))
H14: =IF(COUNTA('Prot. TLD - Solar de Verona'!$F14,'Prot. TLD - Solar de Verona'!$G14)<>2,"",DAYS360('Prot. TLD - Solar de Verona'!$F14,'Prot. TLD - Solar de Verona'!$G14,FALSE)) | K14: =IFERROR(IF(ControladorDeProjetos3673[[#This Row],[Duração Real (em dias)]]=0,"",IF(ABS((ControladorDeProjetos3673[[#This Row],[Duração Real (em dias)]]-ControladorDeProjetos3673[[#This Row],[Duração Estimada (em dias)]])/ControladorDeProjetos3673[[#This Row],[Duração Estimada (em dias)]])>Sinalizador_Porcentagem,1,0)),"") | L14: =IF(COUNTA('Prot. TLD - Solar de Verona'!$I14,'Prot. TLD - Solar de Verona'!$J14)<>2,"",DAYS360('Prot. TLD - Solar de Verona'!$I14,'Prot. TLD - Solar de Verona'!$J14,FALSE))
H15: =IF(COUNTA('Prot. TLD - Solar de Verona'!$F15,'Prot. TLD - Solar de Verona'!$G15)<>2,"",DAYS360('Prot. TLD - Solar de Verona'!$F15,'Prot. TLD - Solar de Verona'!$G15,FALSE)) | K15: =IFERROR(IF(ControladorDeProjetos3673[[#This Row],[Duração Real (em dias)]]=0,"",IF(ABS((ControladorDeProjetos3673[[#This Row],[Duração Real (em dias)]]-ControladorDeProjetos3673[[#This Row],[Duração Estimada (em dias)]])/ControladorDeProjetos3673[[#This Row],[Duração Estimada (em dias)]])>Sinalizador_Porcentagem,1,0)),"") | L15: =IF(COUNTA('Prot. TLD - Solar de Verona'!$I15,'Prot. TLD - Solar de Verona'!$J15)<>2,"",DAYS360('Prot. TLD - Solar de Verona'!$I15,'Prot. TLD - Solar de Verona'!$J15,FALSE))

Sheet Prot. TLD - Sede Hélio
A1: Controlador De Protocolos Sede Hélio - Toledo | G1: CNPJ PRATI: | H1: 35.538.973/0001-63
C2: Sinalizador de Porcentagem Acima/Abaixo:
A4: Status | B4: Protocolo | C4: Atividade | D4: Aprovações | E4: Atribuída a | F4: Estimado Início | G4: Estimado Término | H4: Duração Estimada (em dias) | I4: Real Início | J4: Real Término | K4: Sinalizador para duração real acima/abaixo (em dias)S | L4: Duração Real (em dias) | M4: Anotações | N4: Situação
A5: APRO | B5: 38.423 / 2025 | C5: Solicitação Secretaria do Planejamento estratégico | D5: Prefeitura Toledo | E5: Eduarda | F5: 45880 | G5: 45911 | H5: =IF(COUNTA('Prot. TLD - Sede Hélio'!$F5,'Prot. TLD - Sede Hélio'!$G5)<>2,"",DAYS360('Prot. TLD - Sede Hélio'!$F5,'Prot. TLD - Sede Hélio'!$G5,FALSE)) -> 30 | I5: 45880 | J5: 45905 | K5: =IFERROR(IF(ControladorDeProjetos367311[[#This Row],[Duração Real (em dias)]]=0,"",IF(ABS((ControladorDeProjetos367311[[#This Row],[Duração Real (em dias)]]-ControladorDeProjetos367311[[#This Row],[Duração Estimada (em dias)]])/ControladorDeProjetos367311[[#This Row],[Duração Estimada (em dias)]])>Sinalizador_Porcentagem,1,0)),"") -> 1 | L5: =IF(COUNTA('Prot. TLD - Sede Hélio'!$I5,'Prot. TLD - Sede Hélio'!$J5)<>2,"",DAYS360('Prot. TLD - Sede Hélio'!$I5,'Prot. TLD - Sede Hélio'!$J5,FALSE)) -> 24 | N5: concluido
A6: APRO | B6: 20262762687225 | C6: Protocolo de viabilidade copel | D6: Copel | E6: Renan | F6: 46027 | G6: 46058 | H6: =IF(COUNTA('Prot. TLD - Sede Hélio'!$F6,'Prot. TLD - Sede Hélio'!$G6)<>2,"",DAYS360('Prot. TLD - Sede Hélio'!$F6,'Prot. TLD - Sede Hélio'!$G6,FALSE)) -> 30 | I6: 46027 | J6: 46029 | L6: =ControladorDeProjetos367311[[#This Row],[Real Término]]-ControladorDeProjetos367311[[#This Row],[Real Início]] -> 2
H8: =IF(COUNTA('Prot. TLD - Sede Hélio'!$F8,'Prot. TLD - Sede Hélio'!$G8)<>2,"",DAYS360('Prot. TLD - Sede Hélio'!$F8,'Prot. TLD - Sede Hélio'!$G8,FALSE)) | K8: =IFERROR(IF(ControladorDeProjetos367311[[#This Row],[Duração Real (em dias)]]=0,"",IF(ABS((ControladorDeProjetos367311[[#This Row],[Duração Real (em dias)]]-ControladorDeProjetos367311[[#This Row],[Duração Estimada (em dias)]])/ControladorDeProjetos367311[[#This Row],[Duração Estimada (em dias)]])>Sinalizador_Porcentagem,1,0)),"") | L8: =IF(COUNTA('Prot. TLD - Sede Hélio'!$I8,'Prot. TLD - Sede Hélio'!$J8)<>2,"",DAYS360('Prot. TLD - Sede Hélio'!$I8,'Prot. TLD - Sede Hélio'!$J8,FALSE))
H9: =IF(COUNTA('Prot. TLD - Sede Hélio'!$F9,'Prot. TLD - Sede Hélio'!$G9)<>2,"",DAYS360('Prot. TLD - Sede Hélio'!$F9,'Prot. TLD - Sede Hélio'!$G9,FALSE)) | K9: =IFERROR(IF(ControladorDeProjetos367311[[#This Row],[Duração Real (em dias)]]=0,"",IF(ABS((ControladorDeProjetos367311[[#This Row],[Duração Real (em dias)]]-ControladorDeProjetos367311[[#This Row],[Duração Estimada (em dias)]])/ControladorDeProjetos367311[[#This Row],[Duração Estimada (em dias)]])>Sinalizador_Porcentagem,1,0)),"") | L9: =IF(COUNTA('Prot. TLD - Sede Hélio'!$I9,'Prot. TLD - Sede Hélio'!$J9)<>2,"",DAYS360('Prot. TLD - Sede Hélio'!$I9,'Prot. TLD - Sede Hélio'!$J9,FALSE))
H10: =IF(COUNTA('Prot. TLD - Sede Hélio'!$F10,'Prot. TLD - Sede Hélio'!$G10)<>2,"",DAYS360('Prot. TLD - Sede Hélio'!$F10,'Prot. TLD - Sede Hélio'!$G10,FALSE)) | K10: =IFERROR(IF(ControladorDeProjetos367311[[#This Row],[Duração Real (em dias)]]=0,"",IF(ABS((ControladorDeProjetos367311[[#This Row],[Duração Real (em dias)]]-ControladorDeProjetos367311[[#This Row],[Duração Estimada (em dias)]])/ControladorDeProjetos367311[[#This Row],[Duração Estimada (em dias)]])>Sinalizador_Porcentagem,1,0)),"") | L10: =IF(COUNTA('Prot. TLD - Sede Hélio'!$I10,'Prot. TLD - Sede Hélio'!$J10)<>2,"",DAYS360('Prot. TLD - Sede Hélio'!$I10,'Prot. TLD - Sede Hélio'!$J10,FALSE))
H11: =IF(COUNTA('Prot. TLD - Sede Hélio'!$F11,'Prot. TLD - Sede Hélio'!$G11)<>2,"",DAYS360('Prot. TLD - Sede Hélio'!$F11,'Prot. TLD - Sede Hélio'!$G11,FALSE)) | K11: =IFERROR(IF(ControladorDeProjetos367311[[#This Row],[Duração Real (em dias)]]=0,"",IF(ABS((ControladorDeProjetos367311[[#This Row],[Duração Real (em dias)]]-ControladorDeProjetos367311[[#This Row],[Duração Estimada (em dias)]])/ControladorDeProjetos367311[[#This Row],[Duração Estimada (em dias)]])>Sinalizador_Porcentagem,1,0)),"") | L11: =IF(COUNTA('Prot. TLD - Sede Hélio'!$I11,'Prot. TLD - Sede Hélio'!$J11)<>2,"",DAYS360('Prot. TLD - Sede Hélio'!$I11,'Prot. TLD - Sede Hélio'!$J11,FALSE))
H12: =IF(COUNTA('Prot. TLD - Sede Hélio'!$F12,'Prot. TLD - Sede Hélio'!$G12)<>2,"",DAYS360('Prot. TLD - Sede Hélio'!$F12,'Prot. TLD - Sede Hélio'!$G12,FALSE)) | K12: =IFERROR(IF(ControladorDeProjetos367311[[#This Row],[Duração Real (em dias)]]=0,"",IF(ABS((ControladorDeProjetos367311[[#This Row],[Duração Real (em dias)]]-ControladorDeProjetos367311[[#This Row],[Duração Estimada (em dias)]])/ControladorDeProjetos367311[[#This Row],[Duração Estimada (em dias)]])>Sinalizador_Porcentagem,1,0)),"") | L12: =IF(COUNTA('Prot. TLD - Sede Hélio'!$I12,'Prot. TLD - Sede Hélio'!$J12)<>2,"",DAYS360('Prot. TLD - Sede Hélio'!$I12,'Prot. TLD - Sede Hélio'!$J12,FALSE))
H13: =IF(COUNTA('Prot. TLD - Sede Hélio'!$F13,'Prot. TLD - Sede Hélio'!$G13)<>2,"",DAYS360('Prot. TLD - Sede Hélio'!$F13,'Prot. TLD - Sede Hélio'!$G13,FALSE)) | K13: =IFERROR(IF(ControladorDeProjetos367311[[#This Row],[Duração Real (em dias)]]=0,"",IF(ABS((ControladorDeProjetos367311[[#This Row],[Duração Real (em dias)]]-ControladorDeProjetos367311[[#This Row],[Duração Estimada (em dias)]])/ControladorDeProjetos367311[[#This Row],[Duração Estimada (em dias)]])>Sinalizador_Porcentagem,1,0)),"") | L13: =IF(COUNTA('Prot. TLD - Sede Hélio'!$I13,'Prot. TLD - Sede Hélio'!$J13)<>2,"",DAYS360('Prot. TLD - Sede Hélio'!$I13,'Prot. TLD - Sede Hélio'!$J13,FALSE))
H14: =IF(COUNTA('Prot. TLD - Sede Hélio'!$F14,'Prot. TLD - Sede Hélio'!$G14)<>2,"",DAYS360('Prot. TLD - Sede Hélio'!$F14,'Prot. TLD - Sede Hélio'!$G14,FALSE)) | K14: =IFERROR(IF(ControladorDeProjetos367311[[#This Row],[Duração Real (em dias)]]=0,"",IF(ABS((ControladorDeProjetos367311[[#This Row],[Duração Real (em dias)]]-ControladorDeProjetos367311[[#This Row],[Duração Estimada (em dias)]])/ControladorDeProjetos367311[[#This Row],[Duração Estimada (em dias)]])>Sinalizador_Porcentagem,1,0)),"") | L14: =IF(COUNTA('Prot. TLD - Sede Hélio'!$I14,'Prot. TLD - Sede Hélio'!$J14)<>2,"",DAYS360('Prot. TLD - Sede Hélio'!$I14,'Prot. TLD - Sede Hélio'!$J14,FALSE))
H15: =IF(COUNTA('Prot. TLD - Sede Hélio'!$F15,'Prot. TLD - Sede Hélio'!$G15)<>2,"",DAYS360('Prot. TLD - Sede Hélio'!$F15,'Prot. TLD - Sede Hélio'!$G15,FALSE)) | K15: =IFERROR(IF(ControladorDeProjetos367311[[#This Row],[Duração Real (em dias)]]=0,"",IF(ABS((ControladorDeProjetos367311[[#This Row],[Duração Real (em dias)]]-ControladorDeProjetos367311[[#This Row],[Duração Estimada (em dias)]])/ControladorDeProjetos367311[[#This Row],[Duração Estimada (em dias)]])>Sinalizador_Porcentagem,1,0)),"") | L15: =IF(COUNTA('Prot. TLD - Sede Hélio'!$I15,'Prot. TLD - Sede Hélio'!$J15)<>2,"",DAYS360('Prot. TLD - Sede Hélio'!$I15,'Prot. TLD - Sede Hélio'!$J15,FALSE))

Sheet Prot. TLD - Sperafico
A1: Controlador De Protocolos Sperafico - Toledo | G1: CNPJ PRATI: | H1: 35.538.973/0001-63
C2: Sinalizador de Porcentagem Acima/Abaixo: | G2: CNPJ SPERAFICO | H2: 85.466.951/0001-03
A4: Status | B4: Protocolo | C4: Atividade | D4: Aprovações | E4: Atribuída a | F4: Estimado Início | G4: Estimado Término | H4: Duração Estimada (em dias) | I4: Real Início | J4: Real Término | K4: Sinalizador para duração real acima/abaixo (em dias)S | L4: Duração Real (em dias) | M4: Anotações | N4: Situação
A5: APRO | B5: 46.663 / 2025 | C5: COMURB - solicitação de diretrizes urbanísticas para empreendimento habitacional | D5: Prefeitura Toledo | E5: Eduarda | F5: 45924 | G5: 45954 | H5: =IF(COUNTA('Prot. TLD - Sperafico'!$F5,'Prot. TLD - Sperafico'!$G5)<>2,"",DAYS360('Prot. TLD - Sperafico'!$F5,'Prot. TLD - Sperafico'!$G5,FALSE)) -> 30 | I5: 45924 | K5: =IFERROR(IF(ControladorDeProjetos36731112[[#This Row],[Duração Real (em dias)]]=0,"",IF(ABS((ControladorDeProjetos36731112[[#This Row],[Duração Real (em dias)]]-ControladorDeProjetos36731112[[#This Row],[Duração Estimada (em dias)]])/ControladorDeProjetos36731112[[#This Row],[Duração Estimada (em dias)]])>Sinalizador_Porcentagem,1,0)),"") | L5: =IF(COUNTA('Prot. TLD - Sperafico'!$I5,'Prot. TLD - Sperafico'!$J5)<>2,"",DAYS360('Prot. TLD - Sperafico'!$I5,'Prot. TLD - Sperafico'!$J5,FALSE)) | N5: ANÁLISE
A6: ANÁL | B6: 46.670 / 2025 | C6: Desmembramento | D6: Prefeitura Toledo | E6: Lavinia | F6: 45924 | K6: =IFERROR(IF(ControladorDeProjetos36731112[[#This Row],[Duração Real (em dias)]]=0,"",IF(ABS((ControladorDeProjetos36731112[[#This Row],[Duração Real (em dias)]]-ControladorDeProjetos36731112[[#This Row],[Duração Estimada (em dias)]])/ControladorDeProjetos36731112[[#This Row],[Duração Estimada (em dias)]])>Sinalizador_Porcentagem,1,0)),"") | L6: =IF(COUNTA('Prot. TLD - Sperafico'!$I6,'Prot. TLD - Sperafico'!$J6)<>2,"",DAYS360('Prot. TLD - Sperafico'!$I6,'Prot. TLD - Sperafico'!$J6,FALSE)) | N6: ANÁLISE
A7: ANÁL | B7: 25.025.067-3 | C7: Carta de Viabilidade | D7: Sanepar | E7: Cristian | F7: 45980 | N7: ANÁLISE
H8: =IF(COUNTA('Prot. TLD - Sperafico'!$F8,'Prot. TLD - Sperafico'!$G8)<>2,"",DAYS360('Prot. TLD - Sperafico'!$F8,'Prot. TLD - Sperafico'!$G8,FALSE)) | K8: =IFERROR(IF(ControladorDeProjetos36731112[[#This Row],[Duração Real (em dias)]]=0,"",IF(ABS((ControladorDeProjetos36731112[[#This Row],[Duração Real (em dias)]]-ControladorDeProjetos36731112[[#This Row],[Duração Estimada (em dias)]])/ControladorDeProjetos36731112[[#This Row],[Duração Estimada (em dias)]])>Sinalizador_Porcentagem,1,0)),"") | L8: =IF(COUNTA('Prot. TLD - Sperafico'!$I8,'Prot. TLD - Sperafico'!$J8)<>2,"",DAYS360('Prot. TLD - Sperafico'!$I8,'Prot. TLD - Sperafico'!$J8,FALSE))
H9: =IF(COUNTA('Prot. TLD - Sperafico'!$F9,'Prot. TLD - Sperafico'!$G9)<>2,"",DAYS360('Prot. TLD - Sperafico'!$F9,'Prot. TLD - Sperafico'!$G9,FALSE)) | K9: =IFERROR(IF(ControladorDeProjetos36731112[[#This Row],[Duração Real (em dias)]]=0,"",IF(ABS((ControladorDeProjetos36731112[[#This Row],[Duração Real (em dias)]]-ControladorDeProjetos36731112[[#This Row],[Duração Estimada (em dias)]])/ControladorDeProjetos36731112[[#This Row],[Duração Estimada (em dias)]])>Sinalizador_Porcentagem,1,0)),"") | L9: =IF(COUNTA('Prot. TLD - Sperafico'!$I9,'Prot. TLD - Sperafico'!$J9)<>2,"",DAYS360('Prot. TLD - Sperafico'!$I9,'Prot. TLD - Sperafico'!$J9,FALSE))
H10: =IF(COUNTA('Prot. TLD - Sperafico'!$F10,'Prot. TLD - Sperafico'!$G10)<>2,"",DAYS360('Prot. TLD - Sperafico'!$F10,'Prot. TLD - Sperafico'!$G10,FALSE)) | K10: =IFERROR(IF(ControladorDeProjetos36731112[[#This Row],[Duração Real (em dias)]]=0,"",IF(ABS((ControladorDeProjetos36731112[[#This Row],[Duração Real (em dias)]]-ControladorDeProjetos36731112[[#This Row],[Duração Estimada (em dias)]])/ControladorDeProjetos36731112[[#This Row],[Duração Estimada (em dias)]])>Sinalizador_Porcentagem,1,0)),"") | L10: =IF(COUNTA('Prot. TLD - Sperafico'!$I10,'Prot. TLD - Sperafico'!$J10)<>2,"",DAYS360('Prot. TLD - Sperafico'!$I10,'Prot. TLD - Sperafico'!$J10,FALSE))
H11: =IF(COUNTA('Prot. TLD - Sperafico'!$F11,'Prot. TLD - Sperafico'!$G11)<>2,"",DAYS360('Prot. TLD - Sperafico'!$F11,'Prot. TLD - Sperafico'!$G11,FALSE)) | K11: =IFERROR(IF(ControladorDeProjetos36731112[[#This Row],[Duração Real (em dias)]]=0,"",IF(ABS((ControladorDeProjetos36731112[[#This Row],[Duração Real (em dias)]]-ControladorDeProjetos36731112[[#This Row],[Duração Estimada (em dias)]])/ControladorDeProjetos36731112[[#This Row],[Duração Estimada (em dias)]])>Sinalizador_Porcentagem,1,0)),"") | L11: =IF(COUNTA('Prot. TLD - Sperafico'!$I11,'Prot. TLD - Sperafico'!$J11)<>2,"",DAYS360('Prot. TLD - Sperafico'!$I11,'Prot. TLD - Sperafico'!$J11,FALSE))
H12: =IF(COUNTA('Prot. TLD - Sperafico'!$F12,'Prot. TLD - Sperafico'!$G12)<>2,"",DAYS360('Prot. TLD - Sperafico'!$F12,'Prot. TLD - Sperafico'!$G12,FALSE)) | K12: =IFERROR(IF(ControladorDeProjetos36731112[[#This Row],[Duração Real (em dias)]]=0,"",IF(ABS((ControladorDeProjetos36731112[[#This Row],[Duração Real (em dias)]]-ControladorDeProjetos36731112[[#This Row],[Duração Estimada (em dias)]])/ControladorDeProjetos36731112[[#This Row],[Duração Estimada (em dias)]])>Sinalizador_Porcentagem,1,0)),"") | L12: =IF(COUNTA('Prot. TLD - Sperafico'!$I12,'Prot. TLD - Sperafico'!$J12)<>2,"",DAYS360('Prot. TLD - Sperafico'!$I12,'Prot. TLD - Sperafico'!$J12,FALSE))
H13: =IF(COUNTA('Prot. TLD - Sperafico'!$F13,'Prot. TLD - Sperafico'!$G13)<>2,"",DAYS360('Prot. TLD - Sperafico'!$F13,'Prot. TLD - Sperafico'!$G13,FALSE)) | K13: =IFERROR(IF(ControladorDeProjetos36731112[[#This Row],[Duração Real (em dias)]]=0,"",IF(ABS((ControladorDeProjetos36731112[[#This Row],[Duração Real (em dias)]]-ControladorDeProjetos36731112[[#This Row],[Duração Estimada (em dias)]])/ControladorDeProjetos36731112[[#This Row],[Duração Estimada (em dias)]])>Sinalizador_Porcentagem,1,0)),"") | L13: =IF(COUNTA('Prot. TLD - Sperafico'!$I13,'Prot. TLD - Sperafico'!$J13)<>2,"",DAYS360('Prot. TLD - Sperafico'!$I13,'Prot. TLD - Sperafico'!$J13,FALSE))
H14: =IF(COUNTA('Prot. TLD - Sperafico'!$F14,'Prot. TLD - Sperafico'!$G14)<>2,"",DAYS360('Prot. TLD - Sperafico'!$F14,'Prot. TLD - Sperafico'!$G14,FALSE)) | K14: =IFERROR(IF(ControladorDeProjetos36731112[[#This Row],[Duração Real (em dias)]]=0,"",IF(ABS((ControladorDeProjetos36731112[[#This Row],[Duração Real (em dias)]]-ControladorDeProjetos36731112[[#This Row],[Duração Estimada (em dias)]])/ControladorDeProjetos36731112[[#This Row],[Duração Estimada (em dias)]])>Sinalizador_Porcentagem,1,0)),"") | L14: =IF(COUNTA('Prot. TLD - Sperafico'!$I14,'Prot. TLD - Sperafico'!$J14)<>2,"",DAYS360('Prot. TLD - Sperafico'!$I14,'Prot. TLD - Sperafico'!$J14,FALSE))
H15: =IF(COUNTA('Prot. TLD - Sperafico'!$F15,'Prot. TLD - Sperafico'!$G15)<>2,"",DAYS360('Prot. TLD - Sperafico'!$F15,'Prot. TLD - Sperafico'!$G15,FALSE)) | K15: =IFERROR(IF(ControladorDeProjetos36731112[[#This Row],[Duração Real (em dias)]]=0,"",IF(ABS((ControladorDeProjetos36731112[[#This Row],[Duração Real (em dias)]]-ControladorDeProjetos36731112[[#This Row],[Duração Estimada (em dias)]])/ControladorDeProjetos36731112[[#This Row],[Duração Estimada (em dias)]])>Sinalizador_Porcentagem,1,0)),"") | L15: =IF(COUNTA('Prot. TLD - Sperafico'!$I15,'Prot. TLD - Sperafico'!$J15)<>2,"",DAYS360('Prot. TLD - Sperafico'!$I15,'Prot. TLD - Sperafico'!$J15,FALSE))

Sheet Prot. TLD - 13 de Abril
A1: Controlador De Protocolos Empreendimento 13 de Abril - Toledo | G1: CNPJ PRATI: | H1: 35.538.973/0001-63
C2: Sinalizador de Porcentagem Acima/Abaixo:
A4: Status | B4: Protocolo | C4: Atividade | D4: Aprovações | E4: Atribuída a | F4: Estimado Início | G4: Estimado Término | H4: Duração Estimada (em dias) | I4: Real Início | J4: Real Término | K4: Sinalizador para duração real acima/abaixo (em dias)S | L4: Duração Real (em dias) | M4: Anotações | N4: Situação
A5: ANÁL | B5: 53.640 / 2025 | C5: solicita à COMURB as regras de zoneamento para cinco terrenos. | D5: Prefeitura Toledo | E5: Lavinia | F5: 45964 | G5: 45994 | H5: =IF(COUNTA('Prot. TLD - 13 de Abril'!$F5,'Prot. TLD - 13 de Abril'!$G5)<>2,"",DAYS360('Prot. TLD - 13 de Abril'!$F5,'Prot. TLD - 13 de Abril'!$G5,FALSE)) -> 30 | I5: 46329 | K5: =IFERROR(IF(ControladorDeProjetos367311121315[[#This Row],[Duração Real (em dias)]]=0,"",IF(ABS((ControladorDeProjetos367311121315[[#This Row],[Duração Real (em dias)]]-ControladorDeProjetos367311121315[[#This Row],[Duração Estimada (em dias)]])/ControladorDeProjetos367311121315[[#This Row],[Duração Estimada (em dias)]])>Sinalizador_Porcentagem,1,0)),"") | N5: ANÁLISE
H8: =IF(COUNTA('Prot. TLD - 13 de Abril'!$F8,'Prot. TLD - 13 de Abril'!$G8)<>2,"",DAYS360('Prot. TLD - 13 de Abril'!$F8,'Prot. TLD - 13 de Abril'!$G8,FALSE)) | K8: =IFERROR(IF(ControladorDeProjetos367311121315[[#This Row],[Duração Real (em dias)]]=0,"",IF(ABS((ControladorDeProjetos367311121315[[#This Row],[Duração Real (em dias)]]-ControladorDeProjetos367311121315[[#This Row],[Duração Estimada (em dias)]])/ControladorDeProjetos367311121315[[#This Row],[Duração Estimada (em dias)]])>Sinalizador_Porcentagem,1,0)),"") | L8: =IF(COUNTA('Prot. TLD - 13 de Abril'!$I8,'Prot. TLD - 13 de Abril'!$J8)<>2,"",DAYS360('Prot. TLD - 13 de Abril'!$I8,'Prot. TLD - 13 de Abril'!$J8,FALSE))
H9: =IF(COUNTA('Prot. TLD - 13 de Abril'!$F9,'Prot. TLD - 13 de Abril'!$G9)<>2,"",DAYS360('Prot. TLD - 13 de Abril'!$F9,'Prot. TLD - 13 de Abril'!$G9,FALSE)) | K9: =IFERROR(IF(ControladorDeProjetos367311121315[[#This Row],[Duração Real (em dias)]]=0,"",IF(ABS((ControladorDeProjetos367311121315[[#This Row],[Duração Real (em dias)]]-ControladorDeProjetos367311121315[[#This Row],[Duração Estimada (em dias)]])/ControladorDeProjetos367311121315[[#This Row],[Duração Estimada (em dias)]])>Sinalizador_Porcentagem,1,0)),"") | L9: =IF(COUNTA('Prot. TLD - 13 de Abril'!$I9,'Prot. TLD - 13 de Abril'!$J9)<>2,"",DAYS360('Prot. TLD - 13 de Abril'!$I9,'Prot. TLD - 13 de Abril'!$J9,FALSE))
H10: =IF(COUNTA('Prot. TLD - 13 de Abril'!$F10,'Prot. TLD - 13 de Abril'!$G10)<>2,"",DAYS360('Prot. TLD - 13 de Abril'!$F10,'Prot. TLD - 13 de Abril'!$G10,FALSE)) | K10: =IFERROR(IF(ControladorDeProjetos367311121315[[#This Row],[Duração Real (em dias)]]=0,"",IF(ABS((ControladorDeProjetos367311121315[[#This Row],[Duração Real (em dias)]]-ControladorDeProjetos367311121315[[#This Row],[Duração Estimada (em dias)]])/ControladorDeProjetos367311121315[[#This Row],[Duração Estimada (em dias)]])>Sinalizador_Porcentagem,1,0)),"") | L10: =IF(COUNTA('Prot. TLD - 13 de Abril'!$I10,'Prot. TLD - 13 de Abril'!$J10)<>2,"",DAYS360('Prot. TLD - 13 de Abril'!$I10,'Prot. TLD - 13 de Abril'!$J10,FALSE))
H11: =IF(COUNTA('Prot. TLD - 13 de Abril'!$F11,'Prot. TLD - 13 de Abril'!$G11)<>2,"",DAYS360('Prot. TLD - 13 de Abril'!$F11,'Prot. TLD - 13 de Abril'!$G11,FALSE)) | K11: =IFERROR(IF(ControladorDeProjetos367311121315[[#This Row],[Duração Real (em dias)]]=0,"",IF(ABS((ControladorDeProjetos367311121315[[#This Row],[Duração Real (em dias)]]-ControladorDeProjetos367311121315[[#This Row],[Duração Estimada (em dias)]])/ControladorDeProjetos367311121315[[#This Row],[Duração Estimada (em dias)]])>Sinalizador_Porcentagem,1,0)),"") | L11: =IF(COUNTA('Prot. TLD - 13 de Abril'!$I11,'Prot. TLD - 13 de Abril'!$J11)<>2,"",DAYS360('Prot. TLD - 13 de Abril'!$I11,'Prot. TLD - 13 de Abril'!$J11,FALSE))
H12: =IF(COUNTA('Prot. TLD - 13 de Abril'!$F12,'Prot. TLD - 13 de Abril'!$G12)<>2,"",DAYS360('Prot. TLD - 13 de Abril'!$F12,'Prot. TLD - 13 de Abril'!$G12,FALSE)) | K12: =IFERROR(IF(ControladorDeProjetos367311121315[[#This Row],[Duração Real (em dias)]]=0,"",IF(ABS((ControladorDeProjetos367311121315[[#This Row],[Duração Real (em dias)]]-ControladorDeProjetos367311121315[[#This Row],[Duração Estimada (em dias)]])/ControladorDeProjetos367311121315[[#This Row],[Duração Estimada (em dias)]])>Sinalizador_Porcentagem,1,0)),"") | L12: =IF(COUNTA('Prot. TLD - 13 de Abril'!$I12,'Prot. TLD - 13 de Abril'!$J12)<>2,"",DAYS360('Prot. TLD - 13 de Abril'!$I12,'Prot. TLD - 13 de Abril'!$J12,FALSE))
H13: =IF(COUNTA('Prot. TLD - 13 de Abril'!$F13,'Prot. TLD - 13 de Abril'!$G13)<>2,"",DAYS360('Prot. TLD - 13 de Abril'!$F13,'Prot. TLD - 13 de Abril'!$G13,FALSE)) | K13: =IFERROR(IF(ControladorDeProjetos367311121315[[#This Row],[Duração Real (em dias)]]=0,"",IF(ABS((ControladorDeProjetos367311121315[[#This Row],[Duração Real (em dias)]]-ControladorDeProjetos367311121315[[#This Row],[Duração Estimada (em dias)]])/ControladorDeProjetos367311121315[[#This Row],[Duração Estimada (em dias)]])>Sinalizador_Porcentagem,1,0)),"") | L13: =IF(COUNTA('Prot. TLD - 13 de Abril'!$I13,'Prot. TLD - 13 de Abril'!$J13)<>2,"",DAYS360('Prot. TLD - 13 de Abril'!$I13,'Prot. TLD - 13 de Abril'!$J13,FALSE))
H14: =IF(COUNTA('Prot. TLD - 13 de Abril'!$F14,'Prot. TLD - 13 de Abril'!$G14)<>2,"",DAYS360('Prot. TLD - 13 de Abril'!$F14,'Prot. TLD - 13 de Abril'!$G14,FALSE)) | K14: =IFERROR(IF(ControladorDeProjetos367311121315[[#This Row],[Duração Real (em dias)]]=0,"",IF(ABS((ControladorDeProjetos367311121315[[#This Row],[Duração Real (em dias)]]-ControladorDeProjetos367311121315[[#This Row],[Duração Estimada (em dias)]])/ControladorDeProjetos367311121315[[#This Row],[Duração Estimada (em dias)]])>Sinalizador_Porcentagem,1,0)),"") | L14: =IF(COUNTA('Prot. TLD - 13 de Abril'!$I14,'Prot. TLD - 13 de Abril'!$J14)<>2,"",DAYS360('Prot. TLD - 13 de Abril'!$I14,'Prot. TLD - 13 de Abril'!$J14,FALSE))
H15: =IF(COUNTA('Prot. TLD - 13 de Abril'!$F15,'Prot. TLD - 13 de Abril'!$G15)<>2,"",DAYS360('Prot. TLD - 13 de Abril'!$F15,'Prot. TLD - 13 de Abril'!$G15,FALSE)) | K15: =IFERROR(IF(ControladorDeProjetos367311121315[[#This Row],[Duração Real (em dias)]]=0,"",IF(ABS((ControladorDeProjetos367311121315[[#This Row],[Duração Real (em dias)]]-ControladorDeProjetos367311121315[[#This Row],[Duração Estimada (em dias)]])/ControladorDeProjetos367311121315[[#This Row],[Duração Estimada (em dias)]])>Sinalizador_Porcentagem,1,0)),"") | L15: =IF(COUNTA('Prot. TLD - 13 de Abril'!$I15,'Prot. TLD - 13 de Abril'!$J15)<>2,"",DAYS360('Prot. TLD - 13 de Abril'!$I15,'Prot. TLD - 13 de Abril'!$J15,FALSE))

Sheet Prot. TLD - Reserva do Lago
A1: Controlador De Protocolos Reserva do Lago - Toledo | G1: CNPJ PRATI: | H1: 35.538.973/0001-63
C2: Sinalizador de Porcentagem Acima/Abaixo:
A4: Status | B4: Protocolo | C4: Atividade | D4: Aprovações | E4: Atribuída a | F4: Estimado Início | G4: Estimado Término | H4: Duração Estimada (em dias) | I4: Real Início | J4: Real Término | K4: Sinalizador para duração real acima/abaixo (em dias)S | L4: Duração Real (em dias) | M4: Anotações | N4: Situação
A5: ANÁL | B5: 46.664 / 2025 | C5: Desmembramento | D5: Prefeitura Toledo | E5: Lavinia | F5: 45924 | H5: =IF(COUNTA('Prot. TLD - Reserva do Lago'!$F5,'Prot. TLD - Reserva do Lago'!$G5)<>2,"",DAYS360('Prot. TLD - Reserva do Lago'!$F5,'Prot. TLD - Reserva do Lago'!$G5,FALSE)) | K5: =IFERROR(IF(ControladorDeProjetos3673111213[[#This Row],[Duração Real (em dias)]]=0,"",IF(ABS((ControladorDeProjetos3673111213[[#This Row],[Duração Real (em dias)]]-ControladorDeProjetos3673111213[[#This Row],[Duração Estimada (em dias)]])/ControladorDeProjetos3673111213[[#This Row],[Duração Estimada (em dias)]])>Sinalizador_Porcentagem,1,0)),"") | L5: =IF(COUNTA('Prot. TLD - Reserva do Lago'!$I5,'Prot. TLD - Reserva do Lago'!$J5)<>2,"",DAYS360('Prot. TLD - Reserva do Lago'!$I5,'Prot. TLD - Reserva do Lago'!$J5,FALSE))
A6: ANÁL | B6: 16.482 / 2026 | C6: Impacto de vizinhança | D6: Prefeitura Toledo | E6: Lavinia | F6: 46113 | G6: 46143 | H6: =IF(COUNTA('Prot. TLD - Reserva do Lago'!$F6,'Prot. TLD - Reserva do Lago'!$G6)<>2,"",DAYS360('Prot. TLD - Reserva do Lago'!$F6,'Prot. TLD - Reserva do Lago'!$G6,FALSE)) -> 30 | K6: =IFERROR(IF(ControladorDeProjetos3673111213[[#This Row],[Duração Real (em dias)]]=0,"",IF(ABS((ControladorDeProjetos3673111213[[#This Row],[Duração Real (em dias)]]-ControladorDeProjetos3673111213[[#This Row],[Duração Estimada (em dias)]])/ControladorDeProjetos3673111213[[#This Row],[Duração Estimada (em dias)]])>Sinalizador_Porcentagem,1,0)),"") | L6: =IF(COUNTA('Prot. TLD - Reserva do Lago'!$I6,'Prot. TLD - Reserva do Lago'!$J6)<>2,"",DAYS360('Prot. TLD - Reserva do Lago'!$I6,'Prot. TLD - Reserva do Lago'!$J6,FALSE))
A7: APRO | B7: 355149 | C7: Solicitação de baixa na condição resolutivo da matricula | D7: Cartório Reg. Imóveis | E7: Eduarda | F7: 46113 | G7: 46143 | H7: =IF(COUNTA('Prot. TLD - Reserva do Lago'!$F7,'Prot. TLD - Reserva do Lago'!$G7)<>2,"",DAYS360('Prot. TLD - Reserva do Lago'!$F7,'Prot. TLD - Reserva do Lago'!$G7,FALSE)) -> 30 | I7: 46112 | J7: 46125 | K7: =IFERROR(IF(ControladorDeProjetos3673111213[[#This Row],[Duração Real (em dias)]]=0,"",IF(ABS((ControladorDeProjetos3673111213[[#This Row],[Duração Real (em dias)]]-ControladorDeProjetos3673111213[[#This Row],[Duração Estimada (em dias)]])/ControladorDeProjetos3673111213[[#This Row],[Duração Estimada (em dias)]])>Sinalizador_Porcentagem,1,0)),"") -> 1 | L7: =IF(COUNTA('Prot. TLD - Reserva do Lago'!$I7,'Prot. TLD - Reserva do Lago'!$J7)<>2,"",DAYS360('Prot. TLD - Reserva do Lago'!$I7,'Prot. TLD - Reserva do Lago'!$J7,FALSE)) -> 13
A8: ANÁL | B8: 6D6B59C9F0 | D8: ANAC | E8: Michael | H8: =IF(COUNTA('Prot. TLD - Reserva do Lago'!$F8,'Prot. TLD - Reserva do Lago'!$G8)<>2,"",DAYS360('Prot. TLD - Reserva do Lago'!$F8,'Prot. TLD - Reserva do Lago'!$G8,FALSE)) | K8: =IFERROR(IF(ControladorDeProjetos3673111213[[#This Row],[Duração Real (em dias)]]=0,"",IF(ABS((ControladorDeProjetos3673111213[[#This Row],[Duração Real (em dias)]]-ControladorDeProjetos3673111213[[#This Row],[Duração Estimada (em dias)]])/ControladorDeProjetos3673111213[[#This Row],[Duração Estimada (em dias)]])>Sinalizador_Porcentagem,1,0)),"") | L8: =IF(COUNTA('Prot. TLD - Reserva do Lago'!$I8,'Prot. TLD - Reserva do Lago'!$J8)<>2,"",DAYS360('Prot. TLD - Reserva do Lago'!$I8,'Prot. TLD - Reserva do Lago'!$J8,FALSE))
A9: ANÁL | B9: 21.524 / 2026 | C9: Anuência Prévia | D9: Prefeitura Toledo | E9: Lavinia | F9: 46141 | G9: 46171 | H9: =IF(COUNTA('Prot. TLD - Reserva do Lago'!$F9,'Prot. TLD - Reserva do Lago'!$G9)<>2,"",DAYS360('Prot. TLD - Reserva do Lago'!$F9,'Prot. TLD - Reserva do Lago'!$G9,FALSE)) -> 30 | K9: =IFERROR(IF(ControladorDeProjetos3673111213[[#This Row],[Duração Real (em dias)]]=0,"",IF(ABS((ControladorDeProjetos3673111213[[#This Row],[Duração Real (em dias)]]-ControladorDeProjetos3673111213[[#This Row],[Duração Estimada (em dias)]])/ControladorDeProjetos3673111213[[#This Row],[Duração Estimada (em dias)]])>Sinalizador_Porcentagem,1,0)),"") | L9: =IF(COUNTA('Prot. TLD - Reserva do Lago'!$I9,'Prot. TLD - Reserva do Lago'!$J9)<>2,"",DAYS360('Prot. TLD - Reserva do Lago'!$I9,'Prot. TLD - Reserva do Lago'!$J9,FALSE))
A10: APRO | B10: 20264175634246 | C10: CARTA VIABILIDADE | D10: Copel | E10: Eduarda | H10: =IF(COUNTA('Prot. TLD - Reserva do Lago'!$F10,'Prot. TLD - Reserva do Lago'!$G10)<>2,"",DAYS360('Prot. TLD - Reserva do Lago'!$F10,'Prot. TLD - Reserva do Lago'!$G10,FALSE)) | K10: =IFERROR(IF(ControladorDeProjetos3673111213[[#This Row],[Duração Real (em dias)]]=0,"",IF(ABS((ControladorDeProjetos3673111213[[#This Row],[Duração Real (em dias)]]-ControladorDeProjetos3673111213[[#This Row],[Duração Estimada (em dias)]])/ControladorDeProjetos3673111213[[#This Row],[Duração Estimada (em dias)]])>Sinalizador_Porcentagem,1,0)),"") | L10: =IF(COUNTA('Prot. TLD - Reserva do Lago'!$I10,'Prot. TLD - Reserva do Lago'!$J10)<>2,"",DAYS360('Prot. TLD - Reserva do Lago'!$I10,'Prot. TLD - Reserva do Lago'!$J10,FALSE))
H11: =IF(COUNTA('Prot. TLD - Reserva do Lago'!$F11,'Prot. TLD - Reserva do Lago'!$G11)<>2,"",DAYS360('Prot. TLD - Reserva do Lago'!$F11,'Prot. TLD - Reserva do Lago'!$G11,FALSE)) | K11: =IFERROR(IF(ControladorDeProjetos3673111213[[#This Row],[Duração Real (em dias)]]=0,"",IF(ABS((ControladorDeProjetos3673111213[[#This Row],[Duração Real (em dias)]]-ControladorDeProjetos3673111213[[#This Row],[Duração Estimada (em dias)]])/ControladorDeProjetos3673111213[[#This Row],[Duração Estimada (em dias)]])>Sinalizador_Porcentagem,1,0)),"") | L11: =IF(COUNTA('Prot. TLD - Reserva do Lago'!$I11,'Prot. TLD - Reserva do Lago'!$J11)<>2,"",DAYS360('Prot. TLD - Reserva do Lago'!$I11,'Prot. TLD - Reserva do Lago'!$J11,FALSE))
H12: =IF(COUNTA('Prot. TLD - Reserva do Lago'!$F12,'Prot. TLD - Reserva do Lago'!$G12)<>2,"",DAYS360('Prot. TLD - Reserva do Lago'!$F12,'Prot. TLD - Reserva do Lago'!$G12,FALSE)) | K12: =IFERROR(IF(ControladorDeProjetos3673111213[[#This Row],[Duração Real (em dias)]]=0,"",IF(ABS((ControladorDeProjetos3673111213[[#This Row],[Duração Real (em dias)]]-ControladorDeProjetos3673111213[[#This Row],[Duração Estimada (em dias)]])/ControladorDeProjetos3673111213[[#This Row],[Duração Estimada (em dias)]])>Sinalizador_Porcentagem,1,0)),"") | L12: =IF(COUNTA('Prot. TLD - Reserva do Lago'!$I12,'Prot. TLD - Reserva do Lago'!$J12)<>2,"",DAYS360('Prot. TLD - Reserva do Lago'!$I12,'Prot. TLD - Reserva do Lago'!$J12,FALSE))
H13: =IF(COUNTA('Prot. TLD - Reserva do Lago'!$F13,'Prot. TLD - Reserva do Lago'!$G13)<>2,"",DAYS360('Prot. TLD - Reserva do Lago'!$F13,'Prot. TLD - Reserva do Lago'!$G13,FALSE)) | K13: =IFERROR(IF(ControladorDeProjetos3673111213[[#This Row],[Duração Real (em dias)]]=0,"",IF(ABS((ControladorDeProjetos3673111213[[#This Row],[Duração Real (em dias)]]-ControladorDeProjetos3673111213[[#This Row],[Duração Estimada (em dias)]])/ControladorDeProjetos3673111213[[#This Row],[Duração Estimada (em dias)]])>Sinalizador_Porcentagem,1,0)),"") | L13: =IF(COUNTA('Prot. TLD - Reserva do Lago'!$I13,'Prot. TLD - Reserva do Lago'!$J13)<>2,"",DAYS360('Prot. TLD - Reserva do Lago'!$I13,'Prot. TLD - Reserva do Lago'!$J13,FALSE))
H14: =IF(COUNTA('Prot. TLD - Reserva do Lago'!$F14,'Prot. TLD - Reserva do Lago'!$G14)<>2,"",DAYS360('Prot. TLD - Reserva do Lago'!$F14,'Prot. TLD - Reserva do Lago'!$G14,FALSE)) | K14: =IFERROR(IF(ControladorDeProjetos3673111213[[#This Row],[Duração Real (em dias)]]=0,"",IF(ABS((ControladorDeProjetos3673111213[[#This Row],[Duração Real (em dias)]]-ControladorDeProjetos3673111213[[#This Row],[Duração Estimada (em dias)]])/ControladorDeProjetos3673111213[[#This Row],[Duração Estimada (em dias)]])>Sinalizador_Porcentagem,1,0)),"") | L14: =IF(COUNTA('Prot. TLD - Reserva do Lago'!$I14,'Prot. TLD - Reserva do Lago'!$J14)<>2,"",DAYS360('Prot. TLD - Reserva do Lago'!$I14,'Prot. TLD - Reserva do Lago'!$J14,FALSE))
H15: =IF(COUNTA('Prot. TLD - Reserva do Lago'!$F15,'Prot. TLD - Reserva do Lago'!$G15)<>2,"",DAYS360('Prot. TLD - Reserva do Lago'!$F15,'Prot. TLD - Reserva do Lago'!$G15,FALSE)) | K15: =IFERROR(IF(ControladorDeProjetos3673111213[[#This Row],[Duração Real (em dias)]]=0,"",IF(ABS((ControladorDeProjetos3673111213[[#This Row],[Duração Real (em dias)]]-ControladorDeProjetos3673111213[[#This Row],[Duração Estimada (em dias)]])/ControladorDeProjetos3673111213[[#This Row],[Duração Estimada (em dias)]])>Sinalizador_Porcentagem,1,0)),"") | L15: =IF(COUNTA('Prot. TLD - Reserva do Lago'!$I15,'Prot. TLD - Reserva do Lago'!$J15)<>2,"",DAYS360('Prot. TLD - Reserva do Lago'!$I15,'Prot. TLD - Reserva do Lago'!$J15,FALSE))

Sheet Prot. TLD - Lot. Vera Cruz
A1: Controlador De Protocolos Loteamento Vera Cruz - Toledo | G1: CNPJ PRATI: | H1: 35.538.973/0001-63
C2: Sinalizador de Porcentagem Acima/Abaixo:
A4: Status | B4: Projeto + Protocolo | C4: Atividade | D4: Aprovações | E4: Atribuída a | F4: Estimado Início | G4: Estimado Término | H4: Duração Estimada (em dias) | I4: Real Início | J4: Real Término | K4: Sinalizador para duração real acima/abaixo (em dias)S | L4: Duração Real (em dias) | M4: Anotações | N4: Situação
A5: CANC | B5: Vera Cruz - 20245786446752 | C5: Aprovação de projeto elétrico | D5: Copel | E5: Taciana | F5: 45322 | G5: 45352 | H5: =ControladorDeProjetos36[[#This Row],[Estimado Término]]-ControladorDeProjetos36[[#This Row],[Estimado Início]] -> 30 | I5: 45322 | J5: 45338 | K5: =IFERROR(IF(ControladorDeProjetos36[[#This Row],[Duração Real (em dias)]]=0,"",IF(ABS((ControladorDeProjetos36[[#This Row],[Duração Real (em dias)]]-ControladorDeProjetos36[[#This Row],[Duração Estimada (em dias)]])/ControladorDeProjetos36[[#This Row],[Duração Estimada (em dias)]])>Sinalizador_Porcentagem,1,0)),"") -> 1 | L5: =IF(COUNTA('Prot. TLD - Lot. Vera Cruz'!$I5,'Prot. TLD - Lot. Vera Cruz'!$J5)<>2,"",DAYS360('Prot. TLD - Lot. Vera Cruz'!$I5,'Prot. TLD - Lot. Vera Cruz'!$J5,FALSE)) -> 16 | M5: Protocolo aberto pelo projetista Germano W. | N5: Reprovado. Necessários correções e abertura de novo protocolo.
A6: CANC | B6: Vera Cruz - 20245974227560 | C6: Aprovação de projeto elétrico | D6: Copel | E6: Taciana | F6: 45349 | G6: 45378 | H6: =ControladorDeProjetos36[[#This Row],[Estimado Término]]-ControladorDeProjetos36[[#This Row],[Estimado Início]] -> 29 | I6: 45349 | K6: =IFERROR(IF(ControladorDeProjetos36[[#This Row],[Duração Real (em dias)]]=0,"",IF(ABS((ControladorDeProjetos36[[#This Row],[Duração Real (em dias)]]-ControladorDeProjetos36[[#This Row],[Duração Estimada (em dias)]])/ControladorDeProjetos36[[#This Row],[Duração Estimada (em dias)]])>Sinalizador_Porcentagem,1,0)),"") | L6: =IF(COUNTA('Prot. TLD - Lot. Vera Cruz'!$I6,'Prot. TLD - Lot. Vera Cruz'!$J6)<>2,"",DAYS360('Prot. TLD - Lot. Vera Cruz'!$I6,'Prot. TLD - Lot. Vera Cruz'!$J6,FALSE)) | M6: Protocolo aberto pelo projetista Germano W.
A7: CANC | B7: Vera Cruz - 22573/2023 | C7: Solicita alvará de parcelamento do solo | D7: Prefeitura Toledo | E7: Taciana | F7: 45057 | G7: 45423 | H7: =ControladorDeProjetos36[[#This Row],[Estimado Término]]-ControladorDeProjetos36[[#This Row],[Estimado Início]] -> 366 | I7: 45057 | K7: =IFERROR(IF(ControladorDeProjetos36[[#This Row],[Duração Real (em dias)]]=0,"",IF(ABS((ControladorDeProjetos36[[#This Row],[Duração Real (em dias)]]-ControladorDeProjetos36[[#This Row],[Duração Estimada (em dias)]])/ControladorDeProjetos36[[#This Row],[Duração Estimada (em dias)]])>Sinalizador_Porcentagem,1,0)),"") | L7: =IF(COUNTA('Prot. TLD - Lot. Vera Cruz'!$I7,'Prot. TLD - Lot. Vera Cruz'!$J7)<>2,"",DAYS360('Prot. TLD - Lot. Vera Cruz'!$I7,'Prot. TLD - Lot. Vera Cruz'!$J7,FALSE)) | M7: Protocolo aberto pela projetista Ana Cella Tramarim | N7: Aguardando liberação do projeto elétrico pela Copel
A8: APRO | B8: PRAD Vera Cruz - 21.658.811-8 | C8: Apresentação do segungo relatório de monitoramento da área PRAD | D8: IAT | E8: Taciana | F8: 45322 | G8: =ControladorDeProjetos36[[#This Row],[Estimado Início]]+30 -> 45352 | H8: =ControladorDeProjetos36[[#This Row],[Estimado Término]]-ControladorDeProjetos36[[#This Row],[Estimado Início]] -> 30 | I8: 45322 | K8: =IFERROR(IF(ControladorDeProjetos36[[#This Row],[Duração Real (em dias)]]=0,"",IF(ABS((ControladorDeProjetos36[[#This Row],[Duração Real (em dias)]]-ControladorDeProjetos36[[#This Row],[Duração Estimada (em dias)]])/ControladorDeProjetos36[[#This Row],[Duração Estimada (em dias)]])>Sinalizador_Porcentagem,1,0)),"") | L8: =IF(COUNTA('Prot. TLD - Lot. Vera Cruz'!$I8,'Prot. TLD - Lot. Vera Cruz'!$J8)<>2,"",DAYS360('Prot. TLD - Lot. Vera Cruz'!$I8,'Prot. TLD - Lot. Vera Cruz'!$J8,FALSE)) | M8: Protocolo aberto pelo Eng. Florestal Yuri Coelho | N8: Protocolo aberto para envio dos relatórios de monitoramento.
A9: APRO | B9: SEDE ÉLIO - 42467 / 2024 | C9: Solicitação a COMURB para condominio residencial horizontal | D9: Prefeitura Toledo | E9: Taciana | F9: 45532 | G9: 45563 | H9: =ControladorDeProjetos36[[#This Row],[Estimado Término]]-ControladorDeProjetos36[[#This Row],[Estimado Início]] -> 31 | I9: 45532 | J9: 45589 | K9: =IFERROR(IF(ControladorDeProjetos36[[#This Row],[Duração Real (em dias)]]=0,"",IF(ABS((ControladorDeProjetos36[[#This Row],[Duração Real (em dias)]]-ControladorDeProjetos36[[#This Row],[Duração Estimada (em dias)]])/ControladorDeProjetos36[[#This Row],[Duração Estimada (em dias)]])>Sinalizador_Porcentagem,1,0)),"") -> 1 | L9: =IF(COUNTA('Prot. TLD - Lot. Vera Cruz'!$I9,'Prot. TLD - Lot. Vera Cruz'!$J9)<>2,"",DAYS360('Prot. TLD - Lot. Vera Cruz'!$I9,'Prot. TLD - Lot. Vera Cruz'!$J9,FALSE)) -> 56 | N9: Concluído
K10: =IFERROR(IF(ControladorDeProjetos36[[#This Row],[Duração Real (em dias)]]=0,"",IF(ABS((ControladorDeProjetos36[[#This Row],[Duração Real (em dias)]]-ControladorDeProjetos36[[#This Row],[Duração Estimada (em dias)]])/ControladorDeProjetos36[[#This Row],[Duração Estimada (em dias)]])>Sinalizador_Porcentagem,1,0)),"") | L10: =IF(COUNTA('Prot. TLD - Lot. Vera Cruz'!$I10,'Prot. TLD - Lot. Vera Cruz'!$J10)<>2,"",DAYS360('Prot. TLD - Lot. Vera Cruz'!$I10,'Prot. TLD - Lot. Vera Cruz'!$J10,FALSE))
K11: =IFERROR(IF(ControladorDeProjetos36[[#This Row],[Duração Real (em dias)]]=0,"",IF(ABS((ControladorDeProjetos36[[#This Row],[Duração Real (em dias)]]-ControladorDeProjetos36[[#This Row],[Duração Estimada (em dias)]])/ControladorDeProjetos36[[#This Row],[Duração Estimada (em dias)]])>Sinalizador_Porcentagem,1,0)),"") | L11: =IF(COUNTA('Prot. TLD - Lot. Vera Cruz'!$I11,'Prot. TLD - Lot. Vera Cruz'!$J11)<>2,"",DAYS360('Prot. TLD - Lot. Vera Cruz'!$I11,'Prot. TLD - Lot. Vera Cruz'!$J11,FALSE))
K12: =IFERROR(IF(ControladorDeProjetos36[[#This Row],[Duração Real (em dias)]]=0,"",IF(ABS((ControladorDeProjetos36[[#This Row],[Duração Real (em dias)]]-ControladorDeProjetos36[[#This Row],[Duração Estimada (em dias)]])/ControladorDeProjetos36[[#This Row],[Duração Estimada (em dias)]])>Sinalizador_Porcentagem,1,0)),"") | L12: =IF(COUNTA('Prot. TLD - Lot. Vera Cruz'!$I12,'Prot. TLD - Lot. Vera Cruz'!$J12)<>2,"",DAYS360('Prot. TLD - Lot. Vera Cruz'!$I12,'Prot. TLD - Lot. Vera Cruz'!$J12,FALSE))
K13: =IFERROR(IF(ControladorDeProjetos36[[#This Row],[Duração Real (em dias)]]=0,"",IF(ABS((ControladorDeProjetos36[[#This Row],[Duração Real (em dias)]]-ControladorDeProjetos36[[#This Row],[Duração Estimada (em dias)]])/ControladorDeProjetos36[[#This Row],[Duração Estimada (em dias)]])>Sinalizador_Porcentagem,1,0)),"") | L13: =IF(COUNTA('Prot. TLD - Lot. Vera Cruz'!$I13,'Prot. TLD - Lot. Vera Cruz'!$J13)<>2,"",DAYS360('Prot. TLD - Lot. Vera Cruz'!$I13,'Prot. TLD - Lot. Vera Cruz'!$J13,FALSE))
K14: =IFERROR(IF(ControladorDeProjetos36[[#This Row],[Duração Real (em dias)]]=0,"",IF(ABS((ControladorDeProjetos36[[#This Row],[Duração Real (em dias)]]-ControladorDeProjetos36[[#This Row],[Duração Estimada (em dias)]])/ControladorDeProjetos36[[#This Row],[Duração Estimada (em dias)]])>Sinalizador_Porcentagem,1,0)),"") | L14: =IF(COUNTA('Prot. TLD - Lot. Vera Cruz'!$I14,'Prot. TLD - Lot. Vera Cruz'!$J14)<>2,"",DAYS360('Prot. TLD - Lot. Vera Cruz'!$I14,'Prot. TLD - Lot. Vera Cruz'!$J14,FALSE))
K15: =IFERROR(IF(ControladorDeProjetos36[[#This Row],[Duração Real (em dias)]]=0,"",IF(ABS((ControladorDeProjetos36[[#This Row],[Duração Real (em dias)]]-ControladorDeProjetos36[[#This Row],[Duração Estimada (em dias)]])/ControladorDeProjetos36[[#This Row],[Duração Estimada (em dias)]])>Sinalizador_Porcentagem,1,0)),"") | L15: =IF(COUNTA('Prot. TLD - Lot. Vera Cruz'!$I15,'Prot. TLD - Lot. Vera Cruz'!$J15)<>2,"",DAYS360('Prot. TLD - Lot. Vera Cruz'!$I15,'Prot. TLD - Lot. Vera Cruz'!$J15,FALSE))

Sheet Prot. TLD - Lot. Ludovico
A1: Controlador De Protocolos Loteamento Ludovico - Toledo | G1: CNPJ PRATI: | H1: 35.538.973/0001-63
C2: Sinalizador de Porcentagem Acima/Abaixo:
A4: Status | B4: Projeto + Protocolo | C4: Atividade | D4: Aprovações | E4: Atribuída a | F4: Estimado Início | G4: Estimado Término | H4: Duração Estimada (em dias) | I4: Real Início | J4: Real Término | K4: Sinalizador para duração real acima/abaixo (em dias)S | L4: Duração Real (em dias) | M4: Anotações | N4: Situação
A5: CANC | B5: Ludovico - 332.058 | D5: Cartório Reg. Imóveis | E5: Giovana | F5: 45421 | G5: 45450 | H5: =IF(COUNTA('Prot. TLD - Lot. Ludovico'!$F5,'Prot. TLD - Lot. Ludovico'!$G5)<>2,"",DAYS360('Prot. TLD - Lot. Ludovico'!$F5,'Prot. TLD - Lot. Ludovico'!$G5,FALSE)) -> 28 | I5: 45421 | J5: 45453 | K5: =IFERROR(IF(ControladorDeProjetos367[[#This Row],[Duração Real (em dias)]]=0,"",IF(ABS((ControladorDeProjetos367[[#This Row],[Duração Real (em dias)]]-ControladorDeProjetos367[[#This Row],[Duração Estimada (em dias)]])/ControladorDeProjetos367[[#This Row],[Duração Estimada (em dias)]])>Sinalizador_Porcentagem,1,0)),"") -> 1 | L5: =IF(COUNTA('Prot. TLD - Lot. Ludovico'!$I5,'Prot. TLD - Lot. Ludovico'!$J5)<>2,"",DAYS360('Prot. TLD - Lot. Ludovico'!$I5,'Prot. TLD - Lot. Ludovico'!$J5,FALSE)) -> 31 | N5: Cancelado
A6: CANC | B6: Ludovico - 338.368 | C6: Cancelamento do SISLEG | D6: Cartório Reg. Imóveis | E6: Taciana | F6: 45614 | G6: 45629 | H6: =IF(COUNTA('Prot. TLD - Lot. Ludovico'!$F6,'Prot. TLD - Lot. Ludovico'!$G6)<>2,"",DAYS360('Prot. TLD - Lot. Ludovico'!$F6,'Prot. TLD - Lot. Ludovico'!$G6,FALSE)) -> 15 | I6: 45614 | J6: 45632 | K6: =IFERROR(IF(ControladorDeProjetos367[[#This Row],[Duração Real (em dias)]]=0,"",IF(ABS((ControladorDeProjetos367[[#This Row],[Duração Real (em dias)]]-ControladorDeProjetos367[[#This Row],[Duração Estimada (em dias)]])/ControladorDeProjetos367[[#This Row],[Duração Estimada (em dias)]])>Sinalizador_Porcentagem,1,0)),"") -> 1 | L6: =IF(COUNTA('Prot. TLD - Lot. Ludovico'!$I6,'Prot. TLD - Lot. Ludovico'!$J6)<>2,"",DAYS360('Prot. TLD - Lot. Ludovico'!$I6,'Prot. TLD - Lot. Ludovico'!$J6,FALSE)) -> 18 | M6: 03/12/2024 - Diligências | N6: Diligência a Retirar
A7: CANC | B7: Ludovico - 336.710 | D7: Cartório Reg. Imóveis | F7: 45566 | G7: 45580 | H7: =IF(COUNTA('Prot. TLD - Lot. Ludovico'!$F7,'Prot. TLD - Lot. Ludovico'!$G7)<>2,"",DAYS360('Prot. TLD - Lot. Ludovico'!$F7,'Prot. TLD - Lot. Ludovico'!$G7,FALSE)) -> 14 | I7: 45566 | J7: 45624 | K7: =IFERROR(IF(ControladorDeProjetos367[[#This Row],[Duração Real (em dias)]]=0,"",IF(ABS((ControladorDeProjetos367[[#This Row],[Duração Real (em dias)]]-ControladorDeProjetos367[[#This Row],[Duração Estimada (em dias)]])/ControladorDeProjetos367[[#This Row],[Duração Estimada (em dias)]])>Sinalizador_Porcentagem,1,0)),"") -> 1 | L7: =IF(COUNTA('Prot. TLD - Lot. Ludovico'!$I7,'Prot. TLD - Lot. Ludovico'!$J7)<>2,"",DAYS360('Prot. TLD - Lot. Ludovico'!$I7,'Prot. TLD - Lot. Ludovico'!$J7,FALSE)) -> 57 | N7: Cancelado
H8: =IF(COUNTA('Prot. TLD - Lot. Ludovico'!$F8,'Prot. TLD - Lot. Ludovico'!$G8)<>2,"",DAYS360('Prot. TLD - Lot. Ludovico'!$F8,'Prot. TLD - Lot. Ludovico'!$G8,FALSE)) | K8: =IFERROR(IF(ControladorDeProjetos367[[#This Row],[Duração Real (em dias)]]=0,"",IF(ABS((ControladorDeProjetos367[[#This Row],[Duração Real (em dias)]]-ControladorDeProjetos367[[#This Row],[Duração Estimada (em dias)]])/ControladorDeProjetos367[[#This Row],[Duração Estimada (em dias)]])>Sinalizador_Porcentagem,1,0)),"") | L8: =IF(COUNTA('Prot. TLD - Lot. Ludovico'!$I8,'Prot. TLD - Lot. Ludovico'!$J8)<>2,"",DAYS360('Prot. TLD - Lot. Ludovico'!$I8,'Prot. TLD - Lot. Ludovico'!$J8,FALSE))
H9: =IF(COUNTA('Prot. TLD - Lot. Ludovico'!$F9,'Prot. TLD - Lot. Ludovico'!$G9)<>2,"",DAYS360('Prot. TLD - Lot. Ludovico'!$F9,'Prot. TLD - Lot. Ludovico'!$G9,FALSE)) | K9: =IFERROR(IF(ControladorDeProjetos367[[#This Row],[Duração Real (em dias)]]=0,"",IF(ABS((ControladorDeProjetos367[[#This Row],[Duração Real (em dias)]]-ControladorDeProjetos367[[#This Row],[Duração Estimada (em dias)]])/ControladorDeProjetos367[[#This Row],[Duração Estimada (em dias)]])>Sinalizador_Porcentagem,1,0)),"") | L9: =IF(COUNTA('Prot. TLD - Lot. Ludovico'!$I9,'Prot. TLD - Lot. Ludovico'!$J9)<>2,"",DAYS360('Prot. TLD - Lot. Ludovico'!$I9,'Prot. TLD - Lot. Ludovico'!$J9,FALSE))
H10: =IF(COUNTA('Prot. TLD - Lot. Ludovico'!$F10,'Prot. TLD - Lot. Ludovico'!$G10)<>2,"",DAYS360('Prot. TLD - Lot. Ludovico'!$F10,'Prot. TLD - Lot. Ludovico'!$G10,FALSE)) | K10: =IFERROR(IF(ControladorDeProjetos367[[#This Row],[Duração Real (em dias)]]=0,"",IF(ABS((ControladorDeProjetos367[[#This Row],[Duração Real (em dias)]]-ControladorDeProjetos367[[#This Row],[Duração Estimada (em dias)]])/ControladorDeProjetos367[[#This Row],[Duração Estimada (em dias)]])>Sinalizador_Porcentagem,1,0)),"") | L10: =IF(COUNTA('Prot. TLD - Lot. Ludovico'!$I10,'Prot. TLD - Lot. Ludovico'!$J10)<>2,"",DAYS360('Prot. TLD - Lot. Ludovico'!$I10,'Prot. TLD - Lot. Ludovico'!$J10,FALSE))
H11: =IF(COUNTA('Prot. TLD - Lot. Ludovico'!$F11,'Prot. TLD - Lot. Ludovico'!$G11)<>2,"",DAYS360('Prot. TLD - Lot. Ludovico'!$F11,'Prot. TLD - Lot. Ludovico'!$G11,FALSE)) | K11: =IFERROR(IF(ControladorDeProjetos367[[#This Row],[Duração Real (em dias)]]=0,"",IF(ABS((ControladorDeProjetos367[[#This Row],[Duração Real (em dias)]]-ControladorDeProjetos367[[#This Row],[Duração Estimada (em dias)]])/ControladorDeProjetos367[[#This Row],[Duração Estimada (em dias)]])>Sinalizador_Porcentagem,1,0)),"") | L11: =IF(COUNTA('Prot. TLD - Lot. Ludovico'!$I11,'Prot. TLD - Lot. Ludovico'!$J11)<>2,"",DAYS360('Prot. TLD - Lot. Ludovico'!$I11,'Prot. TLD - Lot. Ludovico'!$J11,FALSE))
H12: =IF(COUNTA('Prot. TLD - Lot. Ludovico'!$F12,'Prot. TLD - Lot. Ludovico'!$G12)<>2,"",DAYS360('Prot. TLD - Lot. Ludovico'!$F12,'Prot. TLD - Lot. Ludovico'!$G12,FALSE)) | K12: =IFERROR(IF(ControladorDeProjetos367[[#This Row],[Duração Real (em dias)]]=0,"",IF(ABS((ControladorDeProjetos367[[#This Row],[Duração Real (em dias)]]-ControladorDeProjetos367[[#This Row],[Duração Estimada (em dias)]])/ControladorDeProjetos367[[#This Row],[Duração Estimada (em dias)]])>Sinalizador_Porcentagem,1,0)),"") | L12: =IF(COUNTA('Prot. TLD - Lot. Ludovico'!$I12,'Prot. TLD - Lot. Ludovico'!$J12)<>2,"",DAYS360('Prot. TLD - Lot. Ludovico'!$I12,'Prot. TLD - Lot. Ludovico'!$J12,FALSE))
H13: =IF(COUNTA('Prot. TLD - Lot. Ludovico'!$F13,'Prot. TLD - Lot. Ludovico'!$G13)<>2,"",DAYS360('Prot. TLD - Lot. Ludovico'!$F13,'Prot. TLD - Lot. Ludovico'!$G13,FALSE)) | K13: =IFERROR(IF(ControladorDeProjetos367[[#This Row],[Duração Real (em dias)]]=0,"",IF(ABS((ControladorDeProjetos367[[#This Row],[Duração Real (em dias)]]-ControladorDeProjetos367[[#This Row],[Duração Estimada (em dias)]])/ControladorDeProjetos367[[#This Row],[Duração Estimada (em dias)]])>Sinalizador_Porcentagem,1,0)),"") | L13: =IF(COUNTA('Prot. TLD - Lot. Ludovico'!$I13,'Prot. TLD - Lot. Ludovico'!$J13)<>2,"",DAYS360('Prot. TLD - Lot. Ludovico'!$I13,'Prot. TLD - Lot. Ludovico'!$J13,FALSE))
H14: =IF(COUNTA('Prot. TLD - Lot. Ludovico'!$F14,'Prot. TLD - Lot. Ludovico'!$G14)<>2,"",DAYS360('Prot. TLD - Lot. Ludovico'!$F14,'Prot. TLD - Lot. Ludovico'!$G14,FALSE)) | K14: =IFERROR(IF(ControladorDeProjetos367[[#This Row],[Duração Real (em dias)]]=0,"",IF(ABS((ControladorDeProjetos367[[#This Row],[Duração Real (em dias)]]-ControladorDeProjetos367[[#This Row],[Duração Estimada (em dias)]])/ControladorDeProjetos367[[#This Row],[Duração Estimada (em dias)]])>Sinalizador_Porcentagem,1,0)),"") | L14: =IF(COUNTA('Prot. TLD - Lot. Ludovico'!$I14,'Prot. TLD - Lot. Ludovico'!$J14)<>2,"",DAYS360('Prot. TLD - Lot. Ludovico'!$I14,'Prot. TLD - Lot. Ludovico'!$J14,FALSE))
H15: =IF(COUNTA('Prot. TLD - Lot. Ludovico'!$F15,'Prot. TLD - Lot. Ludovico'!$G15)<>2,"",DAYS360('Prot. TLD - Lot. Ludovico'!$F15,'Prot. TLD - Lot. Ludovico'!$G15,FALSE)) | K15: =IFERROR(IF(ControladorDeProjetos367[[#This Row],[Duração Real (em dias)]]=0,"",IF(ABS((ControladorDeProjetos367[[#This Row],[Duração Real (em dias)]]-ControladorDeProjetos367[[#This Row],[Duração Estimada (em dias)]])/ControladorDeProjetos367[[#This Row],[Duração Estimada (em dias)]])>Sinalizador_Porcentagem,1,0)),"") | L15: =IF(COUNTA('Prot. TLD - Lot. Ludovico'!$I15,'Prot. TLD - Lot. Ludovico'!$J15)<>2,"",DAYS360('Prot. TLD - Lot. Ludovico'!$I15,'Prot. TLD - Lot. Ludovico'!$J15,FALSE))

Sheet Prot. TLD - Lot. Gualtieri
B1: Controlador De Protocolos Loteamentol Gualtieri - Toledo
C2: Sinalizador de Porcentagem Acima/Abaixo:
A4: STATUS | B4: Projeto + Protocolo | C4: Atividade | D4: Aprovações | E4: Atribuída a | F4: Estimado Início | G4: Estimado Término | H4: Duração Estimada (em dias) | I4: Real Início | J4: Real Término | K4: Duração Real (em dias) | L4: Anotações | M4: Situação
A5: APRO | B5: Gualtieri - 1628/2024 | C5: Verificação do ISSQN - Solicitação Depto da Receita - Versão: 6 | D5: Prefeitura Toledo | E5: Taciana | F5: 45303 | G5: 45383 | H5: =ControladorDeProjetos510[[#This Row],[Estimado Término]]-ControladorDeProjetos510[[#This Row],[Estimado Início]] -> 80 | I5: 45303 | J5: 45349 | K5: =ControladorDeProjetos510[[#This Row],[Real Término]]-ControladorDeProjetos510[[#This Row],[Real Início]] -> 46 | M5: Concluído
A6: APRO | B6: Parque - 63185/2023 | C6: Solicitação de vistoria de conclusão de obras. Solicitação Secret do Planejamento Estratégico - Versão: 3 | D6: Prefeitura Toledo | E6: Taciana | F6: 45279 | G6: 45352 | H6: =ControladorDeProjetos510[[#This Row],[Estimado Término]]-ControladorDeProjetos510[[#This Row],[Estimado Início]] -> 73 | I6: 45280 | J6: 45349 | K6: =ControladorDeProjetos510[[#This Row],[Real Término]]-ControladorDeProjetos510[[#This Row],[Real Início]] -> 69 | L6: Decreto entregue dia 27/02/2024 | M6: Concluído
A7: APRO | B7: PRAD Gualtieri - 1290/2024 | C7: Apresentação de relatório de monitoramento ambiental referente ao plantio de mudas como compensação ambiental às autorizações florestais do Loteamento Gualtieri, em atendimento ao Termo de Compromisso firmado entre a Prati Empreendimentos LTDA e o Município de Toledo. | D7: Prefeitura Toledo | E7: Taciana | F7: 45301 | G7: 45332 | H7: =ControladorDeProjetos510[[#This Row],[Estimado Término]]-ControladorDeProjetos510[[#This Row],[Estimado Início]] -> 31 | I7: 45301 | J7: 45352 | K7: =ControladorDeProjetos510[[#This Row],[Real Término]]-ControladorDeProjetos510[[#This Row],[Real Início]] -> 51 | M7: Concluído
A8: APRO | B8: PRAD Gualtieri - 21.798.998-1 | C8: Relatórios de conclusão de plantio de mudas, acompanhados de seus respectivos requerimentos de mudas junto ao viveiro florestal do IAT, referente à compensação ambiental sobre as autorizações florestais do Loteamento Gualtieri, município de Toledo/PR, em atendimento ao termo de compromisso firmado entre as partes. | D8: IAT | E8: Taciana | F8: 45351 | G8: 45380 | H8: =ControladorDeProjetos510[[#This Row],[Estimado Término]]-ControladorDeProjetos510[[#This Row],[Estimado Início]] -> 29 | I8: 45351 | J8: 45352 | K8: =ControladorDeProjetos510[[#This Row],[Real Término]]-ControladorDeProjetos510[[#This Row],[Real Início]] -> 1 | M8: Protocolo aberto para envio dos relatórios de monitoramento.
A9: APRO | B9: PRAD Gualtieri - 10335/2024 | C9: Relatório de conclusão de plantio - Lote Rural nº 26/27.D.1.2, comunidade Dois Irmãos, município de Toledo/PR. | D9: Prefeitura Toledo | E9: Taciana | F9: 45355 | G9: 45392 | H9: =ControladorDeProjetos510[[#This Row],[Estimado Término]]-ControladorDeProjetos510[[#This Row],[Estimado Início]] -> 37 | I9: 45355 | K9: =ControladorDeProjetos510[[#This Row],[Real Término]]-ControladorDeProjetos510[[#This Row],[Real Início]] -> -45355 | L9: 08/03/2024 - ultima atualização | M9: Encaminahdo
A10: APRO | B10: PRAD Gualtieri - 22.004.825-0 | C10: RELATÓRIO DE MONITORAMENTO AMBIENTAL (JANEIRO-MARÇO/2024) EM FACE AO PROJETO DE COMPENSAÇÃO AMBIENTAL IMPLANTADO NO PARQUE DAS ARAUCÁRIAS, NA ÁREA INSTITUCIONAL DOS LOTEAMENTOS IMBUIA E FLORA GALANTE E NO LOTE RURAL No 26/27.D.1, ORIGINADA DAS AUTORIZAÇÕES FLORESTAIS NO LOTEAMENTO GUALTIERI. | D10: IAT | E10: Taciana | F10: 45392 | G10: 45422 | H10: =ControladorDeProjetos510[[#This Row],[Estimado Término]]-ControladorDeProjetos510[[#This Row],[Estimado Início]] -> 30 | I10: 45392 | K10: =ControladorDeProjetos510[[#This Row],[Real Término]]-ControladorDeProjetos510[[#This Row],[Real Início]] -> -45392 | L10: Protocolo aberto pelo Engº Florestal Yuri Guimarães Vieira Coelho | M10: Protocolo aberto para envio dos relatórios de monitoramento.
A11: APRO | B11: PRAD Gualtieri - 17296/2024 | C11: RELATÓRIO DE MONITORAMENTO AMBIENTAL (JANEIRO-MARÇO/2024) EM FACE AO PROJETO DE COMPENSAÇÃO AMBIENTAL IMPLANTADO NO PARQUE DAS ARAUCÁRIAS, NA ÁREA INSTITUCIONAL DOS LOTEAMENTOS IMBUIA E FLORA GALANTE E NO LOTE RURAL Nº 26/27.D.1, ORIGINADA DAS AUTORIZAÇÕES FLORESTAIS NO LOTEAMENTO GUALTIERI. | D11: Prefeitura Toledo | E11: Taciana | F11: 45392 | G11: 45422 | H11: =ControladorDeProjetos510[[#This Row],[Estimado Término]]-ControladorDeProjetos510[[#This Row],[Estimado Início]] -> 30 | I11: 45392 | K11: =ControladorDeProjetos510[[#This Row],[Real Término]]-ControladorDeProjetos510[[#This Row],[Real Início]] -> -45392 | M11: Concluído
A12: CANC | B12: Parque - 20246292364583 | C12: Solicitação de desligamento do padrão provisório | D12: Copel | E12: Taciana | F12: 45405 | G12: 45435 | H12: =ControladorDeProjetos510[[#This Row],[Estimado Término]]-ControladorDeProjetos510[[#This Row],[Estimado Início]] -> 30 | I12: 45405 | K12: =ControladorDeProjetos510[[#This Row],[Real Término]]-ControladorDeProjetos510[[#This Row],[Real Início]] -> -45405 | M12: Encaminhado
A13: APRO | B13: Gualtieri - 20718/2024 | D13: Prefeitura Toledo | E13: Ana Cella | F13: 45414 | G13: 45445 | H13: =ControladorDeProjetos510[[#This Row],[Estimado Término]]-ControladorDeProjetos510[[#This Row],[Estimado Início]] -> 31 | I13: 45414 | K13: =ControladorDeProjetos510[[#This Row],[Real Término]]-ControladorDeProjetos510[[#This Row],[Real Início]] -> -45414 | L13: Acesso pelo CNPJ da Ana Cella | M13: Encaminhado
A14: APRO | B14: Gualtieri - 33480/2024 | C14: Solicitação para setor de cadastro ativar cadastros do loteamento | D14: Prefeitura Toledo | E14: Taciana | F14: 45481 | G14: 45502 | H14: =ControladorDeProjetos510[[#This Row],[Estimado Término]]-ControladorDeProjetos510[[#This Row],[Estimado Início]] -> 21 | I14: 45481 | K14: =ControladorDeProjetos510[[#This Row],[Real Término]]-ControladorDeProjetos510[[#This Row],[Real Início]] -> -45481 | L14: 45502 | M14: Encaminhado
A15: APRO | B15: PRAD GUALTIERI - 22.444.285-8 | C15: 3o RELATÓRIO DE MONITORAMENTO AMBIENTAL (ABRIL-JUNHO/2024) EM FACE AO PROJETO DE COMPENSAÇÃO AMBIENTAL IMPLANTADO NO PARQUE DAS ARAUCÁRIAS, NA ÁREA INSTITUCIONAL DOS LOTEAMENTOS IMBUIA E FLORA GALANTE E NO LOTE RURAL No 26/27.D.1, ORIGINADA DAS AUTORIZAÇÕES FLORESTAIS NO LOTEAMENTO GUALTIERI. | D15: IAT | E15: Taciana | F15: 20258808646103 | G15: 45514 | H15: =ControladorDeProjetos510[[#This Row],[Estimado Término]]-ControladorDeProjetos510[[#This Row],[Estimado Início]] -> -20258808600589 | I15: 45483 | K15: =ControladorDeProjetos510[[#This Row],[Real Término]]-ControladorDeProjetos510[[#This Row],[Real Início]] -> -45483 | L15: Protocolo aberto pelo Engº Florestal Yuri Guimarães Vieira Coelho | M15: Protocolo aberto para envio dos relatórios de monitoramento.
A16: APRO | B16: PRAD GUALTIERI - 34098/2024 | C16: APRESENTAÇÃO DE RELATÓRIO DE MONITORAMENTO DOS PLANTIOS DE MUDAS NATIVAS REFERENTE AO PARQUE DAS ARAUCÁRIAS, À ÁREA INSTITUCIONAL DOS LOTEAMENTOS IMBUIA E FLORA GALANTE E AO LOTE RURAL Nº 26/27.D.1 - PRATI EMPREENDIMENTOS | D16: Prefeitura Toledo | E16: Taciana | F16: 45483 | G16: 45514 | H16: =ControladorDeProjetos510[[#This Row],[Estimado Término]]-ControladorDeProjetos510[[#This Row],[Estimado Início]] -> 31 | I16: 45483 | J16: 45532 | K16: =ControladorDeProjetos510[[#This Row],[Real Término]]-ControladorDeProjetos510[[#This Row],[Real Início]] -> 49 | M16: Concluído
A17: APRO | B17: GUALTIERI -36453 / 2024 | C17: SOLICITA UNIFICAÇÃO E DESMEMBRAMENTO NA QUADRA NÚMERO 59. | D17: Prefeitura Toledo | E17: Taciana | F17: 45498 | G17: 45529 | H17: =ControladorDeProjetos510[[#This Row],[Estimado Término]]-ControladorDeProjetos510[[#This Row],[Estimado Início]] -> 31 | I17: 45498 | J17: 45526 | K17: =ControladorDeProjetos510[[#This Row],[Real Término]]-ControladorDeProjetos510[[#This Row],[Real Início]] -> 28 | M17: Concluído
A18: APRO | B18: GUALTIERI - 37325 / 2024 | C18: SOLICITA UNIFICAÇÃO E DESMEMBRAMENTO NA QUADRA NÚMERO 53, PARTE 1. | D18: Prefeitura Toledo | E18: Taciana | F18: 45503 | G18: 45534 | H18: =ControladorDeProjetos510[[#This Row],[Estimado Término]]-ControladorDeProjetos510[[#This Row],[Estimado Início]] -> 31 | I18: 45503 | K18: =ControladorDeProjetos510[[#This Row],[Real Término]]-ControladorDeProjetos510[[#This Row],[Real Início]] -> -45503 | M18: Concluído
A19: APRO | B19: GUALTIERI - 37328 / 2024 | C19: SOLICITA UNIFICAÇÃO E DESMEMBRAMENTO NA QUADRA NÚMERO 53, PARTE 2. | D19: Prefeitura Toledo | E19: Taciana | F19: 45503 | G19: 45534 | H19: =ControladorDeProjetos510[[#This Row],[Estimado Término]]-ControladorDeProjetos510[[#This Row],[Estimado Início]] -> 31 | I19: 45503 | K19: =ControladorDeProjetos510[[#This Row],[Real Término]]-ControladorDeProjetos510[[#This Row],[Real Início]] -> -45503 | M19: Concluído
A20: APRO | B20: GUALTIERI - 334.797 | C20: REQUERIMENTO DE AVERBAÇÃO DA UNIFICAÇÃO. | D20: Cartório Reg. Imóveis | E20: Taciana | F20: 45511 | G20: 45525 | H20: =ControladorDeProjetos510[[#This Row],[Estimado Término]]-ControladorDeProjetos510[[#This Row],[Estimado Início]] -> 14 | I20: 45511 | J20: 45531 | K20: =ControladorDeProjetos510[[#This Row],[Real Término]]-ControladorDeProjetos510[[#This Row],[Real Início]] -> 20 | M20: Concluído
A21: APRO | B21: GUALTIEIRI - 335.352 | C21: REQUERIMENTO DE AVERBAÇÃO DA UNIFICAÇÃO. | D21: Cartório Reg. Imóveis | E21: Taciana | F21: 45527 | G21: 45541 | H21: =ControladorDeProjetos510[[#This Row],[Estimado Término]]-ControladorDeProjetos510[[#This Row],[Estimado Início]] -> 14 | I21: 45527 | J21: 45562 | K21: =ControladorDeProjetos510[[#This Row],[Real Término]]-ControladorDeProjetos510[[#This Row],[Real Início]] -> 35 | M21: Concluído
A22: APRO | B22: GUALTIEIRI - 335.353 | C22: REQUERIMENTO DE AVERBAÇÃO DO DESMEMBRAMENTO. | D22: Cartório Reg. Imóveis | E22: Taciana | F22: 45527 | G22: 45541 | H22: =ControladorDeProjetos510[[#This Row],[Estimado Término]]-ControladorDeProjetos510[[#This Row],[Estimado Início]] -> 14 | I22: 45527 | J22: 45562 | K22: =ControladorDeProjetos510[[#This Row],[Real Término]]-ControladorDeProjetos510[[#This Row],[Real Início]] -> 35 | M22: Concluído
A23: APRO | B23: GUALTIERI - 44186 / 2024 | C23: RECARIMBAR PARA ATENDER DIRIGÊNCIA DOS PROTOCOLOS 335.352 E 335.353 | D23: Prefeitura Toledo | E23: Taciana | F23: 45544 | G23: 45574 | H23: =ControladorDeProjetos510[[#This Row],[Estimado Término]]-ControladorDeProjetos510[[#This Row],[Estimado Início]] -> 30 | K23: =ControladorDeProjetos510[[#This Row],[Real Término]]-ControladorDeProjetos510[[#This Row],[Real Início]] -> 0 | M23: Concluído
A24: APRO | B24: GUALTIERI - 336.214 / 2024 | C24: Parte 01.1 | D24: Cartório Reg. Imóveis | E24: Taciana | F24: 45552 | G24: 45566 | H24: =ControladorDeProjetos510[[#This Row],[Estimado Término]]-ControladorDeProjetos510[[#This Row],[Estimado Início]] -> 14 | I24: 45552 | J24: 45567 | K24: =ControladorDeProjetos510[[#This Row],[Real Término]]-ControladorDeProjetos510[[#This Row],[Real Início]] -> 15 | M24: Concluído
A25: APRO | B25: GUALTIERI - 336.215 / 2024 | C25: Parte 01.2 | D25: Cartório Reg. Imóveis | E25: Taciana | F25: 45552 | G25: 45566 | H25: =ControladorDeProjetos510[[#This Row],[Estimado Término]]-ControladorDeProjetos510[[#This Row],[Estimado Início]] -> 14 | I25: 45552 | J25: 45567 | K25: =ControladorDeProjetos510[[#This Row],[Real Término]]-ControladorDeProjetos510[[#This Row],[Real Início]] -> 15 | M25: Concluído
A26: CANC | B26: GUALTIERI - 336.216 / 2024 | C26: Parte 02.1 | D26: Cartório Reg. Imóveis | E26: Taciana | F26: 45552 | G26: 45566 | H26: =ControladorDeProjetos510[[#This Row],[Estimado Término]]-ControladorDeProjetos510[[#This Row],[Estimado Início]] -> 14 | I26: 45552 | J26: 45566 | K26: =ControladorDeProjetos510[[#This Row],[Real Término]]-ControladorDeProjetos510[[#This Row],[Real Início]] -> 14 | M26: Cancelado
A27: CANC | B27: GUALTIERI - 336.217 / 2024 | C27: Parte 02.2 | D27: Cartório Reg. Imóveis | E27: Taciana | F27: 45552 | G27: 45566 | H27: =ControladorDeProjetos510[[#This Row],[Estimado Término]]-ControladorDeProjetos510[[#This Row],[Estimado Início]] -> 14 | I27: 45566 | J27: 45566 | K27: =ControladorDeProjetos510[[#This Row],[Real Término]]-ControladorDeProjetos510[[#This Row],[Real Início]] -> 0 | M27: Cancelado
A28: APRO | B28: GUALTIERI - 48772 / 2024 | C28: SOLICITA RECARIMBO AO PROTOCOLO N° 37328/2024 | D28: Prefeitura Toledo | E28: Taciana | F28: 45567 | G28: 45598 | H28: =ControladorDeProjetos510[[#This Row],[Estimado Término]]-ControladorDeProjetos510[[#This Row],[Estimado Início]] -> 31 | I28: 45567 | J28: 45575 | K28: =ControladorDeProjetos510[[#This Row],[Real Término]]-ControladorDeProjetos510[[#This Row],[Real Início]] -> 8 | M28: Concluído
A29: APRO | B29: GUALTIERI - 337.247 / 2024 | C29: Parte 02.1 | D29: Cartório Reg. Imóveis | E29: Taciana | F29: 45582 | G29: 45596 | H29: =ControladorDeProjetos510[[#This Row],[Estimado Término]]-ControladorDeProjetos510[[#This Row],[Estimado Início]] -> 14 | I29: 45583 | J29: 45602 | K29: =ControladorDeProjetos510[[#This Row],[Real Término]]-ControladorDeProjetos510[[#This Row],[Real Início]] -> 19 | M29: Concluído
A30: APRO | B30: GUALTIERI - 337.249 / 2024 | C30: Parte 02.2 | D30: Cartório Reg. Imóveis | E30: Taciana | F30: 45582 | G30: 45596 | H30: =ControladorDeProjetos510[[#This Row],[Estimado Término]]-ControladorDeProjetos510[[#This Row],[Estimado Início]] -> 14 | I30: 45583 | J30: 45602 | K30: =ControladorDeProjetos510[[#This Row],[Real Término]]-ControladorDeProjetos510[[#This Row],[Real Início]] -> 19 | M30: Concluído
